Workbook

Sheet ⚙️ NHẬP VIDEO
A1: 🎬 NHẬP LINK VIDEO ➜ TỰ ĐỘNG THÊM TỪ MỚI
A2: 🔗 LINK VIDEO ▸ dán vào đây | B2: https://www.youtube.com/watch?v=ZSxbxpU_qkM&list=PLSLog43d4VU8hPPOu5rOBvcsmMc9l0ZjY | C2: Dán link YouTube rồi chạy HA_video.bat
A3: 🔢 Số từ mới tối đa | B3: 100 | C3: Lấy N từ có tần suất cao nhất (0 = lấy hết)
A4: ✂️ Số ký tự tối thiểu | B4: 1 | C4: 2 = bỏ từ đơn 1 chữ; 1 = lấy cả từ 1 chữ
A5: 🚫 Bỏ hư từ thông dụng | B5: Có | C5: Có / Không (的, 了, 是, 我…)
A6: 🌐 Ngôn ngữ phụ đề | B6: auto | C6: auto hoặc zh-Hans / zh-TW
A7: 📊 TRẠNG THÁI | B7: ❌ Không tìm được chữ Hán trong video này | C7: Script tự cập nhật sau mỗi lần chạy
A8: 🎞️ Nguồn phụ đề | B8: auto | C8: auto / mota / dan / ocr
A9: 📜 LỊCH SỬ VIDEO ĐÃ XỬ LÝ
A10: 📅 NGÀY | B10: 🎬 VIDEO | C10: 🔗 LINK | D10: 🆕 TỪ MỚI | E10: 🔁 ĐÃ CÓ
A11: 2026-08-02 21:16 | B11: HSK 1–2 | 为什么学了很久还是不会说中文？| Why You Still Can’t Speak Chinese? | C11: ▶ Mở video | D11: 80 | E11: 167
A12: 2026-08-02 21:49 | B12: LẠI MUỐN TĂNG LƯƠNG NỮA SAO? 又要涨工资？ 又要漲工資？ Hoạt hình Tiếng Trung #dahuaxiyou | C12: ▶ Mở video | D12: 16 | E12: 6

Sheet 📋 DÁN PHỤ ĐỀ
A1: 📋 DÁN CHỮ HÁN VÀO ĐÂY (dùng khi video không có phụ đề) | E1: =COUNT(E4:E10485)
A2: Mỗi dòng 1 câu. Chép từ mô tả video / gõ lại chữ trên màn hình. Có lẫn tiếng Việt hay pinyin cũng được — script tự lọc. | E2: =COUNTIF(E4:E4100,E34)
A3: ▼ Bắt đầu dán từ dòng 4 ▼ | C3: 🔊 PINYIN (tự động) | D3: 🇻🇳 TIẾNG VIỆT (tự động, tra từ điển) | E3: date | F3: month | G3: year
A4: 今天公司里他打头很热闹 | C4: {=IF($A4="","",_xlfn.LET(_xlpm.s,$A4,_xlpm.dC,'📚 Từ Vựng HSK'!$C$4:$C$1025,_xlpm.dP,'📚 Từ Vựng HSK'!$D$4:$D$1025,_xlpm.dV,'📚 Từ Vựng HSK'!$E$4:$E$1025,_xlpm.md,1,_xlpm.res,_xlfn.REDUCE("0|",_xlfn.SEQUENCE(LEN(_xlpm.s)),_xlfn.LAMBDA(_xlpm.acc,_xlpm.idx,_xlfn.LET(_xlpm.sk,VALUE(LEFT(_xlpm.acc,FIND("|",_xlpm.acc)-1)),_xlpm.str,MID(_xlpm.acc,FIND("|",_xlpm.acc)+1,9999),IF(_xlpm.sk>0,(_xlpm.sk-1)&"|"&_xlpm.str,_xlfn.LET(_xlpm.ka,MID(_xlpm.s,_xlpm.idx,4),_xlpm.kb,MID(_xlpm.s,_xlpm.idx,3),_xlpm.kc,MID(_xlpm.s,_xlpm.idx,2),_xlpm.kd,MID(_xlpm.s,_xlpm.idx,1),_xlpm.pa,IF(LEN(_xlpm.ka)=4,IFERROR(MATCH(_xlpm.ka,_xlpm.dC,0),0),0),_xlpm.pb,IF(LEN(_xlpm.kb)=3,IFERROR(MATCH(_xlpm.kb,_xlpm.dC,0),0),0),_xlpm.pc,IF(LEN(_xlpm.kc)=2,IFERROR(MATCH(_xlpm.kc,_xlpm.dC,0),0),0),_xlpm.pd,IFERROR(MATCH(_xlpm.kd,_xlpm.dC,0),0),_xlpm.pos,IF(_xlpm.pa>0,_xlpm.pa,IF(_xlpm.pb>0,_xlpm.pb,IF(_xlpm.pc>0,_xlpm.pc,_xlpm.pd))),_xlpm.len,IF(_xlpm.pa>0,4,IF(_xlpm.pb>0,3,IF(_xlpm.pc>0,2,1))),_xlpm.wrd,IF(_xlpm.pos=0,_xlpm.kd,IF(_xlpm.md=1,INDEX(_xlpm.dP,_xlpm.pos),INDEX(_xlpm.dV,_xlpm.pos))),_xlpm.sep,IF(_xlpm.str="","",IF(_xlpm.md=1," "," / ")),(_xlpm.len-1)&"|"&_xlpm.str&_xlpm.sep&_xlpm.wrd))))),MID(_xlpm.res,FIND("|",_xlpm.res)+1,9999)))} | D4: {=IF($A4="","",_xlfn.LET(_xlpm.s,$A4,_xlpm.dC,'📚 Từ Vựng HSK'!$C$4:$C$1025,_xlpm.dP,'📚 Từ Vựng HSK'!$D$4:$D$1025,_xlpm.dV,'📚 Từ Vựng HSK'!$E$4:$E$1025,_xlpm.md,2,_xlpm.res,_xlfn.REDUCE("0|",_xlfn.SEQUENCE(LEN(_xlpm.s)),_xlfn.LAMBDA(_xlpm.acc,_xlpm.idx,_xlfn.LET(_xlpm.sk,VALUE(LEFT(_xlpm.acc,FIND("|",_xlpm.acc)-1)),_xlpm.str,MID(_xlpm.acc,FIND("|",_xlpm.acc)+1,9999),IF(_xlpm.sk>0,(_xlpm.sk-1)&"|"&_xlpm.str,_xlfn.LET(_xlpm.ka,MID(_xlpm.s,_xlpm.idx,4),_xlpm.kb,MID(_xlpm.s,_xlpm.idx,3),_xlpm.kc,MID(_xlpm.s,_xlpm.idx,2),_xlpm.kd,MID(_xlpm.s,_xlpm.idx,1),_xlpm.pa,IF(LEN(_xlpm.ka)=4,IFERROR(MATCH(_xlpm.ka,_xlpm.dC,0),0),0),_xlpm.pb,IF(LEN(_xlpm.kb)=3,IFERROR(MATCH(_xlpm.kb,_xlpm.dC,0),0),0),_xlpm.pc,IF(LEN(_xlpm.kc)=2,IFERROR(MATCH(_xlpm.kc,_xlpm.dC,0),0),0),_xlpm.pd,IFERROR(MATCH(_xlpm.kd,_xlpm.dC,0),0),_xlpm.pos,IF(_xlpm.pa>0,_xlpm.pa,IF(_xlpm.pb>0,_xlpm.pb,IF(_xlpm.pc>0,_xlpm.pc,_xlpm.pd))),_xlpm.len,IF(_xlpm.pa>0,4,IF(_xlpm.pb>0,3,IF(_xlpm.pc>0,2,1))),_xlpm.wrd,IF(_xlpm.pos=0,_xlpm.kd,IF(_xlpm.md=1,INDEX(_xlpm.dP,_xlpm.pos),INDEX(_xlpm.dV,_xlpm.pos))),_xlpm.sep,IF(_xlpm.str="","",IF(_xlpm.md=1," "," / ")),(_xlpm.len-1)&"|"&_xlpm.str&_xlpm.sep&_xlpm.wrd))))),MID(_xlpm.res,FIND("|",_xlpm.res)+1,9999)))} | E4: 46244
A5: 你们 常去 哪 吃 午饭 | C5: {=IF($A5="","",_xlfn.LET(_xlpm.s,$A5,_xlpm.dC,'📚 Từ Vựng HSK'!$C$4:$C$1025,_xlpm.dP,'📚 Từ Vựng HSK'!$D$4:$D$1025,_xlpm.dV,'📚 Từ Vựng HSK'!$E$4:$E$1025,_xlpm.md,1,_xlpm.res,_xlfn.REDUCE("0|",_xlfn.SEQUENCE(LEN(_xlpm.s)),_xlfn.LAMBDA(_xlpm.acc,_xlpm.idx,_xlfn.LET(_xlpm.sk,VALUE(LEFT(_xlpm.acc,FIND("|",_xlpm.acc)-1)),_xlpm.str,MID(_xlpm.acc,FIND("|",_xlpm.acc)+1,9999),IF(_xlpm.sk>0,(_xlpm.sk-1)&"|"&_xlpm.str,_xlfn.LET(_xlpm.ka,MID(_xlpm.s,_xlpm.idx,4),_xlpm.kb,MID(_xlpm.s,_xlpm.idx,3),_xlpm.kc,MID(_xlpm.s,_xlpm.idx,2),_xlpm.kd,MID(_xlpm.s,_xlpm.idx,1),_xlpm.pa,IF(LEN(_xlpm.ka)=4,IFERROR(MATCH(_xlpm.ka,_xlpm.dC,0),0),0),_xlpm.pb,IF(LEN(_xlpm.kb)=3,IFERROR(MATCH(_xlpm.kb,_xlpm.dC,0),0),0),_xlpm.pc,IF(LEN(_xlpm.kc)=2,IFERROR(MATCH(_xlpm.kc,_xlpm.dC,0),0),0),_xlpm.pd,IFERROR(MATCH(_xlpm.kd,_xlpm.dC,0),0),_xlpm.pos,IF(_xlpm.pa>0,_xlpm.pa,IF(_xlpm.pb>0,_xlpm.pb,IF(_xlpm.pc>0,_xlpm.pc,_xlpm.pd))),_xlpm.len,IF(_xlpm.pa>0,4,IF(_xlpm.pb>0,3,IF(_xlpm.pc>0,2,1))),_xlpm.wrd,IF(_xlpm.pos=0,_xlpm.kd,IF(_xlpm.md=1,INDEX(_xlpm.dP,_xlpm.pos),INDEX(_xlpm.dV,_xlpm.pos))),_xlpm.sep,IF(_xlpm.str="","",IF(_xlpm.md=1," "," / ")),(_xlpm.len-1)&"|"&_xlpm.str&_xlpm.sep&_xlpm.wrd))))),MID(_xlpm.res,FIND("|",_xlpm.res)+1,9999)))} | D5: {=IF($A5="","",_xlfn.LET(_xlpm.s,$A5,_xlpm.dC,'📚 Từ Vựng HSK'!$C$4:$C$1025,_xlpm.dP,'📚 Từ Vựng HSK'!$D$4:$D$1025,_xlpm.dV,'📚 Từ Vựng HSK'!$E$4:$E$1025,_xlpm.md,2,_xlpm.res,_xlfn.REDUCE("0|",_xlfn.SEQUENCE(LEN(_xlpm.s)),_xlfn.LAMBDA(_xlpm.acc,_xlpm.idx,_xlfn.LET(_xlpm.sk,VALUE(LEFT(_xlpm.acc,FIND("|",_xlpm.acc)-1)),_xlpm.str,MID(_xlpm.acc,FIND("|",_xlpm.acc)+1,9999),IF(_xlpm.sk>0,(_xlpm.sk-1)&"|"&_xlpm.str,_xlfn.LET(_xlpm.ka,MID(_xlpm.s,_xlpm.idx,4),_xlpm.kb,MID(_xlpm.s,_xlpm.idx,3),_xlpm.kc,MID(_xlpm.s,_xlpm.idx,2),_xlpm.kd,MID(_xlpm.s,_xlpm.idx,1),_xlpm.pa,IF(LEN(_xlpm.ka)=4,IFERROR(MATCH(_xlpm.ka,_xlpm.dC,0),0),0),_xlpm.pb,IF(LEN(_xlpm.kb)=3,IFERROR(MATCH(_xlpm.kb,_xlpm.dC,0),0),0),_xlpm.pc,IF(LEN(_xlpm.kc)=2,IFERROR(MATCH(_xlpm.kc,_xlpm.dC,0),0),0),_xlpm.pd,IFERROR(MATCH(_xlpm.kd,_xlpm.dC,0),0),_xlpm.pos,IF(_xlpm.pa>0,_xlpm.pa,IF(_xlpm.pb>0,_xlpm.pb,IF(_xlpm.pc>0,_xlpm.pc,_xlpm.pd))),_xlpm.len,IF(_xlpm.pa>0,4,IF(_xlpm.pb>0,3,IF(_xlpm.pc>0,2,1))),_xlpm.wrd,IF(_xlpm.pos=0,_xlpm.kd,IF(_xlpm.md=1,INDEX(_xlpm.dP,_xlpm.pos),INDEX(_xlpm.dV,_xlpm.pos))),_xlpm.sep,IF(_xlpm.str="","",IF(_xlpm.md=1," "," / ")),(_xlpm.len-1)&"|"&_xlpm.str&_xlpm.sep&_xlpm.wrd))))),MID(_xlpm.res,FIND("|",_xlpm.res)+1,9999)))} | E5: 46244
A6: 上课的时候你们不能说花 | C6: {=IF($A6="","",_xlfn.LET(_xlpm.s,$A6,_xlpm.dC,'📚 Từ Vựng HSK'!$C$4:$C$1025,_xlpm.dP,'📚 Từ Vựng HSK'!$D$4:$D$1025,_xlpm.dV,'📚 Từ Vựng HSK'!$E$4:$E$1025,_xlpm.md,1,_xlpm.res,_xlfn.REDUCE("0|",_xlfn.SEQUENCE(LEN(_xlpm.s)),_xlfn.LAMBDA(_xlpm.acc,_xlpm.idx,_xlfn.LET(_xlpm.sk,VALUE(LEFT(_xlpm.acc,FIND("|",_xlpm.acc)-1)),_xlpm.str,MID(_xlpm.acc,FIND("|",_xlpm.acc)+1,9999),IF(_xlpm.sk>0,(_xlpm.sk-1)&"|"&_xlpm.str,_xlfn.LET(_xlpm.ka,MID(_xlpm.s,_xlpm.idx,4),_xlpm.kb,MID(_xlpm.s,_xlpm.idx,3),_xlpm.kc,MID(_xlpm.s,_xlpm.idx,2),_xlpm.kd,MID(_xlpm.s,_xlpm.idx,1),_xlpm.pa,IF(LEN(_xlpm.ka)=4,IFERROR(MATCH(_xlpm.ka,_xlpm.dC,0),0),0),_xlpm.pb,IF(LEN(_xlpm.kb)=3,IFERROR(MATCH(_xlpm.kb,_xlpm.dC,0),0),0),_xlpm.pc,IF(LEN(_xlpm.kc)=2,IFERROR(MATCH(_xlpm.kc,_xlpm.dC,0),0),0),_xlpm.pd,IFERROR(MATCH(_xlpm.kd,_xlpm.dC,0),0),_xlpm.pos,IF(_xlpm.pa>0,_xlpm.pa,IF(_xlpm.pb>0,_xlpm.pb,IF(_xlpm.pc>0,_xlpm.pc,_xlpm.pd))),_xlpm.len,IF(_xlpm.pa>0,4,IF(_xlpm.pb>0,3,IF(_xlpm.pc>0,2,1))),_xlpm.wrd,IF(_xlpm.pos=0,_xlpm.kd,IF(_xlpm.md=1,INDEX(_xlpm.dP,_xlpm.pos),INDEX(_xlpm.dV,_xlpm.pos))),_xlpm.sep,IF(_xlpm.str="","",IF(_xlpm.md=1," "," / ")),(_xlpm.len-1)&"|"&_xlpm.str&_xlpm.sep&_xlpm.wrd))))),MID(_xlpm.res,FIND("|",_xlpm.res)+1,9999)))} | D6: {=IF($A6="","",_xlfn.LET(_xlpm.s,$A6,_xlpm.dC,'📚 Từ Vựng HSK'!$C$4:$C$1025,_xlpm.dP,'📚 Từ Vựng HSK'!$D$4:$D$1025,_xlpm.dV,'📚 Từ Vựng HSK'!$E$4:$E$1025,_xlpm.md,2,_xlpm.res,_xlfn.REDUCE("0|",_xlfn.SEQUENCE(LEN(_xlpm.s)),_xlfn.LAMBDA(_xlpm.acc,_xlpm.idx,_xlfn.LET(_xlpm.sk,VALUE(LEFT(_xlpm.acc,FIND("|",_xlpm.acc)-1)),_xlpm.str,MID(_xlpm.acc,FIND("|",_xlpm.acc)+1,9999),IF(_xlpm.sk>0,(_xlpm.sk-1)&"|"&_xlpm.str,_xlfn.LET(_xlpm.ka,MID(_xlpm.s,_xlpm.idx,4),_xlpm.kb,MID(_xlpm.s,_xlpm.idx,3),_xlpm.kc,MID(_xlpm.s,_xlpm.idx,2),_xlpm.kd,MID(_xlpm.s,_xlpm.idx,1),_xlpm.pa,IF(LEN(_xlpm.ka)=4,IFERROR(MATCH(_xlpm.ka,_xlpm.dC,0),0),0),_xlpm.pb,IF(LEN(_xlpm.kb)=3,IFERROR(MATCH(_xlpm.kb,_xlpm.dC,0),0),0),_xlpm.pc,IF(LEN(_xlpm.kc)=2,IFERROR(MATCH(_xlpm.kc,_xlpm.dC,0),0),0),_xlpm.pd,IFERROR(MATCH(_xlpm.kd,_xlpm.dC,0),0),_xlpm.pos,IF(_xlpm.pa>0,_xlpm.pa,IF(_xlpm.pb>0,_xlpm.pb,IF(_xlpm.pc>0,_xlpm.pc,_xlpm.pd))),_xlpm.len,IF(_xlpm.pa>0,4,IF(_xlpm.pb>0,3,IF(_xlpm.pc>0,2,1))),_xlpm.wrd,IF(_xlpm.pos=0,_xlpm.kd,IF(_xlpm.md=1,INDEX(_xlpm.dP,_xlpm.pos),INDEX(_xlpm.dV,_xlpm.pos))),_xlpm.sep,IF(_xlpm.str="","",IF(_xlpm.md=1," "," / ")),(_xlpm.len-1)&"|"&_xlpm.str&_xlpm.sep&_xlpm.wrd))))),MID(_xlpm.res,FIND("|",_xlpm.res)+1,9999)))} | E6: 46244
A7: 今天是第一天我做这个工作 | C7: {=IF($A7="","",_xlfn.LET(_xlpm.s,$A7,_xlpm.dC,'📚 Từ Vựng HSK'!$C$4:$C$1025,_xlpm.dP,'📚 Từ Vựng HSK'!$D$4:$D$1025,_xlpm.dV,'📚 Từ Vựng HSK'!$E$4:$E$1025,_xlpm.md,1,_xlpm.res,_xlfn.REDUCE("0|",_xlfn.SEQUENCE(LEN(_xlpm.s)),_xlfn.LAMBDA(_xlpm.acc,_xlpm.idx,_xlfn.LET(_xlpm.sk,VALUE(LEFT(_xlpm.acc,FIND("|",_xlpm.acc)-1)),_xlpm.str,MID(_xlpm.acc,FIND("|",_xlpm.acc)+1,9999),IF(_xlpm.sk>0,(_xlpm.sk-1)&"|"&_xlpm.str,_xlfn.LET(_xlpm.ka,MID(_xlpm.s,_xlpm.idx,4),_xlpm.kb,MID(_xlpm.s,_xlpm.idx,3),_xlpm.kc,MID(_xlpm.s,_xlpm.idx,2),_xlpm.kd,MID(_xlpm.s,_xlpm.idx,1),_xlpm.pa,IF(LEN(_xlpm.ka)=4,IFERROR(MATCH(_xlpm.ka,_xlpm.dC,0),0),0),_xlpm.pb,IF(LEN(_xlpm.kb)=3,IFERROR(MATCH(_xlpm.kb,_xlpm.dC,0),0),0),_xlpm.pc,IF(LEN(_xlpm.kc)=2,IFERROR(MATCH(_xlpm.kc,_xlpm.dC,0),0),0),_xlpm.pd,IFERROR(MATCH(_xlpm.kd,_xlpm.dC,0),0),_xlpm.pos,IF(_xlpm.pa>0,_xlpm.pa,IF(_xlpm.pb>0,_xlpm.pb,IF(_xlpm.pc>0,_xlpm.pc,_xlpm.pd))),_xlpm.len,IF(_xlpm.pa>0,4,IF(_xlpm.pb>0,3,IF(_xlpm.pc>0,2,1))),_xlpm.wrd,IF(_xlpm.pos=0,_xlpm.kd,IF(_xlpm.md=1,INDEX(_xlpm.dP,_xlpm.pos),INDEX(_xlpm.dV,_xlpm.pos))),_xlpm.sep,IF(_xlpm.str="","",IF(_xlpm.md=1," "," / ")),(_xlpm.len-1)&"|"&_xlpm.str&_xlpm.sep&_xlpm.wrd))))),MID(_xlpm.res,FIND("|",_xlpm.res)+1,9999)))} | D7: {=IF($A7="","",_xlfn.LET(_xlpm.s,$A7,_xlpm.dC,'📚 Từ Vựng HSK'!$C$4:$C$1025,_xlpm.dP,'📚 Từ Vựng HSK'!$D$4:$D$1025,_xlpm.dV,'📚 Từ Vựng HSK'!$E$4:$E$1025,_xlpm.md,2,_xlpm.res,_xlfn.REDUCE("0|",_xlfn.SEQUENCE(LEN(_xlpm.s)),_xlfn.LAMBDA(_xlpm.acc,_xlpm.idx,_xlfn.LET(_xlpm.sk,VALUE(LEFT(_xlpm.acc,FIND("|",_xlpm.acc)-1)),_xlpm.str,MID(_xlpm.acc,FIND("|",_xlpm.acc)+1,9999),IF(_xlpm.sk>0,(_xlpm.sk-1)&"|"&_xlpm.str,_xlfn.LET(_xlpm.ka,MID(_xlpm.s,_xlpm.idx,4),_xlpm.kb,MID(_xlpm.s,_xlpm.idx,3),_xlpm.kc,MID(_xlpm.s,_xlpm.idx,2),_xlpm.kd,MID(_xlpm.s,_xlpm.idx,1),_xlpm.pa,IF(LEN(_xlpm.ka)=4,IFERROR(MATCH(_xlpm.ka,_xlpm.dC,0),0),0),_xlpm.pb,IF(LEN(_xlpm.kb)=3,IFERROR(MATCH(_xlpm.kb,_xlpm.dC,0),0),0),_xlpm.pc,IF(LEN(_xlpm.kc)=2,IFERROR(MATCH(_xlpm.kc,_xlpm.dC,0),0),0),_xlpm.pd,IFERROR(MATCH(_xlpm.kd,_xlpm.dC,0),0),_xlpm.pos,IF(_xlpm.pa>0,_xlpm.pa,IF(_xlpm.pb>0,_xlpm.pb,IF(_xlpm.pc>0,_xlpm.pc,_xlpm.pd))),_xlpm.len,IF(_xlpm.pa>0,4,IF(_xlpm.pb>0,3,IF(_xlpm.pc>0,2,1))),_xlpm.wrd,IF(_xlpm.pos=0,_xlpm.kd,IF(_xlpm.md=1,INDEX(_xlpm.dP,_xlpm.pos),INDEX(_xlpm.dV,_xlpm.pos))),_xlpm.sep,IF(_xlpm.str="","",IF(_xlpm.md=1," "," / ")),(_xlpm.len-1)&"|"&_xlpm.str&_xlpm.sep&_xlpm.wrd))))),MID(_xlpm.res,FIND("|",_xlpm.res)+1,9999)))} | E7: 46244
A8: 这是第几次你们说话 | C8: {=IF($A8="","",_xlfn.LET(_xlpm.s,$A8,_xlpm.dC,'📚 Từ Vựng HSK'!$C$4:$C$1025,_xlpm.dP,'📚 Từ Vựng HSK'!$D$4:$D$1025,_xlpm.dV,'📚 Từ Vựng HSK'!$E$4:$E$1025,_xlpm.md,1,_xlpm.res,_xlfn.REDUCE("0|",_xlfn.SEQUENCE(LEN(_xlpm.s)),_xlfn.LAMBDA(_xlpm.acc,_xlpm.idx,_xlfn.LET(_xlpm.sk,VALUE(LEFT(_xlpm.acc,FIND("|",_xlpm.acc)-1)),_xlpm.str,MID(_xlpm.acc,FIND("|",_xlpm.acc)+1,9999),IF(_xlpm.sk>0,(_xlpm.sk-1)&"|"&_xlpm.str,_xlfn.LET(_xlpm.ka,MID(_xlpm.s,_xlpm.idx,4),_xlpm.kb,MID(_xlpm.s,_xlpm.idx,3),_xlpm.kc,MID(_xlpm.s,_xlpm.idx,2),_xlpm.kd,MID(_xlpm.s,_xlpm.idx,1),_xlpm.pa,IF(LEN(_xlpm.ka)=4,IFERROR(MATCH(_xlpm.ka,_xlpm.dC,0),0),0),_xlpm.pb,IF(LEN(_xlpm.kb)=3,IFERROR(MATCH(_xlpm.kb,_xlpm.dC,0),0),0),_xlpm.pc,IF(LEN(_xlpm.kc)=2,IFERROR(MATCH(_xlpm.kc,_xlpm.dC,0),0),0),_xlpm.pd,IFERROR(MATCH(_xlpm.kd,_xlpm.dC,0),0),_xlpm.pos,IF(_xlpm.pa>0,_xlpm.pa,IF(_xlpm.pb>0,_xlpm.pb,IF(_xlpm.pc>0,_xlpm.pc,_xlpm.pd))),_xlpm.len,IF(_xlpm.pa>0,4,IF(_xlpm.pb>0,3,IF(_xlpm.pc>0,2,1))),_xlpm.wrd,IF(_xlpm.pos=0,_xlpm.kd,IF(_xlpm.md=1,INDEX(_xlpm.dP,_xlpm.pos),INDEX(_xlpm.dV,_xlpm.pos))),_xlpm.sep,IF(_xlpm.str="","",IF(_xlpm.md=1," "," / ")),(_xlpm.len-1)&"|"&_xlpm.str&_xlpm.sep&_xlpm.wrd))))),MID(_xlpm.res,FIND("|",_xlpm.res)+1,9999)))} | D8: {=IF($A8="","",_xlfn.LET(_xlpm.s,$A8,_xlpm.dC,'📚 Từ Vựng HSK'!$C$4:$C$1025,_xlpm.dP,'📚 Từ Vựng HSK'!$D$4:$D$1025,_xlpm.dV,'📚 Từ Vựng HSK'!$E$4:$E$1025,_xlpm.md,2,_xlpm.res,_xlfn.REDUCE("0|",_xlfn.SEQUENCE(LEN(_xlpm.s)),_xlfn.LAMBDA(_xlpm.acc,_xlpm.idx,_xlfn.LET(_xlpm.sk,VALUE(LEFT(_xlpm.acc,FIND("|",_xlpm.acc)-1)),_xlpm.str,MID(_xlpm.acc,FIND("|",_xlpm.acc)+1,9999),IF(_xlpm.sk>0,(_xlpm.sk-1)&"|"&_xlpm.str,_xlfn.LET(_xlpm.ka,MID(_xlpm.s,_xlpm.idx,4),_xlpm.kb,MID(_xlpm.s,_xlpm.idx,3),_xlpm.kc,MID(_xlpm.s,_xlpm.idx,2),_xlpm.kd,MID(_xlpm.s,_xlpm.idx,1),_xlpm.pa,IF(LEN(_xlpm.ka)=4,IFERROR(MATCH(_xlpm.ka,_xlpm.dC,0),0),0),_xlpm.pb,IF(LEN(_xlpm.kb)=3,IFERROR(MATCH(_xlpm.kb,_xlpm.dC,0),0),0),_xlpm.pc,IF(LEN(_xlpm.kc)=2,IFERROR(MATCH(_xlpm.kc,_xlpm.dC,0),0),0),_xlpm.pd,IFERROR(MATCH(_xlpm.kd,_xlpm.dC,0),0),_xlpm.pos,IF(_xlpm.pa>0,_xlpm.pa,IF(_xlpm.pb>0,_xlpm.pb,IF(_xlpm.pc>0,_xlpm.pc,_xlpm.pd))),_xlpm.len,IF(_xlpm.pa>0,4,IF(_xlpm.pb>0,3,IF(_xlpm.pc>0,2,1))),_xlpm.wrd,IF(_xlpm.pos=0,_xlpm.kd,IF(_xlpm.md=1,INDEX(_xlpm.dP,_xlpm.pos),INDEX(_xlpm.dV,_xlpm.pos))),_xlpm.sep,IF(_xlpm.str="","",IF(_xlpm.md=1," "," / ")),(_xlpm.len-1)&"|"&_xlpm.str&_xlpm.sep&_xlpm.wrd))))),MID(_xlpm.res,FIND("|",_xlpm.res)+1,9999)))} | E8: 46244
A9: 你 觉得 汉语 难学吗？ | C9: {=IF($A9="","",_xlfn.LET(_xlpm.s,$A9,_xlpm.dC,'📚 Từ Vựng HSK'!$C$4:$C$1025,_xlpm.dP,'📚 Từ Vựng HSK'!$D$4:$D$1025,_xlpm.dV,'📚 Từ Vựng HSK'!$E$4:$E$1025,_xlpm.md,1,_xlpm.res,_xlfn.REDUCE("0|",_xlfn.SEQUENCE(LEN(_xlpm.s)),_xlfn.LAMBDA(_xlpm.acc,_xlpm.idx,_xlfn.LET(_xlpm.sk,VALUE(LEFT(_xlpm.acc,FIND("|",_xlpm.acc)-1)),_xlpm.str,MID(_xlpm.acc,FIND("|",_xlpm.acc)+1,9999),IF(_xlpm.sk>0,(_xlpm.sk-1)&"|"&_xlpm.str,_xlfn.LET(_xlpm.ka,MID(_xlpm.s,_xlpm.idx,4),_xlpm.kb,MID(_xlpm.s,_xlpm.idx,3),_xlpm.kc,MID(_xlpm.s,_xlpm.idx,2),_xlpm.kd,MID(_xlpm.s,_xlpm.idx,1),_xlpm.pa,IF(LEN(_xlpm.ka)=4,IFERROR(MATCH(_xlpm.ka,_xlpm.dC,0),0),0),_xlpm.pb,IF(LEN(_xlpm.kb)=3,IFERROR(MATCH(_xlpm.kb,_xlpm.dC,0),0),0),_xlpm.pc,IF(LEN(_xlpm.kc)=2,IFERROR(MATCH(_xlpm.kc,_xlpm.dC,0),0),0),_xlpm.pd,IFERROR(MATCH(_xlpm.kd,_xlpm.dC,0),0),_xlpm.pos,IF(_xlpm.pa>0,_xlpm.pa,IF(_xlpm.pb>0,_xlpm.pb,IF(_xlpm.pc>0,_xlpm.pc,_xlpm.pd))),_xlpm.len,IF(_xlpm.pa>0,4,IF(_xlpm.pb>0,3,IF(_xlpm.pc>0,2,1))),_xlpm.wrd,IF(_xlpm.pos=0,_xlpm.kd,IF(_xlpm.md=1,INDEX(_xlpm.dP,_xlpm.pos),INDEX(_xlpm.dV,_xlpm.pos))),_xlpm.sep,IF(_xlpm.str="","",IF(_xlpm.md=1," "," / ")),(_xlpm.len-1)&"|"&_xlpm.str&_xlpm.sep&_xlpm.wrd))))),MID(_xlpm.res,FIND("|",_xlpm.res)+1,9999)))} | D9: {=IF($A9="","",_xlfn.LET(_xlpm.s,$A9,_xlpm.dC,'📚 Từ Vựng HSK'!$C$4:$C$1025,_xlpm.dP,'📚 Từ Vựng HSK'!$D$4:$D$1025,_xlpm.dV,'📚 Từ Vựng HSK'!$E$4:$E$1025,_xlpm.md,2,_xlpm.res,_xlfn.REDUCE("0|",_xlfn.SEQUENCE(LEN(_xlpm.s)),_xlfn.LAMBDA(_xlpm.acc,_xlpm.idx,_xlfn.LET(_xlpm.sk,VALUE(LEFT(_xlpm.acc,FIND("|",_xlpm.acc)-1)),_xlpm.str,MID(_xlpm.acc,FIND("|",_xlpm.acc)+1,9999),IF(_xlpm.sk>0,(_xlpm.sk-1)&"|"&_xlpm.str,_xlfn.LET(_xlpm.ka,MID(_xlpm.s,_xlpm.idx,4),_xlpm.kb,MID(_xlpm.s,_xlpm.idx,3),_xlpm.kc,MID(_xlpm.s,_xlpm.idx,2),_xlpm.kd,MID(_xlpm.s,_xlpm.idx,1),_xlpm.pa,IF(LEN(_xlpm.ka)=4,IFERROR(MATCH(_xlpm.ka,_xlpm.dC,0),0),0),_xlpm.pb,IF(LEN(_xlpm.kb)=3,IFERROR(MATCH(_xlpm.kb,_xlpm.dC,0),0),0),_xlpm.pc,IF(LEN(_xlpm.kc)=2,IFERROR(MATCH(_xlpm.kc,_xlpm.dC,0),0),0),_xlpm.pd,IFERROR(MATCH(_xlpm.kd,_xlpm.dC,0),0),_xlpm.pos,IF(_xlpm.pa>0,_xlpm.pa,IF(_xlpm.pb>0,_xlpm.pb,IF(_xlpm.pc>0,_xlpm.pc,_xlpm.pd))),_xlpm.len,IF(_xlpm.pa>0,4,IF(_xlpm.pb>0,3,IF(_xlpm.pc>0,2,1))),_xlpm.wrd,IF(_xlpm.pos=0,_xlpm.kd,IF(_xlpm.md=1,INDEX(_xlpm.dP,_xlpm.pos),INDEX(_xlpm.dV,_xlpm.pos))),_xlpm.sep,IF(_xlpm.str="","",IF(_xlpm.md=1," "," / ")),(_xlpm.len-1)&"|"&_xlpm.str&_xlpm.sep&_xlpm.wrd))))),MID(_xlpm.res,FIND("|",_xlpm.res)+1,9999)))} | E9: 46244
A10: 这种 要 很男喝 | C10: {=IF($A10="","",_xlfn.LET(_xlpm.s,$A10,_xlpm.dC,'📚 Từ Vựng HSK'!$C$4:$C$1025,_xlpm.dP,'📚 Từ Vựng HSK'!$D$4:$D$1025,_xlpm.dV,'📚 Từ Vựng HSK'!$E$4:$E$1025,_xlpm.md,1,_xlpm.res,_xlfn.REDUCE("0|",_xlfn.SEQUENCE(LEN(_xlpm.s)),_xlfn.LAMBDA(_xlpm.acc,_xlpm.idx,_xlfn.LET(_xlpm.sk,VALUE(LEFT(_xlpm.acc,FIND("|",_xlpm.acc)-1)),_xlpm.str,MID(_xlpm.acc,FIND("|",_xlpm.acc)+1,9999),IF(_xlpm.sk>0,(_xlpm.sk-1)&"|"&_xlpm.str,_xlfn.LET(_xlpm.ka,MID(_xlpm.s,_xlpm.idx,4),_xlpm.kb,MID(_xlpm.s,_xlpm.idx,3),_xlpm.kc,MID(_xlpm.s,_xlpm.idx,2),_xlpm.kd,MID(_xlpm.s,_xlpm.idx,1),_xlpm.pa,IF(LEN(_xlpm.ka)=4,IFERROR(MATCH(_xlpm.ka,_xlpm.dC,0),0),0),_xlpm.pb,IF(LEN(_xlpm.kb)=3,IFERROR(MATCH(_xlpm.kb,_xlpm.dC,0),0),0),_xlpm.pc,IF(LEN(_xlpm.kc)=2,IFERROR(MATCH(_xlpm.kc,_xlpm.dC,0),0),0),_xlpm.pd,IFERROR(MATCH(_xlpm.kd,_xlpm.dC,0),0),_xlpm.pos,IF(_xlpm.pa>0,_xlpm.pa,IF(_xlpm.pb>0,_xlpm.pb,IF(_xlpm.pc>0,_xlpm.pc,_xlpm.pd))),_xlpm.len,IF(_xlpm.pa>0,4,IF(_xlpm.pb>0,3,IF(_xlpm.pc>0,2,1))),_xlpm.wrd,IF(_xlpm.pos=0,_xlpm.kd,IF(_xlpm.md=1,INDEX(_xlpm.dP,_xlpm.pos),INDEX(_xlpm.dV,_xlpm.pos))),_xlpm.sep,IF(_xlpm.str="","",IF(_xlpm.md=1," "," / ")),(_xlpm.len-1)&"|"&_xlpm.str&_xlpm.sep&_xlpm.wrd))))),MID(_xlpm.res,FIND("|",_xlpm.res)+1,9999)))} | D10: {=IF($A10="","",_xlfn.LET(_xlpm.s,$A10,_xlpm.dC,'📚 Từ Vựng HSK'!$C$4:$C$1025,_xlpm.dP,'📚 Từ Vựng HSK'!$D$4:$D$1025,_xlpm.dV,'📚 Từ Vựng HSK'!$E$4:$E$1025,_xlpm.md,2,_xlpm.res,_xlfn.REDUCE("0|",_xlfn.SEQUENCE(LEN(_xlpm.s)),_xlfn.LAMBDA(_xlpm.acc,_xlpm.idx,_xlfn.LET(_xlpm.sk,VALUE(LEFT(_xlpm.acc,FIND("|",_xlpm.acc)-1)),_xlpm.str,MID(_xlpm.acc,FIND("|",_xlpm.acc)+1,9999),IF(_xlpm.sk>0,(_xlpm.sk-1)&"|"&_xlpm.str,_xlfn.LET(_xlpm.ka,MID(_xlpm.s,_xlpm.idx,4),_xlpm.kb,MID(_xlpm.s,_xlpm.idx,3),_xlpm.kc,MID(_xlpm.s,_xlpm.idx,2),_xlpm.kd,MID(_xlpm.s,_xlpm.idx,1),_xlpm.pa,IF(LEN(_xlpm.ka)=4,IFERROR(MATCH(_xlpm.ka,_xlpm.dC,0),0),0),_xlpm.pb,IF(LEN(_xlpm.kb)=3,IFERROR(MATCH(_xlpm.kb,_xlpm.dC,0),0),0),_xlpm.pc,IF(LEN(_xlpm.kc)=2,IFERROR(MATCH(_xlpm.kc,_xlpm.dC,0),0),0),_xlpm.pd,IFERROR(MATCH(_xlpm.kd,_xlpm.dC,0),0),_xlpm.pos,IF(_xlpm.pa>0,_xlpm.pa,IF(_xlpm.pb>0,_xlpm.pb,IF(_xlpm.pc>0,_xlpm.pc,_xlpm.pd))),_xlpm.len,IF(_xlpm.pa>0,4,IF(_xlpm.pb>0,3,IF(_xlpm.pc>0,2,1))),_xlpm.wrd,IF(_xlpm.pos=0,_xlpm.kd,IF(_xlpm.md=1,INDEX(_xlpm.dP,_xlpm.pos),INDEX(_xlpm.dV,_xlpm.pos))),_xlpm.sep,IF(_xlpm.str="","",IF(_xlpm.md=1," "," / ")),(_xlpm.len-1)&"|"&_xlpm.str&_xlpm.sep&_xlpm.wrd))))),MID(_xlpm.res,FIND("|",_xlpm.res)+1,9999)))} | E10: 46244
A11: 最近他学习很进步 | C11: {=IF($A11="","",_xlfn.LET(_xlpm.s,$A11,_xlpm.dC,'📚 Từ Vựng HSK'!$C$4:$C$1025,_xlpm.dP,'📚 Từ Vựng HSK'!$D$4:$D$1025,_xlpm.dV,'📚 Từ Vựng HSK'!$E$4:$E$1025,_xlpm.md,1,_xlpm.res,_xlfn.REDUCE("0|",_xlfn.SEQUENCE(LEN(_xlpm.s)),_xlfn.LAMBDA(_xlpm.acc,_xlpm.idx,_xlfn.LET(_xlpm.sk,VALUE(LEFT(_xlpm.acc,FIND("|",_xlpm.acc)-1)),_xlpm.str,MID(_xlpm.acc,FIND("|",_xlpm.acc)+1,9999),IF(_xlpm.sk>0,(_xlpm.sk-1)&"|"&_xlpm.str,_xlfn.LET(_xlpm.ka,MID(_xlpm.s,_xlpm.idx,4),_xlpm.kb,MID(_xlpm.s,_xlpm.idx,3),_xlpm.kc,MID(_xlpm.s,_xlpm.idx,2),_xlpm.kd,MID(_xlpm.s,_xlpm.idx,1),_xlpm.pa,IF(LEN(_xlpm.ka)=4,IFERROR(MATCH(_xlpm.ka,_xlpm.dC,0),0),0),_xlpm.pb,IF(LEN(_xlpm.kb)=3,IFERROR(MATCH(_xlpm.kb,_xlpm.dC,0),0),0),_xlpm.pc,IF(LEN(_xlpm.kc)=2,IFERROR(MATCH(_xlpm.kc,_xlpm.dC,0),0),0),_xlpm.pd,IFERROR(MATCH(_xlpm.kd,_xlpm.dC,0),0),_xlpm.pos,IF(_xlpm.pa>0,_xlpm.pa,IF(_xlpm.pb>0,_xlpm.pb,IF(_xlpm.pc>0,_xlpm.pc,_xlpm.pd))),_xlpm.len,IF(_xlpm.pa>0,4,IF(_xlpm.pb>0,3,IF(_xlpm.pc>0,2,1))),_xlpm.wrd,IF(_xlpm.pos=0,_xlpm.kd,IF(_xlpm.md=1,INDEX(_xlpm.dP,_xlpm.pos),INDEX(_xlpm.dV,_xlpm.pos))),_xlpm.sep,IF(_xlpm.str="","",IF(_xlpm.md=1," "," / ")),(_xlpm.len-1)&"|"&_xlpm.str&_xlpm.sep&_xlpm.wrd))))),MID(_xlpm.res,FIND("|",_xlpm.res)+1,9999)))} | D11: {=IF($A11="","",_xlfn.LET(_xlpm.s,$A11,_xlpm.dC,'📚 Từ Vựng HSK'!$C$4:$C$1025,_xlpm.dP,'📚 Từ Vựng HSK'!$D$4:$D$1025,_xlpm.dV,'📚 Từ Vựng HSK'!$E$4:$E$1025,_xlpm.md,2,_xlpm.res,_xlfn.REDUCE("0|",_xlfn.SEQUENCE(LEN(_xlpm.s)),_xlfn.LAMBDA(_xlpm.acc,_xlpm.idx,_xlfn.LET(_xlpm.sk,VALUE(LEFT(_xlpm.acc,FIND("|",_xlpm.acc)-1)),_xlpm.str,MID(_xlpm.acc,FIND("|",_xlpm.acc)+1,9999),IF(_xlpm.sk>0,(_xlpm.sk-1)&"|"&_xlpm.str,_xlfn.LET(_xlpm.ka,MID(_xlpm.s,_xlpm.idx,4),_xlpm.kb,MID(_xlpm.s,_xlpm.idx,3),_xlpm.kc,MID(_xlpm.s,_xlpm.idx,2),_xlpm.kd,MID(_xlpm.s,_xlpm.idx,1),_xlpm.pa,IF(LEN(_xlpm.ka)=4,IFERROR(MATCH(_xlpm.ka,_xlpm.dC,0),0),0),_xlpm.pb,IF(LEN(_xlpm.kb)=3,IFERROR(MATCH(_xlpm.kb,_xlpm.dC,0),0),0),_xlpm.pc,IF(LEN(_xlpm.kc)=2,IFERROR(MATCH(_xlpm.kc,_xlpm.dC,0),0),0),_xlpm.pd,IFERROR(MATCH(_xlpm.kd,_xlpm.dC,0),0),_xlpm.pos,IF(_xlpm.pa>0,_xlpm.pa,IF(_xlpm.pb>0,_xlpm.pb,IF(_xlpm.pc>0,_xlpm.pc,_xlpm.pd))),_xlpm.len,IF(_xlpm.pa>0,4,IF(_xlpm.pb>0,3,IF(_xlpm.pc>0,2,1))),_xlpm.wrd,IF(_xlpm.pos=0,_xlpm.kd,IF(_xlpm.md=1,INDEX(_xlpm.dP,_xlpm.pos),INDEX(_xlpm.dV,_xlpm.pos))),_xlpm.sep,IF(_xlpm.str="","",IF(_xlpm.md=1," "," / ")),(_xlpm.len-1)&"|"&_xlpm.str&_xlpm.sep&_xlpm.wrd))))),MID(_xlpm.res,FIND("|",_xlpm.res)+1,9999)))} | E11: 46244
A12: 这个月她没有进步 | C12: {=IF($A12="","",_xlfn.LET(_xlpm.s,$A12,_xlpm.dC,'📚 Từ Vựng HSK'!$C$4:$C$1025,_xlpm.dP,'📚 Từ Vựng HSK'!$D$4:$D$1025,_xlpm.dV,'📚 Từ Vựng HSK'!$E$4:$E$1025,_xlpm.md,1,_xlpm.res,_xlfn.REDUCE("0|",_xlfn.SEQUENCE(LEN(_xlpm.s)),_xlfn.LAMBDA(_xlpm.acc,_xlpm.idx,_xlfn.LET(_xlpm.sk,VALUE(LEFT(_xlpm.acc,FIND("|",_xlpm.acc)-1)),_xlpm.str,MID(_xlpm.acc,FIND("|",_xlpm.acc)+1,9999),IF(_xlpm.sk>0,(_xlpm.sk-1)&"|"&_xlpm.str,_xlfn.LET(_xlpm.ka,MID(_xlpm.s,_xlpm.idx,4),_xlpm.kb,MID(_xlpm.s,_xlpm.idx,3),_xlpm.kc,MID(_xlpm.s,_xlpm.idx,2),_xlpm.kd,MID(_xlpm.s,_xlpm.idx,1),_xlpm.pa,IF(LEN(_xlpm.ka)=4,IFERROR(MATCH(_xlpm.ka,_xlpm.dC,0),0),0),_xlpm.pb,IF(LEN(_xlpm.kb)=3,IFERROR(MATCH(_xlpm.kb,_xlpm.dC,0),0),0),_xlpm.pc,IF(LEN(_xlpm.kc)=2,IFERROR(MATCH(_xlpm.kc,_xlpm.dC,0),0),0),_xlpm.pd,IFERROR(MATCH(_xlpm.kd,_xlpm.dC,0),0),_xlpm.pos,IF(_xlpm.pa>0,_xlpm.pa,IF(_xlpm.pb>0,_xlpm.pb,IF(_xlpm.pc>0,_xlpm.pc,_xlpm.pd))),_xlpm.len,IF(_xlpm.pa>0,4,IF(_xlpm.pb>0,3,IF(_xlpm.pc>0,2,1))),_xlpm.wrd,IF(_xlpm.pos=0,_xlpm.kd,IF(_xlpm.md=1,INDEX(_xlpm.dP,_xlpm.pos),INDEX(_xlpm.dV,_xlpm.pos))),_xlpm.sep,IF(_xlpm.str="","",IF(_xlpm.md=1," "," / ")),(_xlpm.len-1)&"|"&_xlpm.str&_xlpm.sep&_xlpm.wrd))))),MID(_xlpm.res,FIND("|",_xlpm.res)+1,9999)))} | D12: {=IF($A12="","",_xlfn.LET(_xlpm.s,$A12,_xlpm.dC,'📚 Từ Vựng HSK'!$C$4:$C$1025,_xlpm.dP,'📚 Từ Vựng HSK'!$D$4:$D$1025,_xlpm.dV,'📚 Từ Vựng HSK'!$E$4:$E$1025,_xlpm.md,2,_xlpm.res,_xlfn.REDUCE("0|",_xlfn.SEQUENCE(LEN(_xlpm.s)),_xlfn.LAMBDA(_xlpm.acc,_xlpm.idx,_xlfn.LET(_xlpm.sk,VALUE(LEFT(_xlpm.acc,FIND("|",_xlpm.acc)-1)),_xlpm.str,MID(_xlpm.acc,FIND("|",_xlpm.acc)+1,9999),IF(_xlpm.sk>0,(_xlpm.sk-1)&"|"&_xlpm.str,_xlfn.LET(_xlpm.ka,MID(_xlpm.s,_xlpm.idx,4),_xlpm.kb,MID(_xlpm.s,_xlpm.idx,3),_xlpm.kc,MID(_xlpm.s,_xlpm.idx,2),_xlpm.kd,MID(_xlpm.s,_xlpm.idx,1),_xlpm.pa,IF(LEN(_xlpm.ka)=4,IFERROR(MATCH(_xlpm.ka,_xlpm.dC,0),0),0),_xlpm.pb,IF(LEN(_xlpm.kb)=3,IFERROR(MATCH(_xlpm.kb,_xlpm.dC,0),0),0),_xlpm.pc,IF(LEN(_xlpm.kc)=2,IFERROR(MATCH(_xlpm.kc,_xlpm.dC,0),0),0),_xlpm.pd,IFERROR(MATCH(_xlpm.kd,_xlpm.dC,0),0),_xlpm.pos,IF(_xlpm.pa>0,_xlpm.pa,IF(_xlpm.pb>0,_xlpm.pb,IF(_xlpm.pc>0,_xlpm.pc,_xlpm.pd))),_xlpm.len,IF(_xlpm.pa>0,4,IF(_xlpm.pb>0,3,IF(_xlpm.pc>0,2,1))),_xlpm.wrd,IF(_xlpm.pos=0,_xlpm.kd,IF(_xlpm.md=1,INDEX(_xlpm.dP,_xlpm.pos),INDEX(_xlpm.dV,_xlpm.pos))),_xlpm.sep,IF(_xlpm.str="","",IF(_xlpm.md=1," "," / ")),(_xlpm.len-1)&"|"&_xlpm.str&_xlpm.sep&_xlpm.wrd))))),MID(_xlpm.res,FIND("|",_xlpm.res)+1,9999)))} | E12: 46244
A13: 你们 要努力学汉语 | C13: {=IF($A13="","",_xlfn.LET(_xlpm.s,$A13,_xlpm.dC,'📚 Từ Vựng HSK'!$C$4:$C$1025,_xlpm.dP,'📚 Từ Vựng HSK'!$D$4:$D$1025,_xlpm.dV,'📚 Từ Vựng HSK'!$E$4:$E$1025,_xlpm.md,1,_xlpm.res,_xlfn.REDUCE("0|",_xlfn.SEQUENCE(LEN(_xlpm.s)),_xlfn.LAMBDA(_xlpm.acc,_xlpm.idx,_xlfn.LET(_xlpm.sk,VALUE(LEFT(_xlpm.acc,FIND("|",_xlpm.acc)-1)),_xlpm.str,MID(_xlpm.acc,FIND("|",_xlpm.acc)+1,9999),IF(_xlpm.sk>0,(_xlpm.sk-1)&"|"&_xlpm.str,_xlfn.LET(_xlpm.ka,MID(_xlpm.s,_xlpm.idx,4),_xlpm.kb,MID(_xlpm.s,_xlpm.idx,3),_xlpm.kc,MID(_xlpm.s,_xlpm.idx,2),_xlpm.kd,MID(_xlpm.s,_xlpm.idx,1),_xlpm.pa,IF(LEN(_xlpm.ka)=4,IFERROR(MATCH(_xlpm.ka,_xlpm.dC,0),0),0),_xlpm.pb,IF(LEN(_xlpm.kb)=3,IFERROR(MATCH(_xlpm.kb,_xlpm.dC,0),0),0),_xlpm.pc,IF(LEN(_xlpm.kc)=2,IFERROR(MATCH(_xlpm.kc,_xlpm.dC,0),0),0),_xlpm.pd,IFERROR(MATCH(_xlpm.kd,_xlpm.dC,0),0),_xlpm.pos,IF(_xlpm.pa>0,_xlpm.pa,IF(_xlpm.pb>0,_xlpm.pb,IF(_xlpm.pc>0,_xlpm.pc,_xlpm.pd))),_xlpm.len,IF(_xlpm.pa>0,4,IF(_xlpm.pb>0,3,IF(_xlpm.pc>0,2,1))),_xlpm.wrd,IF(_xlpm.pos=0,_xlpm.kd,IF(_xlpm.md=1,INDEX(_xlpm.dP,_xlpm.pos),INDEX(_xlpm.dV,_xlpm.pos))),_xlpm.sep,IF(_xlpm.str="","",IF(_xlpm.md=1," "," / ")),(_xlpm.len-1)&"|"&_xlpm.str&_xlpm.sep&_xlpm.wrd))))),MID(_xlpm.res,FIND("|",_xlpm.res)+1,9999)))} | D13: {=IF($A13="","",_xlfn.LET(_xlpm.s,$A13,_xlpm.dC,'📚 Từ Vựng HSK'!$C$4:$C$1025,_xlpm.dP,'📚 Từ Vựng HSK'!$D$4:$D$1025,_xlpm.dV,'📚 Từ Vựng HSK'!$E$4:$E$1025,_xlpm.md,2,_xlpm.res,_xlfn.REDUCE("0|",_xlfn.SEQUENCE(LEN(_xlpm.s)),_xlfn.LAMBDA(_xlpm.acc,_xlpm.idx,_xlfn.LET(_xlpm.sk,VALUE(LEFT(_xlpm.acc,FIND("|",_xlpm.acc)-1)),_xlpm.str,MID(_xlpm.acc,FIND("|",_xlpm.acc)+1,9999),IF(_xlpm.sk>0,(_xlpm.sk-1)&"|"&_xlpm.str,_xlfn.LET(_xlpm.ka,MID(_xlpm.s,_xlpm.idx,4),_xlpm.kb,MID(_xlpm.s,_xlpm.idx,3),_xlpm.kc,MID(_xlpm.s,_xlpm.idx,2),_xlpm.kd,MID(_xlpm.s,_xlpm.idx,1),_xlpm.pa,IF(LEN(_xlpm.ka)=4,IFERROR(MATCH(_xlpm.ka,_xlpm.dC,0),0),0),_xlpm.pb,IF(LEN(_xlpm.kb)=3,IFERROR(MATCH(_xlpm.kb,_xlpm.dC,0),0),0),_xlpm.pc,IF(LEN(_xlpm.kc)=2,IFERROR(MATCH(_xlpm.kc,_xlpm.dC,0),0),0),_xlpm.pd,IFERROR(MATCH(_xlpm.kd,_xlpm.dC,0),0),_xlpm.pos,IF(_xlpm.pa>0,_xlpm.pa,IF(_xlpm.pb>0,_xlpm.pb,IF(_xlpm.pc>0,_xlpm.pc,_xlpm.pd))),_xlpm.len,IF(_xlpm.pa>0,4,IF(_xlpm.pb>0,3,IF(_xlpm.pc>0,2,1))),_xlpm.wrd,IF(_xlpm.pos=0,_xlpm.kd,IF(_xlpm.md=1,INDEX(_xlpm.dP,_xlpm.pos),INDEX(_xlpm.dV,_xlpm.pos))),_xlpm.sep,IF(_xlpm.str="","",IF(_xlpm.md=1," "," / ")),(_xlpm.len-1)&"|"&_xlpm.str&_xlpm.sep&_xlpm.wrd))))),MID(_xlpm.res,FIND("|",_xlpm.res)+1,9999)))} | E13: 46244
A14: 如果不努力工作 | C14: {=IF($A14="","",_xlfn.LET(_xlpm.s,$A14,_xlpm.dC,'📚 Từ Vựng HSK'!$C$4:$C$1025,_xlpm.dP,'📚 Từ Vựng HSK'!$D$4:$D$1025,_xlpm.dV,'📚 Từ Vựng HSK'!$E$4:$E$1025,_xlpm.md,1,_xlpm.res,_xlfn.REDUCE("0|",_xlfn.SEQUENCE(LEN(_xlpm.s)),_xlfn.LAMBDA(_xlpm.acc,_xlpm.idx,_xlfn.LET(_xlpm.sk,VALUE(LEFT(_xlpm.acc,FIND("|",_xlpm.acc)-1)),_xlpm.str,MID(_xlpm.acc,FIND("|",_xlpm.acc)+1,9999),IF(_xlpm.sk>0,(_xlpm.sk-1)&"|"&_xlpm.str,_xlfn.LET(_xlpm.ka,MID(_xlpm.s,_xlpm.idx,4),_xlpm.kb,MID(_xlpm.s,_xlpm.idx,3),_xlpm.kc,MID(_xlpm.s,_xlpm.idx,2),_xlpm.kd,MID(_xlpm.s,_xlpm.idx,1),_xlpm.pa,IF(LEN(_xlpm.ka)=4,IFERROR(MATCH(_xlpm.ka,_xlpm.dC,0),0),0),_xlpm.pb,IF(LEN(_xlpm.kb)=3,IFERROR(MATCH(_xlpm.kb,_xlpm.dC,0),0),0),_xlpm.pc,IF(LEN(_xlpm.kc)=2,IFERROR(MATCH(_xlpm.kc,_xlpm.dC,0),0),0),_xlpm.pd,IFERROR(MATCH(_xlpm.kd,_xlpm.dC,0),0),_xlpm.pos,IF(_xlpm.pa>0,_xlpm.pa,IF(_xlpm.pb>0,_xlpm.pb,IF(_xlpm.pc>0,_xlpm.pc,_xlpm.pd))),_xlpm.len,IF(_xlpm.pa>0,4,IF(_xlpm.pb>0,3,IF(_xlpm.pc>0,2,1))),_xlpm.wrd,IF(_xlpm.pos=0,_xlpm.kd,IF(_xlpm.md=1,INDEX(_xlpm.dP,_xlpm.pos),INDEX(_xlpm.dV,_xlpm.pos))),_xlpm.sep,IF(_xlpm.str="","",IF(_xlpm.md=1," "," / ")),(_xlpm.len-1)&"|"&_xlpm.str&_xlpm.sep&_xlpm.wrd))))),MID(_xlpm.res,FIND("|",_xlpm.res)+1,9999)))} | D14: {=IF($A14="","",_xlfn.LET(_xlpm.s,$A14,_xlpm.dC,'📚 Từ Vựng HSK'!$C$4:$C$1025,_xlpm.dP,'📚 Từ Vựng HSK'!$D$4:$D$1025,_xlpm.dV,'📚 Từ Vựng HSK'!$E$4:$E$1025,_xlpm.md,2,_xlpm.res,_xlfn.REDUCE("0|",_xlfn.SEQUENCE(LEN(_xlpm.s)),_xlfn.LAMBDA(_xlpm.acc,_xlpm.idx,_xlfn.LET(_xlpm.sk,VALUE(LEFT(_xlpm.acc,FIND("|",_xlpm.acc)-1)),_xlpm.str,MID(_xlpm.acc,FIND("|",_xlpm.acc)+1,9999),IF(_xlpm.sk>0,(_xlpm.sk-1)&"|"&_xlpm.str,_xlfn.LET(_xlpm.ka,MID(_xlpm.s,_xlpm.idx,4),_xlpm.kb,MID(_xlpm.s,_xlpm.idx,3),_xlpm.kc,MID(_xlpm.s,_xlpm.idx,2),_xlpm.kd,MID(_xlpm.s,_xlpm.idx,1),_xlpm.pa,IF(LEN(_xlpm.ka)=4,IFERROR(MATCH(_xlpm.ka,_xlpm.dC,0),0),0),_xlpm.pb,IF(LEN(_xlpm.kb)=3,IFERROR(MATCH(_xlpm.kb,_xlpm.dC,0),0),0),_xlpm.pc,IF(LEN(_xlpm.kc)=2,IFERROR(MATCH(_xlpm.kc,_xlpm.dC,0),0),0),_xlpm.pd,IFERROR(MATCH(_xlpm.kd,_xlpm.dC,0),0),_xlpm.pos,IF(_xlpm.pa>0,_xlpm.pa,IF(_xlpm.pb>0,_xlpm.pb,IF(_xlpm.pc>0,_xlpm.pc,_xlpm.pd))),_xlpm.len,IF(_xlpm.pa>0,4,IF(_xlpm.pb>0,3,IF(_xlpm.pc>0,2,1))),_xlpm.wrd,IF(_xlpm.pos=0,_xlpm.kd,IF(_xlpm.md=1,INDEX(_xlpm.dP,_xlpm.pos),INDEX(_xlpm.dV,_xlpm.pos))),_xlpm.sep,IF(_xlpm.str="","",IF(_xlpm.md=1," "," / ")),(_xlpm.len-1)&"|"&_xlpm.str&_xlpm.sep&_xlpm.wrd))))),MID(_xlpm.res,FIND("|",_xlpm.res)+1,9999)))} | E14: 46244
A15: 你们的老师的发音很准 | C15: {=IF($A15="","",_xlfn.LET(_xlpm.s,$A15,_xlpm.dC,'📚 Từ Vựng HSK'!$C$4:$C$1025,_xlpm.dP,'📚 Từ Vựng HSK'!$D$4:$D$1025,_xlpm.dV,'📚 Từ Vựng HSK'!$E$4:$E$1025,_xlpm.md,1,_xlpm.res,_xlfn.REDUCE("0|",_xlfn.SEQUENCE(LEN(_xlpm.s)),_xlfn.LAMBDA(_xlpm.acc,_xlpm.idx,_xlfn.LET(_xlpm.sk,VALUE(LEFT(_xlpm.acc,FIND("|",_xlpm.acc)-1)),_xlpm.str,MID(_xlpm.acc,FIND("|",_xlpm.acc)+1,9999),IF(_xlpm.sk>0,(_xlpm.sk-1)&"|"&_xlpm.str,_xlfn.LET(_xlpm.ka,MID(_xlpm.s,_xlpm.idx,4),_xlpm.kb,MID(_xlpm.s,_xlpm.idx,3),_xlpm.kc,MID(_xlpm.s,_xlpm.idx,2),_xlpm.kd,MID(_xlpm.s,_xlpm.idx,1),_xlpm.pa,IF(LEN(_xlpm.ka)=4,IFERROR(MATCH(_xlpm.ka,_xlpm.dC,0),0),0),_xlpm.pb,IF(LEN(_xlpm.kb)=3,IFERROR(MATCH(_xlpm.kb,_xlpm.dC,0),0),0),_xlpm.pc,IF(LEN(_xlpm.kc)=2,IFERROR(MATCH(_xlpm.kc,_xlpm.dC,0),0),0),_xlpm.pd,IFERROR(MATCH(_xlpm.kd,_xlpm.dC,0),0),_xlpm.pos,IF(_xlpm.pa>0,_xlpm.pa,IF(_xlpm.pb>0,_xlpm.pb,IF(_xlpm.pc>0,_xlpm.pc,_xlpm.pd))),_xlpm.len,IF(_xlpm.pa>0,4,IF(_xlpm.pb>0,3,IF(_xlpm.pc>0,2,1))),_xlpm.wrd,IF(_xlpm.pos=0,_xlpm.kd,IF(_xlpm.md=1,INDEX(_xlpm.dP,_xlpm.pos),INDEX(_xlpm.dV,_xlpm.pos))),_xlpm.sep,IF(_xlpm.str="","",IF(_xlpm.md=1," "," / ")),(_xlpm.len-1)&"|"&_xlpm.str&_xlpm.sep&_xlpm.wrd))))),MID(_xlpm.res,FIND("|",_xlpm.res)+1,9999)))} | D15: {=IF($A15="","",_xlfn.LET(_xlpm.s,$A15,_xlpm.dC,'📚 Từ Vựng HSK'!$C$4:$C$1025,_xlpm.dP,'📚 Từ Vựng HSK'!$D$4:$D$1025,_xlpm.dV,'📚 Từ Vựng HSK'!$E$4:$E$1025,_xlpm.md,2,_xlpm.res,_xlfn.REDUCE("0|",_xlfn.SEQUENCE(LEN(_xlpm.s)),_xlfn.LAMBDA(_xlpm.acc,_xlpm.idx,_xlfn.LET(_xlpm.sk,VALUE(LEFT(_xlpm.acc,FIND("|",_xlpm.acc)-1)),_xlpm.str,MID(_xlpm.acc,FIND("|",_xlpm.acc)+1,9999),IF(_xlpm.sk>0,(_xlpm.sk-1)&"|"&_xlpm.str,_xlfn.LET(_xlpm.ka,MID(_xlpm.s,_xlpm.idx,4),_xlpm.kb,MID(_xlpm.s,_xlpm.idx,3),_xlpm.kc,MID(_xlpm.s,_xlpm.idx,2),_xlpm.kd,MID(_xlpm.s,_xlpm.idx,1),_xlpm.pa,IF(LEN(_xlpm.ka)=4,IFERROR(MATCH(_xlpm.ka,_xlpm.dC,0),0),0),_xlpm.pb,IF(LEN(_xlpm.kb)=3,IFERROR(MATCH(_xlpm.kb,_xlpm.dC,0),0),0),_xlpm.pc,IF(LEN(_xlpm.kc)=2,IFERROR(MATCH(_xlpm.kc,_xlpm.dC,0),0),0),_xlpm.pd,IFERROR(MATCH(_xlpm.kd,_xlpm.dC,0),0),_xlpm.pos,IF(_xlpm.pa>0,_xlpm.pa,IF(_xlpm.pb>0,_xlpm.pb,IF(_xlpm.pc>0,_xlpm.pc,_xlpm.pd))),_xlpm.len,IF(_xlpm.pa>0,4,IF(_xlpm.pb>0,3,IF(_xlpm.pc>0,2,1))),_xlpm.wrd,IF(_xlpm.pos=0,_xlpm.kd,IF(_xlpm.md=1,INDEX(_xlpm.dP,_xlpm.pos),INDEX(_xlpm.dV,_xlpm.pos))),_xlpm.sep,IF(_xlpm.str="","",IF(_xlpm.md=1," "," / ")),(_xlpm.len-1)&"|"&_xlpm.str&_xlpm.sep&_xlpm.wrd))))),MID(_xlpm.res,FIND("|",_xlpm.res)+1,9999)))} | E15: 46244
... A63: 你可以上网叫电话费 | C63: {=IF($A63="","",_xlfn.LET(_xlpm.s,$A63,_xlpm.dC,'📚 Từ Vựng HSK'!$C$4:$C$1025,_xlpm.dP,'📚 Từ Vựng HSK'!$D$4:$D$1025,_xlpm.dV,'📚 Từ Vựng HSK'!$E$4:$E$1025,_xlpm.md,1,_xlpm.res,_xlfn.REDUCE("0|",_xlfn.SEQUENCE(LEN(_xlpm.s)),_xlfn.LAMBDA(_xlpm.acc,_xlpm.idx,_xlfn.LET(_xlpm.sk,VALUE(LEFT(_xlpm.acc,FIND("|",_xlpm.acc)-1)),_xlpm.str,MID(_xlpm.acc,FIND("|",_xlpm.acc)+1,9999),IF(_xlpm.sk>0,(_xlpm.sk-1)&"|"&_xlpm.str,_xlfn.LET(_xlpm.ka,MID(_xlpm.s,_xlpm.idx,4),_xlpm.kb,MID(_xlpm.s,_xlpm.idx,3),_xlpm.kc,MID(_xlpm.s,_xlpm.idx,2),_xlpm.kd,MID(_xlpm.s,_xlpm.idx,1),_xlpm.pa,IF(LEN(_xlpm.ka)=4,IFERROR(MATCH(_xlpm.ka,_xlpm.dC,0),0),0),_xlpm.pb,IF(LEN(_xlpm.kb)=3,IFERROR(MATCH(_xlpm.kb,_xlpm.dC,0),0),0),_xlpm.pc,IF(LEN(_xlpm.kc)=2,IFERROR(MATCH(_xlpm.kc,_xlpm.dC,0),0),0),_xlpm.pd,IFERROR(MATCH(_xlpm.kd,_xlpm.dC,0),0),_xlpm.pos,IF(_xlpm.pa>0,_xlpm.pa,IF(_xlpm.pb>0,_xlpm.pb,IF(_xlpm.pc>0,_xlpm.pc,_xlpm.pd))),_xlpm.len,IF(_xlpm.pa>0,4,IF(_xlpm.pb>0,3,IF(_xlpm.pc>0,2,1))),_xlpm.wrd,IF(_xlpm.pos=0,_xlpm.kd,IF(_xlpm.md=1,INDEX(_xlpm.dP,_xlpm.pos),INDEX(_xlpm.dV,_xlpm.pos))),_xlpm.sep,IF(_xlpm.str="","",IF(_xlpm.md=1," "," / ")),(_xlpm.len-1)&"|"&_xlpm.str&_xlpm.sep&_xlpm.wrd))))),MID(_xlpm.res,FIND("|",_xlpm.res)+1,9999)))} | D63: {=IF($A63="","",_xlfn.LET(_xlpm.s,$A63,_xlpm.dC,'📚 Từ Vựng HSK'!$C$4:$C$1025,_xlpm.dP,'📚 Từ Vựng HSK'!$D$4:$D$1025,_xlpm.dV,'📚 Từ Vựng HSK'!$E$4:$E$1025,_xlpm.md,2,_xlpm.res,_xlfn.REDUCE("0|",_xlfn.SEQUENCE(LEN(_xlpm.s)),_xlfn.LAMBDA(_xlpm.acc,_xlpm.idx,_xlfn.LET(_xlpm.sk,VALUE(LEFT(_xlpm.acc,FIND("|",_xlpm.acc)-1)),_xlpm.str,MID(_xlpm.acc,FIND("|",_xlpm.acc)+1,9999),IF(_xlpm.sk>0,(_xlpm.sk-1)&"|"&_xlpm.str,_xlfn.LET(_xlpm.ka,MID(_xlpm.s,_xlpm.idx,4),_xlpm.kb,MID(_xlpm.s,_xlpm.idx,3),_xlpm.kc,MID(_xlpm.s,_xlpm.idx,2),_xlpm.kd,MID(_xlpm.s,_xlpm.idx,1),_xlpm.pa,IF(LEN(_xlpm.ka)=4,IFERROR(MATCH(_xlpm.ka,_xlpm.dC,0),0),0),_xlpm.pb,IF(LEN(_xlpm.kb)=3,IFERROR(MATCH(_xlpm.kb,_xlpm.dC,0),0),0),_xlpm.pc,IF(LEN(_xlpm.kc)=2,IFERROR(MATCH(_xlpm.kc,_xlpm.dC,0),0),0),_xlpm.pd,IFERROR(MATCH(_xlpm.kd,_xlpm.dC,0),0),_xlpm.pos,IF(_xlpm.pa>0,_xlpm.pa,IF(_xlpm.pb>0,_xlpm.pb,IF(_xlpm.pc>0,_xlpm.pc,_xlpm.pd))),_xlpm.len,IF(_xlpm.pa>0,4,IF(_xlpm.pb>0,3,IF(_xlpm.pc>0,2,1))),_xlpm.wrd,IF(_xlpm.pos=0,_xlpm.kd,IF(_xlpm.md=1,INDEX(_xlpm.dP,_xlpm.pos),INDEX(_xlpm.dV,_xlpm.pos))),_xlpm.sep,IF(_xlpm.str="","",IF(_xlpm.md=1," "," / ")),(_xlpm.len-1)&"|"&_xlpm.str&_xlpm.sep&_xlpm.wrd))))),MID(_xlpm.res,FIND("|",_xlpm.res)+1,9999)))} | E63: 46245
C64: {=IF($A64="","",_xlfn.LET(_xlpm.s,$A64,_xlpm.dC,'📚 Từ Vựng HSK'!$C$4:$C$1025,_xlpm.dP,'📚 Từ Vựng HSK'!$D$4:$D$1025,_xlpm.dV,'📚 Từ Vựng HSK'!$E$4:$E$1025,_xlpm.md,1,_xlpm.res,_xlfn.REDUCE("0|",_xlfn.SEQUENCE(LEN(_xlpm.s)),_xlfn.LAMBDA(_xlpm.acc,_xlpm.idx,_xlfn.LET(_xlpm.sk,VALUE(LEFT(_xlpm.acc,FIND("|",_xlpm.acc)-1)),_xlpm.str,MID(_xlpm.acc,FIND("|",_xlpm.acc)+1,9999),IF(_xlpm.sk>0,(_xlpm.sk-1)&"|"&_xlpm.str,_xlfn.LET(_xlpm.ka,MID(_xlpm.s,_xlpm.idx,4),_xlpm.kb,MID(_xlpm.s,_xlpm.idx,3),_xlpm.kc,MID(_xlpm.s,_xlpm.idx,2),_xlpm.kd,MID(_xlpm.s,_xlpm.idx,1),_xlpm.pa,IF(LEN(_xlpm.ka)=4,IFERROR(MATCH(_xlpm.ka,_xlpm.dC,0),0),0),_xlpm.pb,IF(LEN(_xlpm.kb)=3,IFERROR(MATCH(_xlpm.kb,_xlpm.dC,0),0),0),_xlpm.pc,IF(LEN(_xlpm.kc)=2,IFERROR(MATCH(_xlpm.kc,_xlpm.dC,0),0),0),_xlpm.pd,IFERROR(MATCH(_xlpm.kd,_xlpm.dC,0),0),_xlpm.pos,IF(_xlpm.pa>0,_xlpm.pa,IF(_xlpm.pb>0,_xlpm.pb,IF(_xlpm.pc>0,_xlpm.pc,_xlpm.pd))),_xlpm.len,IF(_xlpm.pa>0,4,IF(_xlpm.pb>0,3,IF(_xlpm.pc>0,2,1))),_xlpm.wrd,IF(_xlpm.pos=0,_xlpm.kd,IF(_xlpm.md=1,INDEX(_xlpm.dP,_xlpm.pos),INDEX(_xlpm.dV,_xlpm.pos))),_xlpm.sep,IF(_xlpm.str="","",IF(_xlpm.md=1," "," / ")),(_xlpm.len-1)&"|"&_xlpm.str&_xlpm.sep&_xlpm.wrd))))),MID(_xlpm.res,FIND("|",_xlpm.res)+1,9999)))} | D64: {=IF($A64="","",_xlfn.LET(_xlpm.s,$A64,_xlpm.dC,'📚 Từ Vựng HSK'!$C$4:$C$1025,_xlpm.dP,'📚 Từ Vựng HSK'!$D$4:$D$1025,_xlpm.dV,'📚 Từ Vựng HSK'!$E$4:$E$1025,_xlpm.md,2,_xlpm.res,_xlfn.REDUCE("0|",_xlfn.SEQUENCE(LEN(_xlpm.s)),_xlfn.LAMBDA(_xlpm.acc,_xlpm.idx,_xlfn.LET(_xlpm.sk,VALUE(LEFT(_xlpm.acc,FIND("|",_xlpm.acc)-1)),_xlpm.str,MID(_xlpm.acc,FIND("|",_xlpm.acc)+1,9999),IF(_xlpm.sk>0,(_xlpm.sk-1)&"|"&_xlpm.str,_xlfn.LET(_xlpm.ka,MID(_xlpm.s,_xlpm.idx,4),_xlpm.kb,MID(_xlpm.s,_xlpm.idx,3),_xlpm.kc,MID(_xlpm.s,_xlpm.idx,2),_xlpm.kd,MID(_xlpm.s,_xlpm.idx,1),_xlpm.pa,IF(LEN(_xlpm.ka)=4,IFERROR(MATCH(_xlpm.ka,_xlpm.dC,0),0),0),_xlpm.pb,IF(LEN(_xlpm.kb)=3,IFERROR(MATCH(_xlpm.kb,_xlpm.dC,0),0),0),_xlpm.pc,IF(LEN(_xlpm.kc)=2,IFERROR(MATCH(_xlpm.kc,_xlpm.dC,0),0),0),_xlpm.pd,IFERROR(MATCH(_xlpm.kd,_xlpm.dC,0),0),_xlpm.pos,IF(_xlpm.pa>0,_xlpm.pa,IF(_xlpm.pb>0,_xlpm.pb,IF(_xlpm.pc>0,_xlpm.pc,_xlpm.pd))),_xlpm.len,IF(_xlpm.pa>0,4,IF(_xlpm.pb>0,3,IF(_xlpm.pc>0,2,1))),_xlpm.wrd,IF(_xlpm.pos=0,_xlpm.kd,IF(_xlpm.md=1,INDEX(_xlpm.dP,_xlpm.pos),INDEX(_xlpm.dV,_xlpm.pos))),_xlpm.sep,IF(_xlpm.str="","",IF(_xlpm.md=1," "," / ")),(_xlpm.len-1)&"|"&_xlpm.str&_xlpm.sep&_xlpm.wrd))))),MID(_xlpm.res,FIND("|",_xlpm.res)+1,9999)))}
C65: {=IF($A65="","",_xlfn.LET(_xlpm.s,$A65,_xlpm.dC,'📚 Từ Vựng HSK'!$C$4:$C$1025,_xlpm.dP,'📚 Từ Vựng HSK'!$D$4:$D$1025,_xlpm.dV,'📚 Từ Vựng HSK'!$E$4:$E$1025,_xlpm.md,1,_xlpm.res,_xlfn.REDUCE("0|",_xlfn.SEQUENCE(LEN(_xlpm.s)),_xlfn.LAMBDA(_xlpm.acc,_xlpm.idx,_xlfn.LET(_xlpm.sk,VALUE(LEFT(_xlpm.acc,FIND("|",_xlpm.acc)-1)),_xlpm.str,MID(_xlpm.acc,FIND("|",_xlpm.acc)+1,9999),IF(_xlpm.sk>0,(_xlpm.sk-1)&"|"&_xlpm.str,_xlfn.LET(_xlpm.ka,MID(_xlpm.s,_xlpm.idx,4),_xlpm.kb,MID(_xlpm.s,_xlpm.idx,3),_xlpm.kc,MID(_xlpm.s,_xlpm.idx,2),_xlpm.kd,MID(_xlpm.s,_xlpm.idx,1),_xlpm.pa,IF(LEN(_xlpm.ka)=4,IFERROR(MATCH(_xlpm.ka,_xlpm.dC,0),0),0),_xlpm.pb,IF(LEN(_xlpm.kb)=3,IFERROR(MATCH(_xlpm.kb,_xlpm.dC,0),0),0),_xlpm.pc,IF(LEN(_xlpm.kc)=2,IFERROR(MATCH(_xlpm.kc,_xlpm.dC,0),0),0),_xlpm.pd,IFERROR(MATCH(_xlpm.kd,_xlpm.dC,0),0),_xlpm.pos,IF(_xlpm.pa>0,_xlpm.pa,IF(_xlpm.pb>0,_xlpm.pb,IF(_xlpm.pc>0,_xlpm.pc,_xlpm.pd))),_xlpm.len,IF(_xlpm.pa>0,4,IF(_xlpm.pb>0,3,IF(_xlpm.pc>0,2,1))),_xlpm.wrd,IF(_xlpm.pos=0,_xlpm.kd,IF(_xlpm.md=1,INDEX(_xlpm.dP,_xlpm.pos),INDEX(_xlpm.dV,_xlpm.pos))),_xlpm.sep,IF(_xlpm.str="","",IF(_xlpm.md=1," "," / ")),(_xlpm.len-1)&"|"&_xlpm.str&_xlpm.sep&_xlpm.wrd))))),MID(_xlpm.res,FIND("|",_xlpm.res)+1,9999)))} | D65: {=IF($A65="","",_xlfn.LET(_xlpm.s,$A65,_xlpm.dC,'📚 Từ Vựng HSK'!$C$4:$C$1025,_xlpm.dP,'📚 Từ Vựng HSK'!$D$4:$D$1025,_xlpm.dV,'📚 Từ Vựng HSK'!$E$4:$E$1025,_xlpm.md,2,_xlpm.res,_xlfn.REDUCE("0|",_xlfn.SEQUENCE(LEN(_xlpm.s)),_xlfn.LAMBDA(_xlpm.acc,_xlpm.idx,_xlfn.LET(_xlpm.sk,VALUE(LEFT(_xlpm.acc,FIND("|",_xlpm.acc)-1)),_xlpm.str,MID(_xlpm.acc,FIND("|",_xlpm.acc)+1,9999),IF(_xlpm.sk>0,(_xlpm.sk-1)&"|"&_xlpm.str,_xlfn.LET(_xlpm.ka,MID(_xlpm.s,_xlpm.idx,4),_xlpm.kb,MID(_xlpm.s,_xlpm.idx,3),_xlpm.kc,MID(_xlpm.s,_xlpm.idx,2),_xlpm.kd,MID(_xlpm.s,_xlpm.idx,1),_xlpm.pa,IF(LEN(_xlpm.ka)=4,IFERROR(MATCH(_xlpm.ka,_xlpm.dC,0),0),0),_xlpm.pb,IF(LEN(_xlpm.kb)=3,IFERROR(MATCH(_xlpm.kb,_xlpm.dC,0),0),0),_xlpm.pc,IF(LEN(_xlpm.kc)=2,IFERROR(MATCH(_xlpm.kc,_xlpm.dC,0),0),0),_xlpm.pd,IFERROR(MATCH(_xlpm.kd,_xlpm.dC,0),0),_xlpm.pos,IF(_xlpm.pa>0,_xlpm.pa,IF(_xlpm.pb>0,_xlpm.pb,IF(_xlpm.pc>0,_xlpm.pc,_xlpm.pd))),_xlpm.len,IF(_xlpm.pa>0,4,IF(_xlpm.pb>0,3,IF(_xlpm.pc>0,2,1))),_xlpm.wrd,IF(_xlpm.pos=0,_xlpm.kd,IF(_xlpm.md=1,INDEX(_xlpm.dP,_xlpm.pos),INDEX(_xlpm.dV,_xlpm.pos))),_xlpm.sep,IF(_xlpm.str="","",IF(_xlpm.md=1," "," / ")),(_xlpm.len-1)&"|"&_xlpm.str&_xlpm.sep&_xlpm.wrd))))),MID(_xlpm.res,FIND("|",_xlpm.res)+1,9999)))}
C66: {=IF($A66="","",_xlfn.LET(_xlpm.s,$A66,_xlpm.dC,'📚 Từ Vựng HSK'!$C$4:$C$1025,_xlpm.dP,'📚 Từ Vựng HSK'!$D$4:$D$1025,_xlpm.dV,'📚 Từ Vựng HSK'!$E$4:$E$1025,_xlpm.md,1,_xlpm.res,_xlfn.REDUCE("0|",_xlfn.SEQUENCE(LEN(_xlpm.s)),_xlfn.LAMBDA(_xlpm.acc,_xlpm.idx,_xlfn.LET(_xlpm.sk,VALUE(LEFT(_xlpm.acc,FIND("|",_xlpm.acc)-1)),_xlpm.str,MID(_xlpm.acc,FIND("|",_xlpm.acc)+1,9999),IF(_xlpm.sk>0,(_xlpm.sk-1)&"|"&_xlpm.str,_xlfn.LET(_xlpm.ka,MID(_xlpm.s,_xlpm.idx,4),_xlpm.kb,MID(_xlpm.s,_xlpm.idx,3),_xlpm.kc,MID(_xlpm.s,_xlpm.idx,2),_xlpm.kd,MID(_xlpm.s,_xlpm.idx,1),_xlpm.pa,IF(LEN(_xlpm.ka)=4,IFERROR(MATCH(_xlpm.ka,_xlpm.dC,0),0),0),_xlpm.pb,IF(LEN(_xlpm.kb)=3,IFERROR(MATCH(_xlpm.kb,_xlpm.dC,0),0),0),_xlpm.pc,IF(LEN(_xlpm.kc)=2,IFERROR(MATCH(_xlpm.kc,_xlpm.dC,0),0),0),_xlpm.pd,IFERROR(MATCH(_xlpm.kd,_xlpm.dC,0),0),_xlpm.pos,IF(_xlpm.pa>0,_xlpm.pa,IF(_xlpm.pb>0,_xlpm.pb,IF(_xlpm.pc>0,_xlpm.pc,_xlpm.pd))),_xlpm.len,IF(_xlpm.pa>0,4,IF(_xlpm.pb>0,3,IF(_xlpm.pc>0,2,1))),_xlpm.wrd,IF(_xlpm.pos=0,_xlpm.kd,IF(_xlpm.md=1,INDEX(_xlpm.dP,_xlpm.pos),INDEX(_xlpm.dV,_xlpm.pos))),_xlpm.sep,IF(_xlpm.str="","",IF(_xlpm.md=1," "," / ")),(_xlpm.len-1)&"|"&_xlpm.str&_xlpm.sep&_xlpm.wrd))))),MID(_xlpm.res,FIND("|",_xlpm.res)+1,9999)))} | D66: {=IF($A66="","",_xlfn.LET(_xlpm.s,$A66,_xlpm.dC,'📚 Từ Vựng HSK'!$C$4:$C$1025,_xlpm.dP,'📚 Từ Vựng HSK'!$D$4:$D$1025,_xlpm.dV,'📚 Từ Vựng HSK'!$E$4:$E$1025,_xlpm.md,2,_xlpm.res,_xlfn.REDUCE("0|",_xlfn.SEQUENCE(LEN(_xlpm.s)),_xlfn.LAMBDA(_xlpm.acc,_xlpm.idx,_xlfn.LET(_xlpm.sk,VALUE(LEFT(_xlpm.acc,FIND("|",_xlpm.acc)-1)),_xlpm.str,MID(_xlpm.acc,FIND("|",_xlpm.acc)+1,9999),IF(_xlpm.sk>0,(_xlpm.sk-1)&"|"&_xlpm.str,_xlfn.LET(_xlpm.ka,MID(_xlpm.s,_xlpm.idx,4),_xlpm.kb,MID(_xlpm.s,_xlpm.idx,3),_xlpm.kc,MID(_xlpm.s,_xlpm.idx,2),_xlpm.kd,MID(_xlpm.s,_xlpm.idx,1),_xlpm.pa,IF(LEN(_xlpm.ka)=4,IFERROR(MATCH(_xlpm.ka,_xlpm.dC,0),0),0),_xlpm.pb,IF(LEN(_xlpm.kb)=3,IFERROR(MATCH(_xlpm.kb,_xlpm.dC,0),0),0),_xlpm.pc,IF(LEN(_xlpm.kc)=2,IFERROR(MATCH(_xlpm.kc,_xlpm.dC,0),0),0),_xlpm.pd,IFERROR(MATCH(_xlpm.kd,_xlpm.dC,0),0),_xlpm.pos,IF(_xlpm.pa>0,_xlpm.pa,IF(_xlpm.pb>0,_xlpm.pb,IF(_xlpm.pc>0,_xlpm.pc,_xlpm.pd))),_xlpm.len,IF(_xlpm.pa>0,4,IF(_xlpm.pb>0,3,IF(_xlpm.pc>0,2,1))),_xlpm.wrd,IF(_xlpm.pos=0,_xlpm.kd,IF(_xlpm.md=1,INDEX(_xlpm.dP,_xlpm.pos),INDEX(_xlpm.dV,_xlpm.pos))),_xlpm.sep,IF(_xlpm.str="","",IF(_xlpm.md=1," "," / ")),(_xlpm.len-1)&"|"&_xlpm.str&_xlpm.sep&_xlpm.wrd))))),MID(_xlpm.res,FIND("|",_xlpm.res)+1,9999)))}
C67: {=IF($A67="","",_xlfn.LET(_xlpm.s,$A67,_xlpm.dC,'📚 Từ Vựng HSK'!$C$4:$C$1025,_xlpm.dP,'📚 Từ Vựng HSK'!$D$4:$D$1025,_xlpm.dV,'📚 Từ Vựng HSK'!$E$4:$E$1025,_xlpm.md,1,_xlpm.res,_xlfn.REDUCE("0|",_xlfn.SEQUENCE(LEN(_xlpm.s)),_xlfn.LAMBDA(_xlpm.acc,_xlpm.idx,_xlfn.LET(_xlpm.sk,VALUE(LEFT(_xlpm.acc,FIND("|",_xlpm.acc)-1)),_xlpm.str,MID(_xlpm.acc,FIND("|",_xlpm.acc)+1,9999),IF(_xlpm.sk>0,(_xlpm.sk-1)&"|"&_xlpm.str,_xlfn.LET(_xlpm.ka,MID(_xlpm.s,_xlpm.idx,4),_xlpm.kb,MID(_xlpm.s,_xlpm.idx,3),_xlpm.kc,MID(_xlpm.s,_xlpm.idx,2),_xlpm.kd,MID(_xlpm.s,_xlpm.idx,1),_xlpm.pa,IF(LEN(_xlpm.ka)=4,IFERROR(MATCH(_xlpm.ka,_xlpm.dC,0),0),0),_xlpm.pb,IF(LEN(_xlpm.kb)=3,IFERROR(MATCH(_xlpm.kb,_xlpm.dC,0),0),0),_xlpm.pc,IF(LEN(_xlpm.kc)=2,IFERROR(MATCH(_xlpm.kc,_xlpm.dC,0),0),0),_xlpm.pd,IFERROR(MATCH(_xlpm.kd,_xlpm.dC,0),0),_xlpm.pos,IF(_xlpm.pa>0,_xlpm.pa,IF(_xlpm.pb>0,_xlpm.pb,IF(_xlpm.pc>0,_xlpm.pc,_xlpm.pd))),_xlpm.len,IF(_xlpm.pa>0,4,IF(_xlpm.pb>0,3,IF(_xlpm.pc>0,2,1))),_xlpm.wrd,IF(_xlpm.pos=0,_xlpm.kd,IF(_xlpm.md=1,INDEX(_xlpm.dP,_xlpm.pos),INDEX(_xlpm.dV,_xlpm.pos))),_xlpm.sep,IF(_xlpm.str="","",IF(_xlpm.md=1," "," / ")),(_xlpm.len-1)&"|"&_xlpm.str&_xlpm.sep&_xlpm.wrd))))),MID(_xlpm.res,FIND("|",_xlpm.res)+1,9999)))} | D67: {=IF($A67="","",_xlfn.LET(_xlpm.s,$A67,_xlpm.dC,'📚 Từ Vựng HSK'!$C$4:$C$1025,_xlpm.dP,'📚 Từ Vựng HSK'!$D$4:$D$1025,_xlpm.dV,'📚 Từ Vựng HSK'!$E$4:$E$1025,_xlpm.md,2,_xlpm.res,_xlfn.REDUCE("0|",_xlfn.SEQUENCE(LEN(_xlpm.s)),_xlfn.LAMBDA(_xlpm.acc,_xlpm.idx,_xlfn.LET(_xlpm.sk,VALUE(LEFT(_xlpm.acc,FIND("|",_xlpm.acc)-1)),_xlpm.str,MID(_xlpm.acc,FIND("|",_xlpm.acc)+1,9999),IF(_xlpm.sk>0,(_xlpm.sk-1)&"|"&_xlpm.str,_xlfn.LET(_xlpm.ka,MID(_xlpm.s,_xlpm.idx,4),_xlpm.kb,MID(_xlpm.s,_xlpm.idx,3),_xlpm.kc,MID(_xlpm.s,_xlpm.idx,2),_xlpm.kd,MID(_xlpm.s,_xlpm.idx,1),_xlpm.pa,IF(LEN(_xlpm.ka)=4,IFERROR(MATCH(_xlpm.ka,_xlpm.dC,0),0),0),_xlpm.pb,IF(LEN(_xlpm.kb)=3,IFERROR(MATCH(_xlpm.kb,_xlpm.dC,0),0),0),_xlpm.pc,IF(LEN(_xlpm.kc)=2,IFERROR(MATCH(_xlpm.kc,_xlpm.dC,0),0),0),_xlpm.pd,IFERROR(MATCH(_xlpm.kd,_xlpm.dC,0),0),_xlpm.pos,IF(_xlpm.pa>0,_xlpm.pa,IF(_xlpm.pb>0,_xlpm.pb,IF(_xlpm.pc>0,_xlpm.pc,_xlpm.pd))),_xlpm.len,IF(_xlpm.pa>0,4,IF(_xlpm.pb>0,3,IF(_xlpm.pc>0,2,1))),_xlpm.wrd,IF(_xlpm.pos=0,_xlpm.kd,IF(_xlpm.md=1,INDEX(_xlpm.dP,_xlpm.pos),INDEX(_xlpm.dV,_xlpm.pos))),_xlpm.sep,IF(_xlpm.str="","",IF(_xlpm.md=1," "," / ")),(_xlpm.len-1)&"|"&_xlpm.str&_xlpm.sep&_xlpm.wrd))))),MID(_xlpm.res,FIND("|",_xlpm.res)+1,9999)))}
C68: {=IF($A68="","",_xlfn.LET(_xlpm.s,$A68,_xlpm.dC,'📚 Từ Vựng HSK'!$C$4:$C$1025,_xlpm.dP,'📚 Từ Vựng HSK'!$D$4:$D$1025,_xlpm.dV,'📚 Từ Vựng HSK'!$E$4:$E$1025,_xlpm.md,1,_xlpm.res,_xlfn.REDUCE("0|",_xlfn.SEQUENCE(LEN(_xlpm.s)),_xlfn.LAMBDA(_xlpm.acc,_xlpm.idx,_xlfn.LET(_xlpm.sk,VALUE(LEFT(_xlpm.acc,FIND("|",_xlpm.acc)-1)),_xlpm.str,MID(_xlpm.acc,FIND("|",_xlpm.acc)+1,9999),IF(_xlpm.sk>0,(_xlpm.sk-1)&"|"&_xlpm.str,_xlfn.LET(_xlpm.ka,MID(_xlpm.s,_xlpm.idx,4),_xlpm.kb,MID(_xlpm.s,_xlpm.idx,3),_xlpm.kc,MID(_xlpm.s,_xlpm.idx,2),_xlpm.kd,MID(_xlpm.s,_xlpm.idx,1),_xlpm.pa,IF(LEN(_xlpm.ka)=4,IFERROR(MATCH(_xlpm.ka,_xlpm.dC,0),0),0),_xlpm.pb,IF(LEN(_xlpm.kb)=3,IFERROR(MATCH(_xlpm.kb,_xlpm.dC,0),0),0),_xlpm.pc,IF(LEN(_xlpm.kc)=2,IFERROR(MATCH(_xlpm.kc,_xlpm.dC,0),0),0),_xlpm.pd,IFERROR(MATCH(_xlpm.kd,_xlpm.dC,0),0),_xlpm.pos,IF(_xlpm.pa>0,_xlpm.pa,IF(_xlpm.pb>0,_xlpm.pb,IF(_xlpm.pc>0,_xlpm.pc,_xlpm.pd))),_xlpm.len,IF(_xlpm.pa>0,4,IF(_xlpm.pb>0,3,IF(_xlpm.pc>0,2,1))),_xlpm.wrd,IF(_xlpm.pos=0,_xlpm.kd,IF(_xlpm.md=1,INDEX(_xlpm.dP,_xlpm.pos),INDEX(_xlpm.dV,_xlpm.pos))),_xlpm.sep,IF(_xlpm.str="","",IF(_xlpm.md=1," "," / ")),(_xlpm.len-1)&"|"&_xlpm.str&_xlpm.sep&_xlpm.wrd))))),MID(_xlpm.res,FIND("|",_xlpm.res)+1,9999)))} | D68: {=IF($A68="","",_xlfn.LET(_xlpm.s,$A68,_xlpm.dC,'📚 Từ Vựng HSK'!$C$4:$C$1025,_xlpm.dP,'📚 Từ Vựng HSK'!$D$4:$D$1025,_xlpm.dV,'📚 Từ Vựng HSK'!$E$4:$E$1025,_xlpm.md,2,_xlpm.res,_xlfn.REDUCE("0|",_xlfn.SEQUENCE(LEN(_xlpm.s)),_xlfn.LAMBDA(_xlpm.acc,_xlpm.idx,_xlfn.LET(_xlpm.sk,VALUE(LEFT(_xlpm.acc,FIND("|",_xlpm.acc)-1)),_xlpm.str,MID(_xlpm.acc,FIND("|",_xlpm.acc)+1,9999),IF(_xlpm.sk>0,(_xlpm.sk-1)&"|"&_xlpm.str,_xlfn.LET(_xlpm.ka,MID(_xlpm.s,_xlpm.idx,4),_xlpm.kb,MID(_xlpm.s,_xlpm.idx,3),_xlpm.kc,MID(_xlpm.s,_xlpm.idx,2),_xlpm.kd,MID(_xlpm.s,_xlpm.idx,1),_xlpm.pa,IF(LEN(_xlpm.ka)=4,IFERROR(MATCH(_xlpm.ka,_xlpm.dC,0),0),0),_xlpm.pb,IF(LEN(_xlpm.kb)=3,IFERROR(MATCH(_xlpm.kb,_xlpm.dC,0),0),0),_xlpm.pc,IF(LEN(_xlpm.kc)=2,IFERROR(MATCH(_xlpm.kc,_xlpm.dC,0),0),0),_xlpm.pd,IFERROR(MATCH(_xlpm.kd,_xlpm.dC,0),0),_xlpm.pos,IF(_xlpm.pa>0,_xlpm.pa,IF(_xlpm.pb>0,_xlpm.pb,IF(_xlpm.pc>0,_xlpm.pc,_xlpm.pd))),_xlpm.len,IF(_xlpm.pa>0,4,IF(_xlpm.pb>0,3,IF(_xlpm.pc>0,2,1))),_xlpm.wrd,IF(_xlpm.pos=0,_xlpm.kd,IF(_xlpm.md=1,INDEX(_xlpm.dP,_xlpm.pos),INDEX(_xlpm.dV,_xlpm.pos))),_xlpm.sep,IF(_xlpm.str="","",IF(_xlpm.md=1," "," / ")),(_xlpm.len-1)&"|"&_xlpm.str&_xlpm.sep&_xlpm.wrd))))),MID(_xlpm.res,FIND("|",_xlpm.res)+1,9999)))}
C69: {=IF($A69="","",_xlfn.LET(_xlpm.s,$A69,_xlpm.dC,'📚 Từ Vựng HSK'!$C$4:$C$1025,_xlpm.dP,'📚 Từ Vựng HSK'!$D$4:$D$1025,_xlpm.dV,'📚 Từ Vựng HSK'!$E$4:$E$1025,_xlpm.md,1,_xlpm.res,_xlfn.REDUCE("0|",_xlfn.SEQUENCE(LEN(_xlpm.s)),_xlfn.LAMBDA(_xlpm.acc,_xlpm.idx,_xlfn.LET(_xlpm.sk,VALUE(LEFT(_xlpm.acc,FIND("|",_xlpm.acc)-1)),_xlpm.str,MID(_xlpm.acc,FIND("|",_xlpm.acc)+1,9999),IF(_xlpm.sk>0,(_xlpm.sk-1)&"|"&_xlpm.str,_xlfn.LET(_xlpm.ka,MID(_xlpm.s,_xlpm.idx,4),_xlpm.kb,MID(_xlpm.s,_xlpm.idx,3),_xlpm.kc,MID(_xlpm.s,_xlpm.idx,2),_xlpm.kd,MID(_xlpm.s,_xlpm.idx,1),_xlpm.pa,IF(LEN(_xlpm.ka)=4,IFERROR(MATCH(_xlpm.ka,_xlpm.dC,0),0),0),_xlpm.pb,IF(LEN(_xlpm.kb)=3,IFERROR(MATCH(_xlpm.kb,_xlpm.dC,0),0),0),_xlpm.pc,IF(LEN(_xlpm.kc)=2,IFERROR(MATCH(_xlpm.kc,_xlpm.dC,0),0),0),_xlpm.pd,IFERROR(MATCH(_xlpm.kd,_xlpm.dC,0),0),_xlpm.pos,IF(_xlpm.pa>0,_xlpm.pa,IF(_xlpm.pb>0,_xlpm.pb,IF(_xlpm.pc>0,_xlpm.pc,_xlpm.pd))),_xlpm.len,IF(_xlpm.pa>0,4,IF(_xlpm.pb>0,3,IF(_xlpm.pc>0,2,1))),_xlpm.wrd,IF(_xlpm.pos=0,_xlpm.kd,IF(_xlpm.md=1,INDEX(_xlpm.dP,_xlpm.pos),INDEX(_xlpm.dV,_xlpm.pos))),_xlpm.sep,IF(_xlpm.str="","",IF(_xlpm.md=1," "," / ")),(_xlpm.len-1)&"|"&_xlpm.str&_xlpm.sep&_xlpm.wrd))))),MID(_xlpm.res,FIND("|",_xlpm.res)+1,9999)))} | D69: {=IF($A69="","",_xlfn.LET(_xlpm.s,$A69,_xlpm.dC,'📚 Từ Vựng HSK'!$C$4:$C$1025,_xlpm.dP,'📚 Từ Vựng HSK'!$D$4:$D$1025,_xlpm.dV,'📚 Từ Vựng HSK'!$E$4:$E$1025,_xlpm.md,2,_xlpm.res,_xlfn.REDUCE("0|",_xlfn.SEQUENCE(LEN(_xlpm.s)),_xlfn.LAMBDA(_xlpm.acc,_xlpm.idx,_xlfn.LET(_xlpm.sk,VALUE(LEFT(_xlpm.acc,FIND("|",_xlpm.acc)-1)),_xlpm.str,MID(_xlpm.acc,FIND("|",_xlpm.acc)+1,9999),IF(_xlpm.sk>0,(_xlpm.sk-1)&"|"&_xlpm.str,_xlfn.LET(_xlpm.ka,MID(_xlpm.s,_xlpm.idx,4),_xlpm.kb,MID(_xlpm.s,_xlpm.idx,3),_xlpm.kc,MID(_xlpm.s,_xlpm.idx,2),_xlpm.kd,MID(_xlpm.s,_xlpm.idx,1),_xlpm.pa,IF(LEN(_xlpm.ka)=4,IFERROR(MATCH(_xlpm.ka,_xlpm.dC,0),0),0),_xlpm.pb,IF(LEN(_xlpm.kb)=3,IFERROR(MATCH(_xlpm.kb,_xlpm.dC,0),0),0),_xlpm.pc,IF(LEN(_xlpm.kc)=2,IFERROR(MATCH(_xlpm.kc,_xlpm.dC,0),0),0),_xlpm.pd,IFERROR(MATCH(_xlpm.kd,_xlpm.dC,0),0),_xlpm.pos,IF(_xlpm.pa>0,_xlpm.pa,IF(_xlpm.pb>0,_xlpm.pb,IF(_xlpm.pc>0,_xlpm.pc,_xlpm.pd))),_xlpm.len,IF(_xlpm.pa>0,4,IF(_xlpm.pb>0,3,IF(_xlpm.pc>0,2,1))),_xlpm.wrd,IF(_xlpm.pos=0,_xlpm.kd,IF(_xlpm.md=1,INDEX(_xlpm.dP,_xlpm.pos),INDEX(_xlpm.dV,_xlpm.pos))),_xlpm.sep,IF(_xlpm.str="","",IF(_xlpm.md=1," "," / ")),(_xlpm.len-1)&"|"&_xlpm.str&_xlpm.sep&_xlpm.wrd))))),MID(_xlpm.res,FIND("|",_xlpm.res)+1,9999)))}
C70: {=IF($A70="","",_xlfn.LET(_xlpm.s,$A70,_xlpm.dC,'📚 Từ Vựng HSK'!$C$4:$C$1025,_xlpm.dP,'📚 Từ Vựng HSK'!$D$4:$D$1025,_xlpm.dV,'📚 Từ Vựng HSK'!$E$4:$E$1025,_xlpm.md,1,_xlpm.res,_xlfn.REDUCE("0|",_xlfn.SEQUENCE(LEN(_xlpm.s)),_xlfn.LAMBDA(_xlpm.acc,_xlpm.idx,_xlfn.LET(_xlpm.sk,VALUE(LEFT(_xlpm.acc,FIND("|",_xlpm.acc)-1)),_xlpm.str,MID(_xlpm.acc,FIND("|",_xlpm.acc)+1,9999),IF(_xlpm.sk>0,(_xlpm.sk-1)&"|"&_xlpm.str,_xlfn.LET(_xlpm.ka,MID(_xlpm.s,_xlpm.idx,4),_xlpm.kb,MID(_xlpm.s,_xlpm.idx,3),_xlpm.kc,MID(_xlpm.s,_xlpm.idx,2),_xlpm.kd,MID(_xlpm.s,_xlpm.idx,1),_xlpm.pa,IF(LEN(_xlpm.ka)=4,IFERROR(MATCH(_xlpm.ka,_xlpm.dC,0),0),0),_xlpm.pb,IF(LEN(_xlpm.kb)=3,IFERROR(MATCH(_xlpm.kb,_xlpm.dC,0),0),0),_xlpm.pc,IF(LEN(_xlpm.kc)=2,IFERROR(MATCH(_xlpm.kc,_xlpm.dC,0),0),0),_xlpm.pd,IFERROR(MATCH(_xlpm.kd,_xlpm.dC,0),0),_xlpm.pos,IF(_xlpm.pa>0,_xlpm.pa,IF(_xlpm.pb>0,_xlpm.pb,IF(_xlpm.pc>0,_xlpm.pc,_xlpm.pd))),_xlpm.len,IF(_xlpm.pa>0,4,IF(_xlpm.pb>0,3,IF(_xlpm.pc>0,2,1))),_xlpm.wrd,IF(_xlpm.pos=0,_xlpm.kd,IF(_xlpm.md=1,INDEX(_xlpm.dP,_xlpm.pos),INDEX(_xlpm.dV,_xlpm.pos))),_xlpm.sep,IF(_xlpm.str="","",IF(_xlpm.md=1," "," / ")),(_xlpm.len-1)&"|"&_xlpm.str&_xlpm.sep&_xlpm.wrd))))),MID(_xlpm.res,FIND("|",_xlpm.res)+1,9999)))} | D70: {=IF($A70="","",_xlfn.LET(_xlpm.s,$A70,_xlpm.dC,'📚 Từ Vựng HSK'!$C$4:$C$1025,_xlpm.dP,'📚 Từ Vựng HSK'!$D$4:$D$1025,_xlpm.dV,'📚 Từ Vựng HSK'!$E$4:$E$1025,_xlpm.md,2,_xlpm.res,_xlfn.REDUCE("0|",_xlfn.SEQUENCE(LEN(_xlpm.s)),_xlfn.LAMBDA(_xlpm.acc,_xlpm.idx,_xlfn.LET(_xlpm.sk,VALUE(LEFT(_xlpm.acc,FIND("|",_xlpm.acc)-1)),_xlpm.str,MID(_xlpm.acc,FIND("|",_xlpm.acc)+1,9999),IF(_xlpm.sk>0,(_xlpm.sk-1)&"|"&_xlpm.str,_xlfn.LET(_xlpm.ka,MID(_xlpm.s,_xlpm.idx,4),_xlpm.kb,MID(_xlpm.s,_xlpm.idx,3),_xlpm.kc,MID(_xlpm.s,_xlpm.idx,2),_xlpm.kd,MID(_xlpm.s,_xlpm.idx,1),_xlpm.pa,IF(LEN(_xlpm.ka)=4,IFERROR(MATCH(_xlpm.ka,_xlpm.dC,0),0),0),_xlpm.pb,IF(LEN(_xlpm.kb)=3,IFERROR(MATCH(_xlpm.kb,_xlpm.dC,0),0),0),_xlpm.pc,IF(LEN(_xlpm.kc)=2,IFERROR(MATCH(_xlpm.kc,_xlpm.dC,0),0),0),_xlpm.pd,IFERROR(MATCH(_xlpm.kd,_xlpm.dC,0),0),_xlpm.pos,IF(_xlpm.pa>0,_xlpm.pa,IF(_xlpm.pb>0,_xlpm.pb,IF(_xlpm.pc>0,_xlpm.pc,_xlpm.pd))),_xlpm.len,IF(_xlpm.pa>0,4,IF(_xlpm.pb>0,3,IF(_xlpm.pc>0,2,1))),_xlpm.wrd,IF(_xlpm.pos=0,_xlpm.kd,IF(_xlpm.md=1,INDEX(_xlpm.dP,_xlpm.pos),INDEX(_xlpm.dV,_xlpm.pos))),_xlpm.sep,IF(_xlpm.str="","",IF(_xlpm.md=1," "," / ")),(_xlpm.len-1)&"|"&_xlpm.str&_xlpm.sep&_xlpm.wrd))))),MID(_xlpm.res,FIND("|",_xlpm.res)+1,9999)))}
C71: {=IF($A71="","",_xlfn.LET(_xlpm.s,$A71,_xlpm.dC,'📚 Từ Vựng HSK'!$C$4:$C$1025,_xlpm.dP,'📚 Từ Vựng HSK'!$D$4:$D$1025,_xlpm.dV,'📚 Từ Vựng HSK'!$E$4:$E$1025,_xlpm.md,1,_xlpm.res,_xlfn.REDUCE("0|",_xlfn.SEQUENCE(LEN(_xlpm.s)),_xlfn.LAMBDA(_xlpm.acc,_xlpm.idx,_xlfn.LET(_xlpm.sk,VALUE(LEFT(_xlpm.acc,FIND("|",_xlpm.acc)-1)),_xlpm.str,MID(_xlpm.acc,FIND("|",_xlpm.acc)+1,9999),IF(_xlpm.sk>0,(_xlpm.sk-1)&"|"&_xlpm.str,_xlfn.LET(_xlpm.ka,MID(_xlpm.s,_xlpm.idx,4),_xlpm.kb,MID(_xlpm.s,_xlpm.idx,3),_xlpm.kc,MID(_xlpm.s,_xlpm.idx,2),_xlpm.kd,MID(_xlpm.s,_xlpm.idx,1),_xlpm.pa,IF(LEN(_xlpm.ka)=4,IFERROR(MATCH(_xlpm.ka,_xlpm.dC,0),0),0),_xlpm.pb,IF(LEN(_xlpm.kb)=3,IFERROR(MATCH(_xlpm.kb,_xlpm.dC,0),0),0),_xlpm.pc,IF(LEN(_xlpm.kc)=2,IFERROR(MATCH(_xlpm.kc,_xlpm.dC,0),0),0),_xlpm.pd,IFERROR(MATCH(_xlpm.kd,_xlpm.dC,0),0),_xlpm.pos,IF(_xlpm.pa>0,_xlpm.pa,IF(_xlpm.pb>0,_xlpm.pb,IF(_xlpm.pc>0,_xlpm.pc,_xlpm.pd))),_xlpm.len,IF(_xlpm.pa>0,4,IF(_xlpm.pb>0,3,IF(_xlpm.pc>0,2,1))),_xlpm.wrd,IF(_xlpm.pos=0,_xlpm.kd,IF(_xlpm.md=1,INDEX(_xlpm.dP,_xlpm.pos),INDEX(_xlpm.dV,_xlpm.pos))),_xlpm.sep,IF(_xlpm.str="","",IF(_xlpm.md=1," "," / ")),(_xlpm.len-1)&"|"&_xlpm.str&_xlpm.sep&_xlpm.wrd))))),MID(_xlpm.res,FIND("|",_xlpm.res)+1,9999)))} | D71: {=IF($A71="","",_xlfn.LET(_xlpm.s,$A71,_xlpm.dC,'📚 Từ Vựng HSK'!$C$4:$C$1025,_xlpm.dP,'📚 Từ Vựng HSK'!$D$4:$D$1025,_xlpm.dV,'📚 Từ Vựng HSK'!$E$4:$E$1025,_xlpm.md,2,_xlpm.res,_xlfn.REDUCE("0|",_xlfn.SEQUENCE(LEN(_xlpm.s)),_xlfn.LAMBDA(_xlpm.acc,_xlpm.idx,_xlfn.LET(_xlpm.sk,VALUE(LEFT(_xlpm.acc,FIND("|",_xlpm.acc)-1)),_xlpm.str,MID(_xlpm.acc,FIND("|",_xlpm.acc)+1,9999),IF(_xlpm.sk>0,(_xlpm.sk-1)&"|"&_xlpm.str,_xlfn.LET(_xlpm.ka,MID(_xlpm.s,_xlpm.idx,4),_xlpm.kb,MID(_xlpm.s,_xlpm.idx,3),_xlpm.kc,MID(_xlpm.s,_xlpm.idx,2),_xlpm.kd,MID(_xlpm.s,_xlpm.idx,1),_xlpm.pa,IF(LEN(_xlpm.ka)=4,IFERROR(MATCH(_xlpm.ka,_xlpm.dC,0),0),0),_xlpm.pb,IF(LEN(_xlpm.kb)=3,IFERROR(MATCH(_xlpm.kb,_xlpm.dC,0),0),0),_xlpm.pc,IF(LEN(_xlpm.kc)=2,IFERROR(MATCH(_xlpm.kc,_xlpm.dC,0),0),0),_xlpm.pd,IFERROR(MATCH(_xlpm.kd,_xlpm.dC,0),0),_xlpm.pos,IF(_xlpm.pa>0,_xlpm.pa,IF(_xlpm.pb>0,_xlpm.pb,IF(_xlpm.pc>0,_xlpm.pc,_xlpm.pd))),_xlpm.len,IF(_xlpm.pa>0,4,IF(_xlpm.pb>0,3,IF(_xlpm.pc>0,2,1))),_xlpm.wrd,IF(_xlpm.pos=0,_xlpm.kd,IF(_xlpm.md=1,INDEX(_xlpm.dP,_xlpm.pos),INDEX(_xlpm.dV,_xlpm.pos))),_xlpm.sep,IF(_xlpm.str="","",IF(_xlpm.md=1," "," / ")),(_xlpm.len-1)&"|"&_xlpm.str&_xlpm.sep&_xlpm.wrd))))),MID(_xlpm.res,FIND("|",_xlpm.res)+1,9999)))}
C72: {=IF($A72="","",_xlfn.LET(_xlpm.s,$A72,_xlpm.dC,'📚 Từ Vựng HSK'!$C$4:$C$1025,_xlpm.dP,'📚 Từ Vựng HSK'!$D$4:$D$1025,_xlpm.dV,'📚 Từ Vựng HSK'!$E$4:$E$1025,_xlpm.md,1,_xlpm.res,_xlfn.REDUCE("0|",_xlfn.SEQUENCE(LEN(_xlpm.s)),_xlfn.LAMBDA(_xlpm.acc,_xlpm.idx,_xlfn.LET(_xlpm.sk,VALUE(LEFT(_xlpm.acc,FIND("|",_xlpm.acc)-1)),_xlpm.str,MID(_xlpm.acc,FIND("|",_xlpm.acc)+1,9999),IF(_xlpm.sk>0,(_xlpm.sk-1)&"|"&_xlpm.str,_xlfn.LET(_xlpm.ka,MID(_xlpm.s,_xlpm.idx,4),_xlpm.kb,MID(_xlpm.s,_xlpm.idx,3),_xlpm.kc,MID(_xlpm.s,_xlpm.idx,2),_xlpm.kd,MID(_xlpm.s,_xlpm.idx,1),_xlpm.pa,IF(LEN(_xlpm.ka)=4,IFERROR(MATCH(_xlpm.ka,_xlpm.dC,0),0),0),_xlpm.pb,IF(LEN(_xlpm.kb)=3,IFERROR(MATCH(_xlpm.kb,_xlpm.dC,0),0),0),_xlpm.pc,IF(LEN(_xlpm.kc)=2,IFERROR(MATCH(_xlpm.kc,_xlpm.dC,0),0),0),_xlpm.pd,IFERROR(MATCH(_xlpm.kd,_xlpm.dC,0),0),_xlpm.pos,IF(_xlpm.pa>0,_xlpm.pa,IF(_xlpm.pb>0,_xlpm.pb,IF(_xlpm.pc>0,_xlpm.pc,_xlpm.pd))),_xlpm.len,IF(_xlpm.pa>0,4,IF(_xlpm.pb>0,3,IF(_xlpm.pc>0,2,1))),_xlpm.wrd,IF(_xlpm.pos=0,_xlpm.kd,IF(_xlpm.md=1,INDEX(_xlpm.dP,_xlpm.pos),INDEX(_xlpm.dV,_xlpm.pos))),_xlpm.sep,IF(_xlpm.str="","",IF(_xlpm.md=1," "," / ")),(_xlpm.len-1)&"|"&_xlpm.str&_xlpm.sep&_xlpm.wrd))))),MID(_xlpm.res,FIND("|",_xlpm.res)+1,9999)))} | D72: {=IF($A72="","",_xlfn.LET(_xlpm.s,$A72,_xlpm.dC,'📚 Từ Vựng HSK'!$C$4:$C$1025,_xlpm.dP,'📚 Từ Vựng HSK'!$D$4:$D$1025,_xlpm.dV,'📚 Từ Vựng HSK'!$E$4:$E$1025,_xlpm.md,2,_xlpm.res,_xlfn.REDUCE("0|",_xlfn.SEQUENCE(LEN(_xlpm.s)),_xlfn.LAMBDA(_xlpm.acc,_xlpm.idx,_xlfn.LET(_xlpm.sk,VALUE(LEFT(_xlpm.acc,FIND("|",_xlpm.acc)-1)),_xlpm.str,MID(_xlpm.acc,FIND("|",_xlpm.acc)+1,9999),IF(_xlpm.sk>0,(_xlpm.sk-1)&"|"&_xlpm.str,_xlfn.LET(_xlpm.ka,MID(_xlpm.s,_xlpm.idx,4),_xlpm.kb,MID(_xlpm.s,_xlpm.idx,3),_xlpm.kc,MID(_xlpm.s,_xlpm.idx,2),_xlpm.kd,MID(_xlpm.s,_xlpm.idx,1),_xlpm.pa,IF(LEN(_xlpm.ka)=4,IFERROR(MATCH(_xlpm.ka,_xlpm.dC,0),0),0),_xlpm.pb,IF(LEN(_xlpm.kb)=3,IFERROR(MATCH(_xlpm.kb,_xlpm.dC,0),0),0),_xlpm.pc,IF(LEN(_xlpm.kc)=2,IFERROR(MATCH(_xlpm.kc,_xlpm.dC,0),0),0),_xlpm.pd,IFERROR(MATCH(_xlpm.kd,_xlpm.dC,0),0),_xlpm.pos,IF(_xlpm.pa>0,_xlpm.pa,IF(_xlpm.pb>0,_xlpm.pb,IF(_xlpm.pc>0,_xlpm.pc,_xlpm.pd))),_xlpm.len,IF(_xlpm.pa>0,4,IF(_xlpm.pb>0,3,IF(_xlpm.pc>0,2,1))),_xlpm.wrd,IF(_xlpm.pos=0,_xlpm.kd,IF(_xlpm.md=1,INDEX(_xlpm.dP,_xlpm.pos),INDEX(_xlpm.dV,_xlpm.pos))),_xlpm.sep,IF(_xlpm.str="","",IF(_xlpm.md=1," "," / ")),(_xlpm.len-1)&"|"&_xlpm.str&_xlpm.sep&_xlpm.wrd))))),MID(_xlpm.res,FIND("|",_xlpm.res)+1,9999)))}
C73: {=IF($A73="","",_xlfn.LET(_xlpm.s,$A73,_xlpm.dC,'📚 Từ Vựng HSK'!$C$4:$C$1025,_xlpm.dP,'📚 Từ Vựng HSK'!$D$4:$D$1025,_xlpm.dV,'📚 Từ Vựng HSK'!$E$4:$E$1025,_xlpm.md,1,_xlpm.res,_xlfn.REDUCE("0|",_xlfn.SEQUENCE(LEN(_xlpm.s)),_xlfn.LAMBDA(_xlpm.acc,_xlpm.idx,_xlfn.LET(_xlpm.sk,VALUE(LEFT(_xlpm.acc,FIND("|",_xlpm.acc)-1)),_xlpm.str,MID(_xlpm.acc,FIND("|",_xlpm.acc)+1,9999),IF(_xlpm.sk>0,(_xlpm.sk-1)&"|"&_xlpm.str,_xlfn.LET(_xlpm.ka,MID(_xlpm.s,_xlpm.idx,4),_xlpm.kb,MID(_xlpm.s,_xlpm.idx,3),_xlpm.kc,MID(_xlpm.s,_xlpm.idx,2),_xlpm.kd,MID(_xlpm.s,_xlpm.idx,1),_xlpm.pa,IF(LEN(_xlpm.ka)=4,IFERROR(MATCH(_xlpm.ka,_xlpm.dC,0),0),0),_xlpm.pb,IF(LEN(_xlpm.kb)=3,IFERROR(MATCH(_xlpm.kb,_xlpm.dC,0),0),0),_xlpm.pc,IF(LEN(_xlpm.kc)=2,IFERROR(MATCH(_xlpm.kc,_xlpm.dC,0),0),0),_xlpm.pd,IFERROR(MATCH(_xlpm.kd,_xlpm.dC,0),0),_xlpm.pos,IF(_xlpm.pa>0,_xlpm.pa,IF(_xlpm.pb>0,_xlpm.pb,IF(_xlpm.pc>0,_xlpm.pc,_xlpm.pd))),_xlpm.len,IF(_xlpm.pa>0,4,IF(_xlpm.pb>0,3,IF(_xlpm.pc>0,2,1))),_xlpm.wrd,IF(_xlpm.pos=0,_xlpm.kd,IF(_xlpm.md=1,INDEX(_xlpm.dP,_xlpm.pos),INDEX(_xlpm.dV,_xlpm.pos))),_xlpm.sep,IF(_xlpm.str="","",IF(_xlpm.md=1," "," / ")),(_xlpm.len-1)&"|"&_xlpm.str&_xlpm.sep&_xlpm.wrd))))),MID(_xlpm.res,FIND("|",_xlpm.res)+1,9999)))} | D73: {=IF($A73="","",_xlfn.LET(_xlpm.s,$A73,_xlpm.dC,'📚 Từ Vựng HSK'!$C$4:$C$1025,_xlpm.dP,'📚 Từ Vựng HSK'!$D$4:$D$1025,_xlpm.dV,'📚 Từ Vựng HSK'!$E$4:$E$1025,_xlpm.md,2,_xlpm.res,_xlfn.REDUCE("0|",_xlfn.SEQUENCE(LEN(_xlpm.s)),_xlfn.LAMBDA(_xlpm.acc,_xlpm.idx,_xlfn.LET(_xlpm.sk,VALUE(LEFT(_xlpm.acc,FIND("|",_xlpm.acc)-1)),_xlpm.str,MID(_xlpm.acc,FIND("|",_xlpm.acc)+1,9999),IF(_xlpm.sk>0,(_xlpm.sk-1)&"|"&_xlpm.str,_xlfn.LET(_xlpm.ka,MID(_xlpm.s,_xlpm.idx,4),_xlpm.kb,MID(_xlpm.s,_xlpm.idx,3),_xlpm.kc,MID(_xlpm.s,_xlpm.idx,2),_xlpm.kd,MID(_xlpm.s,_xlpm.idx,1),_xlpm.pa,IF(LEN(_xlpm.ka)=4,IFERROR(MATCH(_xlpm.ka,_xlpm.dC,0),0),0),_xlpm.pb,IF(LEN(_xlpm.kb)=3,IFERROR(MATCH(_xlpm.kb,_xlpm.dC,0),0),0),_xlpm.pc,IF(LEN(_xlpm.kc)=2,IFERROR(MATCH(_xlpm.kc,_xlpm.dC,0),0),0),_xlpm.pd,IFERROR(MATCH(_xlpm.kd,_xlpm.dC,0),0),_xlpm.pos,IF(_xlpm.pa>0,_xlpm.pa,IF(_xlpm.pb>0,_xlpm.pb,IF(_xlpm.pc>0,_xlpm.pc,_xlpm.pd))),_xlpm.len,IF(_xlpm.pa>0,4,IF(_xlpm.pb>0,3,IF(_xlpm.pc>0,2,1))),_xlpm.wrd,IF(_xlpm.pos=0,_xlpm.kd,IF(_xlpm.md=1,INDEX(_xlpm.dP,_xlpm.pos),INDEX(_xlpm.dV,_xlpm.pos))),_xlpm.sep,IF(_xlpm.str="","",IF(_xlpm.md=1," "," / ")),(_xlpm.len-1)&"|"&_xlpm.str&_xlpm.sep&_xlpm.wrd))))),MID(_xlpm.res,FIND("|",_xlpm.res)+1,9999)))}
C74: {=IF($A74="","",_xlfn.LET(_xlpm.s,$A74,_xlpm.dC,'📚 Từ Vựng HSK'!$C$4:$C$1025,_xlpm.dP,'📚 Từ Vựng HSK'!$D$4:$D$1025,_xlpm.dV,'📚 Từ Vựng HSK'!$E$4:$E$1025,_xlpm.md,1,_xlpm.res,_xlfn.REDUCE("0|",_xlfn.SEQUENCE(LEN(_xlpm.s)),_xlfn.LAMBDA(_xlpm.acc,_xlpm.idx,_xlfn.LET(_xlpm.sk,VALUE(LEFT(_xlpm.acc,FIND("|",_xlpm.acc)-1)),_xlpm.str,MID(_xlpm.acc,FIND("|",_xlpm.acc)+1,9999),IF(_xlpm.sk>0,(_xlpm.sk-1)&"|"&_xlpm.str,_xlfn.LET(_xlpm.ka,MID(_xlpm.s,_xlpm.idx,4),_xlpm.kb,MID(_xlpm.s,_xlpm.idx,3),_xlpm.kc,MID(_xlpm.s,_xlpm.idx,2),_xlpm.kd,MID(_xlpm.s,_xlpm.idx,1),_xlpm.pa,IF(LEN(_xlpm.ka)=4,IFERROR(MATCH(_xlpm.ka,_xlpm.dC,0),0),0),_xlpm.pb,IF(LEN(_xlpm.kb)=3,IFERROR(MATCH(_xlpm.kb,_xlpm.dC,0),0),0),_xlpm.pc,IF(LEN(_xlpm.kc)=2,IFERROR(MATCH(_xlpm.kc,_xlpm.dC,0),0),0),_xlpm.pd,IFERROR(MATCH(_xlpm.kd,_xlpm.dC,0),0),_xlpm.pos,IF(_xlpm.pa>0,_xlpm.pa,IF(_xlpm.pb>0,_xlpm.pb,IF(_xlpm.pc>0,_xlpm.pc,_xlpm.pd))),_xlpm.len,IF(_xlpm.pa>0,4,IF(_xlpm.pb>0,3,IF(_xlpm.pc>0,2,1))),_xlpm.wrd,IF(_xlpm.pos=0,_xlpm.kd,IF(_xlpm.md=1,INDEX(_xlpm.dP,_xlpm.pos),INDEX(_xlpm.dV,_xlpm.pos))),_xlpm.sep,IF(_xlpm.str="","",IF(_xlpm.md=1," "," / ")),(_xlpm.len-1)&"|"&_xlpm.str&_xlpm.sep&_xlpm.wrd))))),MID(_xlpm.res,FIND("|",_xlpm.res)+1,9999)))} | D74: {=IF($A74="","",_xlfn.LET(_xlpm.s,$A74,_xlpm.dC,'📚 Từ Vựng HSK'!$C$4:$C$1025,_xlpm.dP,'📚 Từ Vựng HSK'!$D$4:$D$1025,_xlpm.dV,'📚 Từ Vựng HSK'!$E$4:$E$1025,_xlpm.md,2,_xlpm.res,_xlfn.REDUCE("0|",_xlfn.SEQUENCE(LEN(_xlpm.s)),_xlfn.LAMBDA(_xlpm.acc,_xlpm.idx,_xlfn.LET(_xlpm.sk,VALUE(LEFT(_xlpm.acc,FIND("|",_xlpm.acc)-1)),_xlpm.str,MID(_xlpm.acc,FIND("|",_xlpm.acc)+1,9999),IF(_xlpm.sk>0,(_xlpm.sk-1)&"|"&_xlpm.str,_xlfn.LET(_xlpm.ka,MID(_xlpm.s,_xlpm.idx,4),_xlpm.kb,MID(_xlpm.s,_xlpm.idx,3),_xlpm.kc,MID(_xlpm.s,_xlpm.idx,2),_xlpm.kd,MID(_xlpm.s,_xlpm.idx,1),_xlpm.pa,IF(LEN(_xlpm.ka)=4,IFERROR(MATCH(_xlpm.ka,_xlpm.dC,0),0),0),_xlpm.pb,IF(LEN(_xlpm.kb)=3,IFERROR(MATCH(_xlpm.kb,_xlpm.dC,0),0),0),_xlpm.pc,IF(LEN(_xlpm.kc)=2,IFERROR(MATCH(_xlpm.kc,_xlpm.dC,0),0),0),_xlpm.pd,IFERROR(MATCH(_xlpm.kd,_xlpm.dC,0),0),_xlpm.pos,IF(_xlpm.pa>0,_xlpm.pa,IF(_xlpm.pb>0,_xlpm.pb,IF(_xlpm.pc>0,_xlpm.pc,_xlpm.pd))),_xlpm.len,IF(_xlpm.pa>0,4,IF(_xlpm.pb>0,3,IF(_xlpm.pc>0,2,1))),_xlpm.wrd,IF(_xlpm.pos=0,_xlpm.kd,IF(_xlpm.md=1,INDEX(_xlpm.dP,_xlpm.pos),INDEX(_xlpm.dV,_xlpm.pos))),_xlpm.sep,IF(_xlpm.str="","",IF(_xlpm.md=1," "," / ")),(_xlpm.len-1)&"|"&_xlpm.str&_xlpm.sep&_xlpm.wrd))))),MID(_xlpm.res,FIND("|",_xlpm.res)+1,9999)))}
C75: {=IF($A75="","",_xlfn.LET(_xlpm.s,$A75,_xlpm.dC,'📚 Từ Vựng HSK'!$C$4:$C$1025,_xlpm.dP,'📚 Từ Vựng HSK'!$D$4:$D$1025,_xlpm.dV,'📚 Từ Vựng HSK'!$E$4:$E$1025,_xlpm.md,1,_xlpm.res,_xlfn.REDUCE("0|",_xlfn.SEQUENCE(LEN(_xlpm.s)),_xlfn.LAMBDA(_xlpm.acc,_xlpm.idx,_xlfn.LET(_xlpm.sk,VALUE(LEFT(_xlpm.acc,FIND("|",_xlpm.acc)-1)),_xlpm.str,MID(_xlpm.acc,FIND("|",_xlpm.acc)+1,9999),IF(_xlpm.sk>0,(_xlpm.sk-1)&"|"&_xlpm.str,_xlfn.LET(_xlpm.ka,MID(_xlpm.s,_xlpm.idx,4),_xlpm.kb,MID(_xlpm.s,_xlpm.idx,3),_xlpm.kc,MID(_xlpm.s,_xlpm.idx,2),_xlpm.kd,MID(_xlpm.s,_xlpm.idx,1),_xlpm.pa,IF(LEN(_xlpm.ka)=4,IFERROR(MATCH(_xlpm.ka,_xlpm.dC,0),0),0),_xlpm.pb,IF(LEN(_xlpm.kb)=3,IFERROR(MATCH(_xlpm.kb,_xlpm.dC,0),0),0),_xlpm.pc,IF(LEN(_xlpm.kc)=2,IFERROR(MATCH(_xlpm.kc,_xlpm.dC,0),0),0),_xlpm.pd,IFERROR(MATCH(_xlpm.kd,_xlpm.dC,0),0),_xlpm.pos,IF(_xlpm.pa>0,_xlpm.pa,IF(_xlpm.pb>0,_xlpm.pb,IF(_xlpm.pc>0,_xlpm.pc,_xlpm.pd))),_xlpm.len,IF(_xlpm.pa>0,4,IF(_xlpm.pb>0,3,IF(_xlpm.pc>0,2,1))),_xlpm.wrd,IF(_xlpm.pos=0,_xlpm.kd,IF(_xlpm.md=1,INDEX(_xlpm.dP,_xlpm.pos),INDEX(_xlpm.dV,_xlpm.pos))),_xlpm.sep,IF(_xlpm.str="","",IF(_xlpm.md=1," "," / ")),(_xlpm.len-1)&"|"&_xlpm.str&_xlpm.sep&_xlpm.wrd))))),MID(_xlpm.res,FIND("|",_xlpm.res)+1,9999)))} | D75: {=IF($A75="","",_xlfn.LET(_xlpm.s,$A75,_xlpm.dC,'📚 Từ Vựng HSK'!$C$4:$C$1025,_xlpm.dP,'📚 Từ Vựng HSK'!$D$4:$D$1025,_xlpm.dV,'📚 Từ Vựng HSK'!$E$4:$E$1025,_xlpm.md,2,_xlpm.res,_xlfn.REDUCE("0|",_xlfn.SEQUENCE(LEN(_xlpm.s)),_xlfn.LAMBDA(_xlpm.acc,_xlpm.idx,_xlfn.LET(_xlpm.sk,VALUE(LEFT(_xlpm.acc,FIND("|",_xlpm.acc)-1)),_xlpm.str,MID(_xlpm.acc,FIND("|",_xlpm.acc)+1,9999),IF(_xlpm.sk>0,(_xlpm.sk-1)&"|"&_xlpm.str,_xlfn.LET(_xlpm.ka,MID(_xlpm.s,_xlpm.idx,4),_xlpm.kb,MID(_xlpm.s,_xlpm.idx,3),_xlpm.kc,MID(_xlpm.s,_xlpm.idx,2),_xlpm.kd,MID(_xlpm.s,_xlpm.idx,1),_xlpm.pa,IF(LEN(_xlpm.ka)=4,IFERROR(MATCH(_xlpm.ka,_xlpm.dC,0),0),0),_xlpm.pb,IF(LEN(_xlpm.kb)=3,IFERROR(MATCH(_xlpm.kb,_xlpm.dC,0),0),0),_xlpm.pc,IF(LEN(_xlpm.kc)=2,IFERROR(MATCH(_xlpm.kc,_xlpm.dC,0),0),0),_xlpm.pd,IFERROR(MATCH(_xlpm.kd,_xlpm.dC,0),0),_xlpm.pos,IF(_xlpm.pa>0,_xlpm.pa,IF(_xlpm.pb>0,_xlpm.pb,IF(_xlpm.pc>0,_xlpm.pc,_xlpm.pd))),_xlpm.len,IF(_xlpm.pa>0,4,IF(_xlpm.pb>0,3,IF(_xlpm.pc>0,2,1))),_xlpm.wrd,IF(_xlpm.pos=0,_xlpm.kd,IF(_xlpm.md=1,INDEX(_xlpm.dP,_xlpm.pos),INDEX(_xlpm.dV,_xlpm.pos))),_xlpm.sep,IF(_xlpm.str="","",IF(_xlpm.md=1," "," / ")),(_xlpm.len-1)&"|"&_xlpm.str&_xlpm.sep&_xlpm.wrd))))),MID(_xlpm.res,FIND("|",_xlpm.res)+1,9999)))}
... C203: {=IF($A203="","",_xlfn.LET(_xlpm.s,$A203,_xlpm.dC,'📚 Từ Vựng HSK'!$C$4:$C$1025,_xlpm.dP,'📚 Từ Vựng HSK'!$D$4:$D$1025,_xlpm.dV,'📚 Từ Vựng HSK'!$E$4:$E$1025,_xlpm.md,1,_xlpm.res,_xlfn.REDUCE("0|",_xlfn.SEQUENCE(LEN(_xlpm.s)),_xlfn.LAMBDA(_xlpm.acc,_xlpm.idx,_xlfn.LET(_xlpm.sk,VALUE(LEFT(_xlpm.acc,FIND("|",_xlpm.acc)-1)),_xlpm.str,MID(_xlpm.acc,FIND("|",_xlpm.acc)+1,9999),IF(_xlpm.sk>0,(_xlpm.sk-1)&"|"&_xlpm.str,_xlfn.LET(_xlpm.ka,MID(_xlpm.s,_xlpm.idx,4),_xlpm.kb,MID(_xlpm.s,_xlpm.idx,3),_xlpm.kc,MID(_xlpm.s,_xlpm.idx,2),_xlpm.kd,MID(_xlpm.s,_xlpm.idx,1),_xlpm.pa,IF(LEN(_xlpm.ka)=4,IFERROR(MATCH(_xlpm.ka,_xlpm.dC,0),0),0),_xlpm.pb,IF(LEN(_xlpm.kb)=3,IFERROR(MATCH(_xlpm.kb,_xlpm.dC,0),0),0),_xlpm.pc,IF(LEN(_xlpm.kc)=2,IFERROR(MATCH(_xlpm.kc,_xlpm.dC,0),0),0),_xlpm.pd,IFERROR(MATCH(_xlpm.kd,_xlpm.dC,0),0),_xlpm.pos,IF(_xlpm.pa>0,_xlpm.pa,IF(_xlpm.pb>0,_xlpm.pb,IF(_xlpm.pc>0,_xlpm.pc,_xlpm.pd))),_xlpm.len,IF(_xlpm.pa>0,4,IF(_xlpm.pb>0,3,IF(_xlpm.pc>0,2,1))),_xlpm.wrd,IF(_xlpm.pos=0,_xlpm.kd,IF(_xlpm.md=1,INDEX(_xlpm.dP,_xlpm.pos),INDEX(_xlpm.dV,_xlpm.pos))),_xlpm.sep,IF(_xlpm.str="","",IF(_xlpm.md=1," "," / ")),(_xlpm.len-1)&"|"&_xlpm.str&_xlpm.sep&_xlpm.wrd))))),MID(_xlpm.res,FIND("|",_xlpm.res)+1,9999)))} | D203: {=IF($A203="","",_xlfn.LET(_xlpm.s,$A203,_xlpm.dC,'📚 Từ Vựng HSK'!$C$4:$C$1025,_xlpm.dP,'📚 Từ Vựng HSK'!$D$4:$D$1025,_xlpm.dV,'📚 Từ Vựng HSK'!$E$4:$E$1025,_xlpm.md,2,_xlpm.res,_xlfn.REDUCE("0|",_xlfn.SEQUENCE(LEN(_xlpm.s)),_xlfn.LAMBDA(_xlpm.acc,_xlpm.idx,_xlfn.LET(_xlpm.sk,VALUE(LEFT(_xlpm.acc,FIND("|",_xlpm.acc)-1)),_xlpm.str,MID(_xlpm.acc,FIND("|",_xlpm.acc)+1,9999),IF(_xlpm.sk>0,(_xlpm.sk-1)&"|"&_xlpm.str,_xlfn.LET(_xlpm.ka,MID(_xlpm.s,_xlpm.idx,4),_xlpm.kb,MID(_xlpm.s,_xlpm.idx,3),_xlpm.kc,MID(_xlpm.s,_xlpm.idx,2),_xlpm.kd,MID(_xlpm.s,_xlpm.idx,1),_xlpm.pa,IF(LEN(_xlpm.ka)=4,IFERROR(MATCH(_xlpm.ka,_xlpm.dC,0),0),0),_xlpm.pb,IF(LEN(_xlpm.kb)=3,IFERROR(MATCH(_xlpm.kb,_xlpm.dC,0),0),0),_xlpm.pc,IF(LEN(_xlpm.kc)=2,IFERROR(MATCH(_xlpm.kc,_xlpm.dC,0),0),0),_xlpm.pd,IFERROR(MATCH(_xlpm.kd,_xlpm.dC,0),0),_xlpm.pos,IF(_xlpm.pa>0,_xlpm.pa,IF(_xlpm.pb>0,_xlpm.pb,IF(_xlpm.pc>0,_xlpm.pc,_xlpm.pd))),_xlpm.len,IF(_xlpm.pa>0,4,IF(_xlpm.pb>0,3,IF(_xlpm.pc>0,2,1))),_xlpm.wrd,IF(_xlpm.pos=0,_xlpm.kd,IF(_xlpm.md=1,INDEX(_xlpm.dP,_xlpm.pos),INDEX(_xlpm.dV,_xlpm.pos))),_xlpm.sep,IF(_xlpm.str="","",IF(_xlpm.md=1," "," / ")),(_xlpm.len-1)&"|"&_xlpm.str&_xlpm.sep&_xlpm.wrd))))),MID(_xlpm.res,FIND("|",_xlpm.res)+1,9999)))}

Sheet 📚 Từ Vựng HSK
F1: =COUNTA(F4:F5780) | G1: =SUBTOTAL(103,G4:G5820) | H1: =COUNTIF(H4:H5780,"*Đúng*")&" đúng / "&COUNTA(G4:G5780)&" đã viết" | K1: =COUNTA(K4:K502) | L1: =COUNTA(L4:L502) | M1: =COUNTA(M4:M502) | N1: =COUNTA(N4:N502) | O1: =COUNTA(O4:O502) | P1: =COUNTA(P4:P502) | Q1: =COUNTA(Q4:Q502) | U1: =COUNTA(U4:U5780)&" từ"
A2: 🀄 TỪ VỰNG HSK1 + HSK2 — 575 TỪ | Chiết tự · Chủ đề · Tự chấm | Cập nhật 2026-08-02
A3: STT | B3: CẤP ĐỘ | C3: 🀄 HÁN TỰ | D3: 🔊 PINYIN | E3: 🇻🇳 TIẾNG VIỆT | F3: 📝 VIẾT THỬ 1 | G3: 📝 VIẾT THỬ 2 | H3: ✅ ĐÁP ÁN | I3: 🎵 AUDIO | J3: 🌐 YOUGLISH | K3: DAY 1 | L3: DAY 2 | M3: DAY 3 | N3: DAY 4 | O3: DAY 5 | P3: DAY 6 | Q3: DAY 7 | R3: 📅 NGÀY THÊM | S3: ⚠️ GHI CHÚ | T3: 🧩 CHIẾT TỰ & Ý NGHĨA HÁN TỰ | U3: 📂 CHỦ ĐỀ | V3: 💡 CÂU VÍ DỤ (Hán tự) | W3: 🔤 PINYIN & NGHĨA
A4: 7 | B4: HSK1 | C4: 白天 | D4: báitiān | E4: ban ngày | F4: 白天 | G4: 白天 | H4: =IF(TRIM($G4)="","",IF(EXACT(TRIM($G4),TRIM($C4)),"✅ Đúng","❌ Sai")) | I4: =HYPERLINK("https://translate.google.com/translate_tts?ie=UTF-8&tl=zh-CN&client=tw-ob&q=白天","▶") | J4: =HYPERLINK("https://youglish.com/pronounce/白天/chinese","🔍") | R4: 2026-06-17 | T4: 白 [BẠCH] · trắng; rõ ràng; uổng công ↳ Chiết tự: bộ 白 (bạch) — hình tia nắng đầu tiên ló rạng 天 [THIÊN] · trời, ngày, thiên nhiên ↳ Chiết tự: bộ 大 (đại – người) + 一 (nhất) trên đầu — khoảng cao nhất trên đầu người | U4: ⏰ Thời gian & Ngày tháng | V4: 白天很热，晚上很凉。 | W4: Báitiān hěn rè, wǎnshang hěn liáng. Ban ngày rất nóng, buổi tối thì mát.
A5: 11 | B5: HSK1 | C5: 半年 | D5: bànnián | E5: nửa năm | F5: 半年 | G5: 半年 | H5: =IF(TRIM($G5)="","",IF(EXACT(TRIM($G5),TRIM($C5)),"✅ Đúng","❌ Sai")) | I5: =HYPERLINK("https://translate.google.com/translate_tts?ie=UTF-8&tl=zh-CN&client=tw-ob&q=半年","▶") | J5: =HYPERLINK("https://youglish.com/pronounce/半年/chinese","🔍") | R5: 2026-06-17 | T5: 半 [BÁN] · một nửa, phân nửa ↳ Chiết tự: bộ 八 (bát – chia) + 牛 (ngưu – con trâu) — xẻ đôi con trâu 年 [NIÊN] · năm, tuổi ↳ Chiết tự: bộ 干 (can) + 丿 — hình người gánh lúa chín, một vụ lúa là một năm | U5: ⏰ Thời gian & Ngày tháng | V5: 我学中文已经半年了。 | W5: Wǒ xué Zhōngwén yǐjīng bànnián le. Tôi học tiếng Trung đã nửa năm rồi.
A6: 12 | B6: HSK1 | C6: 半天 | D6: bàntiān | E6: nửa ngày | F6: 半天 | G6: 半天 | H6: =IF(TRIM($G6)="","",IF(EXACT(TRIM($G6),TRIM($C6)),"✅ Đúng","❌ Sai")) | I6: =HYPERLINK("https://translate.google.com/translate_tts?ie=UTF-8&tl=zh-CN&client=tw-ob&q=半天","▶") | J6: =HYPERLINK("https://youglish.com/pronounce/半天/chinese","🔍") | R6: 2026-06-17 | T6: 半 [BÁN] · một nửa, phân nửa ↳ Chiết tự: bộ 八 (bát – chia) + 牛 (ngưu – con trâu) — xẻ đôi con trâu 天 [THIÊN] · trời, ngày, thiên nhiên ↳ Chiết tự: bộ 大 (đại – người) + 一 (nhất) trên đầu — khoảng cao nhất trên đầu người | U6: ⏰ Thời gian & Ngày tháng | V6: 我等了你半天。 | W6: Wǒ děng le nǐ bàntiān. Tôi đợi bạn cả nửa ngày.
A7: 76 | B7: HSK1+2 | C7: 点 | D7: diǎn | E7: ít, chút, hơi; giờ | G7: 点 | H7: =IF(TRIM($G7)="","",IF(EXACT(TRIM($G7),TRIM($C7)),"✅ Đúng","❌ Sai")) | I7: =HYPERLINK("https://translate.google.com/translate_tts?ie=UTF-8&tl=zh-CN&client=tw-ob&q=点","▶") | J7: =HYPERLINK("https://youglish.com/pronounce/点/chinese","🔍") | R7: 2026-06-17 | T7: 点 [ĐIỂM] · chấm, điểm; giờ; gọi món ↳ Chiết tự: giản thể của 點: bộ 灬 (hỏa – lửa) + 占 (chiếm – âm đọc) — chấm đen do lửa, đốm nhỏ | U7: ⏰ Thời gian & Ngày tháng | V7: 现在是八点半。 | W7: Xiànzài shì bā diǎn bàn. Bây giờ là tám giờ ba mươi.
A8: 147 | B8: HSK1 | C8: 后 | D8: hòu | E8: sau | F8: 后 | G8: 后 | H8: =IF(TRIM($G8)="","",IF(EXACT(TRIM($G8),TRIM($C8)),"✅ Đúng","❌ Sai")) | I8: =HYPERLINK("https://translate.google.com/translate_tts?ie=UTF-8&tl=zh-CN&client=tw-ob&q=后","▶") | J8: =HYPERLINK("https://youglish.com/pronounce/后/chinese","🔍") | R8: 2026-06-17 | T8: 后 [HẬU] · phía sau, sau này; hoàng hậu ↳ Chiết tự: bộ 厂 (hán) + 一 + 口 (khẩu) — người quay ngoái lại phía sau | U8: ⏰ Thời gian & Ngày tháng | V8: 吃饭后我去散步。 | W8: Chīfàn hòu wǒ qù sànbù. Sau khi ăn cơm tôi đi dạo.
A9: 149 | B9: HSK1 | C9: 后天 | D9: hòutiān | E9: ngày kia | F9: 后天 | G9: 后天 | H9: =IF(TRIM($G9)="","",IF(EXACT(TRIM($G9),TRIM($C9)),"✅ Đúng","❌ Sai")) | I9: =HYPERLINK("https://translate.google.com/translate_tts?ie=UTF-8&tl=zh-CN&client=tw-ob&q=后天","▶") | J9: =HYPERLINK("https://youglish.com/pronounce/后天/chinese","🔍") | R9: 2026-06-17 | T9: 后 [HẬU] · phía sau, sau này; hoàng hậu ↳ Chiết tự: bộ 厂 (hán) + 一 + 口 (khẩu) — người quay ngoái lại phía sau 天 [THIÊN] · trời, ngày, thiên nhiên ↳ Chiết tự: bộ 大 (đại – người) + 一 (nhất) trên đầu — khoảng cao nhất trên đầu người | U9: ⏰ Thời gian & Ngày tháng | V9: 后天是我的生日。 | W9: Hòutiān shì wǒ de shēngri. Ngày mai nữa là sinh nhật tôi.
A10: 172 | B10: HSK1 | C10: 间 | D10: jiān | E10: giữa | G10: 间 | H10: =IF(TRIM($G10)="","",IF(EXACT(TRIM($G10),TRIM($C10)),"✅ Đúng","❌ Sai")) | I10: =HYPERLINK("https://translate.google.com/translate_tts?ie=UTF-8&tl=zh-CN&client=tw-ob&q=间","▶") | J10: =HYPERLINK("https://youglish.com/pronounce/间/chinese","🔍") | R10: 2026-06-17 | T10: 间 [GIAN] · khoảng giữa; gian (lượng từ phòng) ↳ Chiết tự: giản thể của 間: bộ 门 (môn – cửa) + 日 (nhật – mặt trời) — nắng lọt qua khe cửa | U10: ⏰ Thời gian & Ngày tháng | V10: 这两天之间没有休息。 | W10: Zhè liǎng tiān zhījiān méiyǒu xiūxi. Giữa hai ngày này không có nghỉ.
A11: 180 | B11: HSK1 | C11: 今年 | D11: jīnnián | E11: năm nay | F11: 今年 | G11: 今年 | H11: =IF(TRIM($G11)="","",IF(EXACT(TRIM($G11),TRIM($C11)),"✅ Đúng","❌ Sai")) | I11: =HYPERLINK("https://translate.google.com/translate_tts?ie=UTF-8&tl=zh-CN&client=tw-ob&q=今年","▶") | J11: =HYPERLINK("https://youglish.com/pronounce/今年/chinese","🔍") | R11: 2026-06-17 | T11: 今 [KIM] · nay, hiện nay ↳ Chiết tự: bộ 人 (nhân) trùm lên 一 (nhất) — khoảnh khắc đang ở ngay dưới ta 年 [NIÊN] · năm, tuổi ↳ Chiết tự: bộ 干 (can) + 丿 — hình người gánh lúa chín, một vụ lúa là một năm | U11: ⏰ Thời gian & Ngày tháng | V11: 今年我二十岁。 | W11: Jīnnián wǒ èrshí suì. Năm nay tôi hai mươi tuổi.
A12: 181 | B12: HSK1+2 | C12: 今天 | D12: jīntiān | E12: ngày hôm nay | F12: 今天 | G12: 今天 | H12: =IF(TRIM($G12)="","",IF(EXACT(TRIM($G12),TRIM($C12)),"✅ Đúng","❌ Sai")) | I12: =HYPERLINK("https://translate.google.com/translate_tts?ie=UTF-8&tl=zh-CN&client=tw-ob&q=今天","▶") | J12: =HYPERLINK("https://youglish.com/pronounce/今天/chinese","🔍") | R12: 2026-06-17 | T12: 今 [KIM] · nay, hiện nay ↳ Chiết tự: bộ 人 (nhân) trùm lên 一 (nhất) — khoảnh khắc đang ở ngay dưới ta 天 [THIÊN] · trời, ngày, thiên nhiên ↳ Chiết tự: bộ 大 (đại – người) + 一 (nhất) trên đầu — khoảng cao nhất trên đầu người | U12: ⏰ Thời gian & Ngày tháng | V12: 今天天气很好。 | W12: Jīntiān tiānqì hěn hǎo. Hôm nay thời tiết rất đẹp.
A13: 222 | B13: HSK1+3 | C13: 马上 | D13: mǎshàng | E13: ngay lập tức | G13: 马上 | H13: =IF(TRIM($G13)="","",IF(EXACT(TRIM($G13),TRIM($C13)),"✅ Đúng","❌ Sai")) | I13: =HYPERLINK("https://translate.google.com/translate_tts?ie=UTF-8&tl=zh-CN&client=tw-ob&q=马上","▶") | J13: =HYPERLINK("https://youglish.com/pronounce/马上/chinese","🔍") | R13: 2026-06-17 | T13: 马 [MÃ] · con ngựa ↳ Chiết tự: giản thể của 馬: bộ 马 (mã) — hình ngựa có bờm và bốn vó 上 [THƯỢNG] · ở trên, lên, trước đó ↳ Chiết tự: bộ 一 (nhất – mặt đất) + vạch chỉ hướng lên — chữ chỉ sự | U13: ⏰ Thời gian & Ngày tháng | V13: 我马上就来。 | W13: Wǒ mǎshàng jiù lái. Tôi đến ngay đây.
A14: 233 | B14: HSK1 | C14: 每天 | D14: měitiān | E14: mỗi ngày | F14: 每天 | G14: 每天 | H14: =IF(TRIM($G14)="","",IF(EXACT(TRIM($G14),TRIM($C14)),"✅ Đúng","❌ Sai")) | I14: =HYPERLINK("https://translate.google.com/translate_tts?ie=UTF-8&tl=zh-CN&client=tw-ob&q=每天","▶") | J14: =HYPERLINK("https://youglish.com/pronounce/每天/chinese","🔍") | R14: 2026-06-17 | T14: 每 [MỖI] · mỗi, từng ↳ Chiết tự: bộ 母 (mẫu – người mẹ) + 丿 — từng người mẹ, từng cái một 天 [THIÊN] · trời, ngày, thiên nhiên ↳ Chiết tự: bộ 大 (đại – người) + 一 (nhất) trên đầu — khoảng cao nhất trên đầu người | U14: ⏰ Thời gian & Ngày tháng | V14: 我每天六点起床。 | W14: Wǒ měitiān liù diǎn qǐchuáng. Tôi dậy lúc sáu giờ mỗi ngày.
A15: 243 | B15: HSK1+2 | C15: 明天 | D15: míngtiān | E15: ngày mai | F15: 明天 | G15: 明天 | H15: =IF(TRIM($G15)="","",IF(EXACT(TRIM($G15),TRIM($C15)),"✅ Đúng","❌ Sai")) | I15: =HYPERLINK("https://translate.google.com/translate_tts?ie=UTF-8&tl=zh-CN&client=tw-ob&q=明天","▶") | J15: =HYPERLINK("https://youglish.com/pronounce/明天/chinese","🔍") | R15: 2026-06-17 | T15: 明 [MINH] · sáng sủa, rõ ràng; ngày mai ↳ Chiết tự: bộ 日 (nhật – mặt trời) + 月 (nguyệt – mặt trăng) — hai nguồn sáng hợp lại 天 [THIÊN] · trời, ngày, thiên nhiên ↳ Chiết tự: bộ 大 (đại – người) + 一 (nhất) trên đầu — khoảng cao nhất trên đầu người | U15: ⏰ Thời gian & Ngày tháng | V15: 明天我们去学校。 | W15: Míngtiān wǒmen qù xuéxiào. Mai chúng tôi đi đến trường.
A16: 263 | B16: HSK1+2 | C16: 年 | D16: nián | E16: năm | F16: 年 | G16: 年 | H16: =IF(TRIM($G16)="","",IF(EXACT(TRIM($G16),TRIM($C16)),"✅ Đúng","❌ Sai")) | I16: =HYPERLINK("https://translate.google.com/translate_tts?ie=UTF-8&tl=zh-CN&client=tw-ob&q=年","▶") | J16: =HYPERLINK("https://youglish.com/pronounce/年/chinese","🔍") | R16: 2026-06-17 | T16: 年 [NIÊN] · năm, tuổi ↳ Chiết tự: bộ 干 (can) + 丿 — hình người gánh lúa chín, một vụ lúa là một năm | U16: ⏰ Thời gian & Ngày tháng | V16: 我在中国住了三年。 | W16: Wǒ zài Zhōngguó zhù le sān nián. Tôi đã ở Trung Quốc ba năm.
A17: 283 | B17: HSK1 | C17: 前天 | D17: qiántiān | E17: hôm kia | F17: 前天 | G17: 前天 | H17: =IF(TRIM($G17)="","",IF(EXACT(TRIM($G17),TRIM($C17)),"✅ Đúng","❌ Sai")) | I17: =HYPERLINK("https://translate.google.com/translate_tts?ie=UTF-8&tl=zh-CN&client=tw-ob&q=前天","▶") | J17: =HYPERLINK("https://youglish.com/pronounce/前天/chinese","🔍") | R17: 2026-06-17 | T17: 前 [TIỀN] · phía trước, trước đây ↳ Chiết tự: bộ 丷 (bát) + 月 (nguyệt/nhục) + 刂 (đao đứng) — thuyền và bàn chân tiến lên phía trước 天 [THIÊN] · trời, ngày, thiên nhiên ↳ Chiết tự: bộ 大 (đại – người) + 一 (nhất) trên đầu — khoảng cao nhất trên đầu người | U17: ⏰ Thời gian & Ngày tháng | V17: 前天我看了一部电影。 | W17: Qiántiān wǒ kàn le yí bù diànyǐng. Hôm trước nữa tôi xem một bộ phim.
A18: 293 | B18: HSK1+2 | C18: 去年 | D18: qùnián | E18: năm ngoái | F18: 去年 | G18: 去年 | H18: =IF(TRIM($G18)="","",IF(EXACT(TRIM($G18),TRIM($C18)),"✅ Đúng","❌ Sai")) | I18: =HYPERLINK("https://translate.google.com/translate_tts?ie=UTF-8&tl=zh-CN&client=tw-ob&q=去年","▶") | J18: =HYPERLINK("https://youglish.com/pronounce/去年/chinese","🔍") | R18: 2026-06-17 | T18: 去 [KHỨ] · đi, rời khỏi; đã qua ↳ Chiết tự: bộ 土 (thổ – đất) + 厶 (tư) — người rời khỏi chỗ đất mà đi 年 [NIÊN] · năm, tuổi ↳ Chiết tự: bộ 干 (can) + 丿 — hình người gánh lúa chín, một vụ lúa là một năm | U18: ⏰ Thời gian & Ngày tháng | V18: 去年我去了北京。 | W18: Qùnián wǒ qù le Běijīng. Năm ngoái tôi đã đi Bắc Kinh.
A19: 298 | B19: HSK1+2 | C19: 日 | D19: rì | E19: ngày | F19: 日 | G19: 日 | H19: =IF(TRIM($G19)="","",IF(EXACT(TRIM($G19),TRIM($C19)),"✅ Đúng","❌ Sai")) | I19: =HYPERLINK("https://translate.google.com/translate_tts?ie=UTF-8&tl=zh-CN&client=tw-ob&q=日","▶") | J19: =HYPERLINK("https://youglish.com/pronounce/日/chinese","🔍") | R19: 2026-06-17 | T19: 日 [NHẬT] · mặt trời, ngày ↳ Chiết tự: bộ 日 (nhật) — hình mặt trời tròn có chấm giữa | U19: ⏰ Thời gian & Ngày tháng | V19: 今天是五月一日。 | W19: Jīntiān shì wǔ yuè yī rì. Hôm nay là ngày 1 tháng 5.
A20: 299 | B20: HSK1 | C20: 日期 | D20: rìqī | E20: ngày (xác định) | G20: 日期 | H20: =IF(TRIM($G20)="","",IF(EXACT(TRIM($G20),TRIM($C20)),"✅ Đúng","❌ Sai")) | I20: =HYPERLINK("https://translate.google.com/translate_tts?ie=UTF-8&tl=zh-CN&client=tw-ob&q=日期","▶") | J20: =HYPERLINK("https://youglish.com/pronounce/日期/chinese","🔍") | R20: 2026-06-17 | T20: 日 [NHẬT] · mặt trời, ngày ↳ Chiết tự: bộ 日 (nhật) — hình mặt trời tròn có chấm giữa 期 [KỲ] · kỳ hạn, thời kỳ, mong đợi ↳ Chiết tự: bộ 其 (kỳ – âm đọc) + 月 (nguyệt – tháng) — mốc tính theo tháng | U20: ⏰ Thời gian & Ngày tháng | V20: 请写上今天的日期。 | W20: Qǐng xiě shàng jīntiān de rìqī. Xin viết ngày tháng hôm nay vào.
A21: 312 | B21: HSK1+2 | C21: 上午 | D21: shàngwǔ | E21: buổi sáng | F21: 上午 | G21: 上午 | H21: =IF(TRIM($G21)="","",IF(EXACT(TRIM($G21),TRIM($C21)),"✅ Đúng","❌ Sai")) | I21: =HYPERLINK("https://translate.google.com/translate_tts?ie=UTF-8&tl=zh-CN&client=tw-ob&q=上午","▶") | J21: =HYPERLINK("https://youglish.com/pronounce/上午/chinese","🔍") | R21: 2026-06-17 | T21: 上 [THƯỢNG] · ở trên, lên, trước đó ↳ Chiết tự: bộ 一 (nhất – mặt đất) + vạch chỉ hướng lên — chữ chỉ sự 午 [NGỌ] · giờ Ngọ, buổi trưa ↳ Chiết tự: bộ 十 (thập) + 丿 (phiệt) — hình cái chày, mượn chỉ giữa trưa | U21: ⏰ Thời gian & Ngày tháng | V21: 上午我有两节课。 | W21: Shàngwǔ wǒ yǒu liǎng jié kè. Buổi sáng tôi có hai tiết học.
A22: 321 | B22: HSK1+2 | C22: 生日 | D22: shēngrì | E22: sinh nhật | G22: 生日 | H22: =IF(TRIM($G22)="","",IF(EXACT(TRIM($G22),TRIM($C22)),"✅ Đúng","❌ Sai")) | I22: =HYPERLINK("https://translate.google.com/translate_tts?ie=UTF-8&tl=zh-CN&client=tw-ob&q=生日","▶") | J22: =HYPERLINK("https://youglish.com/pronounce/生日/chinese","🔍") | R22: 2026-06-17 | T22: 生 [SINH] · sinh ra, sống; học trò; sống (chưa chín) ↳ Chiết tự: bộ 生 (sinh) — hình mầm cây nhú lên khỏi mặt đất 日 [NHẬT] · mặt trời, ngày ↳ Chiết tự: bộ 日 (nhật) — hình mặt trời tròn có chấm giữa | U22: ⏰ Thời gian & Ngày tháng | V22: 祝你生日快乐！ | W22: Zhù nǐ shēngri kuàilè! Chúc bạn sinh nhật vui vẻ!
A23: 323 | B23: HSK1+2 | C23: 时候 | D23: shíhòu | E23: thời gian, lúc | F23: 时候 | H23: =IF(TRIM($G23)="","",IF(EXACT(TRIM($G23),TRIM($C23)),"✅ Đúng","❌ Sai")) | I23: =HYPERLINK("https://translate.google.com/translate_tts?ie=UTF-8&tl=zh-CN&client=tw-ob&q=时候","▶") | J23: =HYPERLINK("https://youglish.com/pronounce/时候/chinese","🔍") | R23: 2026-06-17 | T23: 时 [THÌ / THỜI] · thời gian; giờ; lúc ↳ Chiết tự: giản thể của 時: bộ 日 (nhật – mặt trời) + 寸 (thốn – tấc) — đo bóng nắng mà tính giờ 候 [HẬU] · đợi chờ; thời điểm ↳ Chiết tự: bộ 亻 (nhân đứng – người) + 侯 (hầu – âm đọc) — người đứng canh đợi | U23: ⏰ Thời gian & Ngày tháng | V23: 小的时候我很爱唱歌。 | W23: Xiǎo de shíhou wǒ hěn ài chànggē. Lúc còn nhỏ tôi rất thích ca hát.
A24: 324 | B24: HSK1+2 | C24: 时间 | D24: shíjiān | E24: thời gian | F24: 时间 | G24: 时间 | H24: =IF(TRIM($G24)="","",IF(EXACT(TRIM($G24),TRIM($C24)),"✅ Đúng","❌ Sai")) | I24: =HYPERLINK("https://translate.google.com/translate_tts?ie=UTF-8&tl=zh-CN&client=tw-ob&q=时间","▶") | J24: =HYPERLINK("https://youglish.com/pronounce/时间/chinese","🔍") | R24: 2026-06-17 | T24: 时 [THÌ / THỜI] · thời gian; giờ; lúc ↳ Chiết tự: giản thể của 時: bộ 日 (nhật – mặt trời) + 寸 (thốn – tấc) — đo bóng nắng mà tính giờ 间 [GIAN] · khoảng giữa; gian (lượng từ phòng) ↳ Chiết tự: giản thể của 間: bộ 门 (môn – cửa) + 日 (nhật – mặt trời) — nắng lọt qua khe cửa | U24: ⏰ Thời gian & Ngày tháng | V24: 我没有时间休息。 | W24: Wǒ méiyǒu shíjiān xiūxi. Tôi không có thời gian nghỉ.
A25: 349 | B25: HSK1 | C25: 天 | D25: tiān | E25: trời | F25: 天 | G25: 天 | H25: =IF(TRIM($G25)="","",IF(EXACT(TRIM($G25),TRIM($C25)),"✅ Đúng","❌ Sai")) | I25: =HYPERLINK("https://translate.google.com/translate_tts?ie=UTF-8&tl=zh-CN&client=tw-ob&q=天","▶") | J25: =HYPERLINK("https://youglish.com/pronounce/天/chinese","🔍") | R25: 2026-06-17 | T25: 天 [THIÊN] · trời, ngày, thiên nhiên ↳ Chiết tự: bộ 大 (đại – người) + 一 (nhất) trên đầu — khoảng cao nhất trên đầu người | U25: ⏰ Thời gian & Ngày tháng | V25: 一个星期有七天。 | W25: Yí ge xīngqī yǒu qī tiān. Một tuần có bảy ngày.
A26: 362 | B26: HSK1 | C26: 晚 | D26: wǎn | E26: buổi tối, muộn | F26: 玩 | G26: 晚 | H26: =IF(TRIM($G26)="","",IF(EXACT(TRIM($G26),TRIM($C26)),"✅ Đúng","❌ Sai")) | I26: =HYPERLINK("https://translate.google.com/translate_tts?ie=UTF-8&tl=zh-CN&client=tw-ob&q=晚","▶") | J26: =HYPERLINK("https://youglish.com/pronounce/晚/chinese","🔍") | R26: 2026-06-17 | T26: 晚 [VÃN] · muộn, tối, buổi tối ↳ Chiết tự: bộ 日 (nhật – mặt trời) + 免 (miễn – âm đọc) — mặt trời đã khuất | U26: ⏰ Thời gian & Ngày tháng | V26: 对不起，我来晚了。 | W26: Duìbuqǐ, wǒ lái wǎn le. Xin lỗi, tôi đến muộn rồi.
A27: 364 | B27: HSK1+2 | C27: 晚上 | D27: wǎnshang | E27: buổi tối | F27: 晚上 | G27: 晚上 | H27: =IF(TRIM($G27)="","",IF(EXACT(TRIM($G27),TRIM($C27)),"✅ Đúng","❌ Sai")) | I27: =HYPERLINK("https://translate.google.com/translate_tts?ie=UTF-8&tl=zh-CN&client=tw-ob&q=晚上","▶") | J27: =HYPERLINK("https://youglish.com/pronounce/晚上/chinese","🔍") | R27: 2026-06-17 | T27: 晚 [VÃN] · muộn, tối, buổi tối ↳ Chiết tự: bộ 日 (nhật – mặt trời) + 免 (miễn – âm đọc) — mặt trời đã khuất 上 [THƯỢNG] · ở trên, lên, trước đó ↳ Chiết tự: bộ 一 (nhất – mặt đất) + vạch chỉ hướng lên — chữ chỉ sự | U27: ⏰ Thời gian & Ngày tháng | V27: 晚上我常常看书。 | W27: Wǎnshang wǒ chángcháng kànshū. Buổi tối tôi thường đọc sách.
A28: 385 | B28: HSK1+2 | C28: 下午 | D28: xiàwǔ | E28: buổi chiều | F28: 下午 | G28: 下午 | H28: =IF(TRIM($G28)="","",IF(EXACT(TRIM($G28),TRIM($C28)),"✅ Đúng","❌ Sai")) | I28: =HYPERLINK("https://translate.google.com/translate_tts?ie=UTF-8&tl=zh-CN&client=tw-ob&q=下午","▶") | J28: =HYPERLINK("https://youglish.com/pronounce/下午/chinese","🔍") | R28: 2026-06-17 | T28: 下 [HẠ] · ở dưới, xuống, kém hơn ↳ Chiết tự: bộ 一 (nhất – mặt đất) + vạch chỉ hướng xuống — chữ chỉ sự 午 [NGỌ] · giờ Ngọ, buổi trưa ↳ Chiết tự: bộ 十 (thập) + 丿 (phiệt) — hình cái chày, mượn chỉ giữa trưa | U28: ⏰ Thời gian & Ngày tháng | V28: 下午三点我们见面。 | W28: Xiàwǔ sān diǎn wǒmen jiànmiàn. Ba giờ chiều chúng ta gặp nhau.
A29: 387 | B29: HSK1+3 | C29: 先 | D29: xiān | E29: trước | G29: 先 | H29: =IF(TRIM($G29)="","",IF(EXACT(TRIM($G29),TRIM($C29)),"✅ Đúng","❌ Sai")) | I29: =HYPERLINK("https://translate.google.com/translate_tts?ie=UTF-8&tl=zh-CN&client=tw-ob&q=先","▶") | J29: =HYPERLINK("https://youglish.com/pronounce/先/chinese","🔍") | R29: 2026-06-17 | T29: 先 [TIÊN] · trước, trước tiên, tổ tiên ↳ Chiết tự: bộ 之 (chi – bàn chân) + 儿 (nhân đi – người) — bàn chân vượt lên trước người | U29: ⏰ Thời gian & Ngày tháng | V29: 你先走，我一会儿到。 | W29: Nǐ xiān zǒu, wǒ yíhuìr dào. Bạn đi trước, tôi tới ngay.
A30: 389 | B30: HSK1+2 | C30: 现在 | D30: xiànzài | E30: hiện tại, bây giờ | G30: 现在 | H30: =IF(TRIM($G30)="","",IF(EXACT(TRIM($G30),TRIM($C30)),"✅ Đúng","❌ Sai")) | I30: =HYPERLINK("https://translate.google.com/translate_tts?ie=UTF-8&tl=zh-CN&client=tw-ob&q=现在","▶") | J30: =HYPERLINK("https://youglish.com/pronounce/现在/chinese","🔍") | R30: 2026-06-17 | T30: 现 [HIỆN] · hiện ra, hiện tại ↳ Chiết tự: giản thể của 現: bộ 王 (ngọc) + 见 (kiến – trông thấy) — ngọc lộ ra trước mắt 在 [TẠI] · ở tại, đang ↳ Chiết tự: bộ 土 (thổ – đất) + 才 (tài – âm đọc) — mầm cây tồn tại trên đất | U30: ⏰ Thời gian & Ngày tháng | V30: 现在几点了？ | W30: Xiànzài jǐ diǎn le? Bây giờ mấy giờ rồi?
A31: 395 | B31: HSK1+2 | C31: 小时 | D31: xiǎoshí | E31: giờ đồng hồ | G31: 小时 | H31: =IF(TRIM($G31)="","",IF(EXACT(TRIM($G31),TRIM($C31)),"✅ Đúng","❌ Sai")) | I31: =HYPERLINK("https://translate.google.com/translate_tts?ie=UTF-8&tl=zh-CN&client=tw-ob&q=小时","▶") | J31: =HYPERLINK("https://youglish.com/pronounce/小时/chinese","🔍") | R31: 2026-06-17 | T31: 小 [TIỂU] · nhỏ bé ↳ Chiết tự: bộ 小 (tiểu) — ba nét tách vụn ra, ý nhỏ 时 [THÌ / THỜI] · thời gian; giờ; lúc ↳ Chiết tự: giản thể của 時: bộ 日 (nhật – mặt trời) + 寸 (thốn – tấc) — đo bóng nắng mà tính giờ | U31: ⏰ Thời gian & Ngày tháng | V31: 我每天工作八小时。 | W31: Wǒ měitiān gōngzuò bā xiǎoshí. Tôi làm việc tám tiếng mỗi ngày.
A32: 402 | B32: HSK1 | C32: 新年 | D32: xīnnián | E32: năm mới | F32: 新年 | G32: 新年 | H32: =IF(TRIM($G32)="","",IF(EXACT(TRIM($G32),TRIM($C32)),"✅ Đúng","❌ Sai")) | I32: =HYPERLINK("https://translate.google.com/translate_tts?ie=UTF-8&tl=zh-CN&client=tw-ob&q=新年","▶") | J32: =HYPERLINK("https://youglish.com/pronounce/新年/chinese","🔍") | R32: 2026-06-17 | T32: 新 [TÂN] · mới mẻ ↳ Chiết tự: bộ 亲 (thân) + 斤 (cân – cái rìu) — lấy rìu đẽo cây tươi, gỗ mới 年 [NIÊN] · năm, tuổi ↳ Chiết tự: bộ 干 (can) + 丿 — hình người gánh lúa chín, một vụ lúa là một năm | U32: ⏰ Thời gian & Ngày tháng | V32: 新年快乐！ | W32: Xīnnián kuàilè! Chúc mừng năm mới!
A33: 403 | B33: HSK1+2 | C33: 星期 | D33: xīngqī | E33: tuần, thứ | F33: 星期 | G33: 星期 | H33: =IF(TRIM($G33)="","",IF(EXACT(TRIM($G33),TRIM($C33)),"✅ Đúng","❌ Sai")) | I33: =HYPERLINK("https://translate.google.com/translate_tts?ie=UTF-8&tl=zh-CN&client=tw-ob&q=星期","▶") | J33: =HYPERLINK("https://youglish.com/pronounce/星期/chinese","🔍") | R33: 2026-06-17 | T33: 星 [TINH] · ngôi sao ↳ Chiết tự: bộ 日 (nhật – vầng sáng) + 生 (sinh – âm đọc) — những đốm sáng sinh ra trên trời 期 [KỲ] · kỳ hạn, thời kỳ, mong đợi ↳ Chiết tự: bộ 其 (kỳ – âm đọc) + 月 (nguyệt – tháng) — mốc tính theo tháng | U33: ⏰ Thời gian & Ngày tháng | V33: 下个星期我很忙。 | W33: Xià ge xīngqī wǒ hěn máng. Tuần sau tôi rất bận.
A34: 404 | B34: HSK1 | C34: 星期日 | D34: xīngqīrì | E34: chủ nhật | F34: 星期日 | G34: 星期日 | H34: =IF(TRIM($G34)="","",IF(EXACT(TRIM($G34),TRIM($C34)),"✅ Đúng","❌ Sai")) | I34: =HYPERLINK("https://translate.google.com/translate_tts?ie=UTF-8&tl=zh-CN&client=tw-ob&q=星期日","▶") | J34: =HYPERLINK("https://youglish.com/pronounce/星期日/chinese","🔍") | R34: 2026-06-17 | T34: 星 [TINH] · ngôi sao ↳ Chiết tự: bộ 日 (nhật – vầng sáng) + 生 (sinh – âm đọc) — những đốm sáng sinh ra trên trời 期 [KỲ] · kỳ hạn, thời kỳ, mong đợi ↳ Chiết tự: bộ 其 (kỳ – âm đọc) + 月 (nguyệt – tháng) — mốc tính theo tháng 日 [NHẬT] · mặt trời, ngày ↳ Chiết tự: bộ 日 (nhật) — hình mặt trời tròn có chấm giữa | U34: ⏰ Thời gian & Ngày tháng | V34: 星期日我不上班。 | W34: Xīngqīrì wǒ bú shàngbān. Chủ nhật tôi không đi làm.
A35: 405 | B35: HSK1 | C35: 星期天 | D35: xīngqītiān | E35: chủ nhật | F35: 星期天 | G35: 星期天 | H35: =IF(TRIM($G35)="","",IF(EXACT(TRIM($G35),TRIM($C35)),"✅ Đúng","❌ Sai")) | I35: =HYPERLINK("https://translate.google.com/translate_tts?ie=UTF-8&tl=zh-CN&client=tw-ob&q=星期天","▶") | J35: =HYPERLINK("https://youglish.com/pronounce/星期天/chinese","🔍") | R35: 2026-06-17 | T35: 星 [TINH] · ngôi sao ↳ Chiết tự: bộ 日 (nhật – vầng sáng) + 生 (sinh – âm đọc) — những đốm sáng sinh ra trên trời 期 [KỲ] · kỳ hạn, thời kỳ, mong đợi ↳ Chiết tự: bộ 其 (kỳ – âm đọc) + 月 (nguyệt – tháng) — mốc tính theo tháng 天 [THIÊN] · trời, ngày, thiên nhiên ↳ Chiết tự: bộ 大 (đại – người) + 一 (nhất) trên đầu — khoảng cao nhất trên đầu người | U35: ⏰ Thời gian & Ngày tháng | V35: 星期天我们去公园。 | W35: Xīngqītiān wǒmen qù gōngyuán. Chủ nhật chúng tôi đi công viên.
A36: 422 | B36: HSK1+3 | C36: 一会儿 | D36: yíhuìr | E36: một chốc | H36: =IF(TRIM($G36)="","",IF(EXACT(TRIM($G36),TRIM($C36)),"✅ Đúng","❌ Sai")) | I36: =HYPERLINK("https://translate.google.com/translate_tts?ie=UTF-8&tl=zh-CN&client=tw-ob&q=一会儿","▶") | J36: =HYPERLINK("https://youglish.com/pronounce/一会儿/chinese","🔍") | R36: 2026-06-17 | T36: 一 [NHẤT] · số một, thứ nhất, toàn bộ ↳ Chiết tự: một nét ngang 一 (nhất) — chữ chỉ sự, vạch một gạch là số 1 会 [HỘI] · biết làm; họp, hội ↳ Chiết tự: giản thể của 會: bộ 人 (nhân – người) + 云 (vân – mây) — người tụ như mây thì thành hội, hội đủ thì biết 儿 [NHI] · trẻ con; hậu tố danh từ ↳ Chiết tự: giản thể của 兒: bộ 儿 (nhân đi – hai chân người) — hình trẻ thóp đầu chưa liền | U36: ⏰ Thời gian & Ngày tháng | V36: 请等一会儿。 | W36: Qǐng děng yíhuìr. Xin đợi một lát.
A37: 434 | B37: HSK1 | C37: 有时候 | D37: yǒushíhou | E37: có lúc | G37: 有时候 | H37: =IF(TRIM($G37)="","",IF(EXACT(TRIM($G37),TRIM($C37)),"✅ Đúng","❌ Sai")) | I37: =HYPERLINK("https://translate.google.com/translate_tts?ie=UTF-8&tl=zh-CN&client=tw-ob&q=有时候","▶") | J37: =HYPERLINK("https://youglish.com/pronounce/有时候/chinese","🔍") | R37: 2026-06-17 | T37: 有 [HỮU] · có, sở hữu ↳ Chiết tự: bộ 又 (hựu – bàn tay) + 月 (nhục – miếng thịt) — tay cầm miếng thịt là có của 时 [THÌ / THỜI] · thời gian; giờ; lúc ↳ Chiết tự: giản thể của 時: bộ 日 (nhật – mặt trời) + 寸 (thốn – tấc) — đo bóng nắng mà tính giờ 候 [HẬU] · đợi chờ; thời điểm ↳ Chiết tự: bộ 亻 (nhân đứng – người) + 侯 (hầu – âm đọc) — người đứng canh đợi | U37: ⏰ Thời gian & Ngày tháng | V37: 有时候我自己做饭。 | W37: Yǒushíhou wǒ zìjǐ zuòfàn. Có lúc tôi tự nấu cơm.
A38: 442 | B38: HSK1+2 | C38: 月 | D38: yuè | E38: tháng, mặt trăng | F38: 月 | G38: 月 | H38: =IF(TRIM($G38)="","",IF(EXACT(TRIM($G38),TRIM($C38)),"✅ Đúng","❌ Sai")) | I38: =HYPERLINK("https://translate.google.com/translate_tts?ie=UTF-8&tl=zh-CN&client=tw-ob&q=月","▶") | J38: =HYPERLINK("https://youglish.com/pronounce/月/chinese","🔍") | R38: 2026-06-17 | T38: 月 [NGUYỆT] · mặt trăng, tháng ↳ Chiết tự: bộ 月 (nguyệt) — hình vầng trăng khuyết | U38: ⏰ Thời gian & Ngày tháng | V38: 一年有十二个月。 | W38: Yì nián yǒu shí'èr ge yuè. Một năm có mười hai tháng.
A39: 443 | B39: HSK1+3 | C39: 再 | D39: zài | E39: lại | H39: =IF(TRIM($G39)="","",IF(EXACT(TRIM($G39),TRIM($C39)),"✅ Đúng","❌ Sai")) | I39: =HYPERLINK("https://translate.google.com/translate_tts?ie=UTF-8&tl=zh-CN&client=tw-ob&q=再","▶") | J39: =HYPERLINK("https://youglish.com/pronounce/再/chinese","🔍") | R39: 2026-06-17 | T39: 再 [TÁI] · lại, lần nữa ↳ Chiết tự: bộ 冂 (quynh) + 一 (nhất) + 土 — chồng thêm một lớp nữa | U39: ⏰ Thời gian & Ngày tháng | V39: 请再说一次。 | W39: Qǐng zài shuō yí cì. Xin nói lại một lần nữa.
A40: 447 | B40: HSK1 | C40: 早 | D40: zǎo | E40: sớm | F40: 早 | G40: 早 | H40: =IF(TRIM($G40)="","",IF(EXACT(TRIM($G40),TRIM($C40)),"✅ Đúng","❌ Sai")) | I40: =HYPERLINK("https://translate.google.com/translate_tts?ie=UTF-8&tl=zh-CN&client=tw-ob&q=早","▶") | J40: =HYPERLINK("https://youglish.com/pronounce/早/chinese","🔍") | R40: 2026-06-17 | T40: 早 [TẢO] · sớm, buổi sáng ↳ Chiết tự: bộ 日 (nhật – mặt trời) + 十 (thập) — mặt trời vừa nhô lên ngọn cỏ | U40: ⏰ Thời gian & Ngày tháng | V40: 你今天来得很早。 | W40: Nǐ jīntiān lái de hěn zǎo. Hôm nay bạn đến rất sớm.
A41: 449 | B41: HSK1+2 | C41: 早上 | D41: zǎoshàng | E41: buổi sáng | F41: 早上 | G41: 早上 | H41: =IF(TRIM($G41)="","",IF(EXACT(TRIM($G41),TRIM($C41)),"✅ Đúng","❌ Sai")) | I41: =HYPERLINK("https://translate.google.com/translate_tts?ie=UTF-8&tl=zh-CN&client=tw-ob&q=早上","▶") | J41: =HYPERLINK("https://youglish.com/pronounce/早上/chinese","🔍") | R41: 2026-06-17 | T41: 早 [TẢO] · sớm, buổi sáng ↳ Chiết tự: bộ 日 (nhật – mặt trời) + 十 (thập) — mặt trời vừa nhô lên ngọn cỏ 上 [THƯỢNG] · ở trên, lên, trước đó ↳ Chiết tự: bộ 一 (nhất – mặt đất) + vạch chỉ hướng lên — chữ chỉ sự | U41: ⏰ Thời gian & Ngày tháng | V41: 早上我喝一杯牛奶。 | W41: Zǎoshang wǒ hē yì bēi niúnǎi. Buổi sáng tôi uống một cốc sữa.
A42: 470 | B42: HSK1+2 | C42: 中午 | D42: zhōngwǔ | E42: buổi trưa | F42: 中午 | G42: 中午 | H42: =IF(TRIM($G42)="","",IF(EXACT(TRIM($G42),TRIM($C42)),"✅ Đúng","❌ Sai")) | I42: =HYPERLINK("https://translate.google.com/translate_tts?ie=UTF-8&tl=zh-CN&client=tw-ob&q=中午","▶") | J42: =HYPERLINK("https://youglish.com/pronounce/中午/chinese","🔍") | R42: 2026-06-17 | T42: 中 [TRUNG] · ở giữa; Trung Quốc ↳ Chiết tự: bộ 丨 (cổn – nét sổ) xuyên chính giữa 口 (khẩu – khung vuông) — chữ chỉ sự 午 [NGỌ] · giờ Ngọ, buổi trưa ↳ Chiết tự: bộ 十 (thập) + 丿 (phiệt) — hình cái chày, mượn chỉ giữa trưa | U42: ⏰ Thời gian & Ngày tháng | V42: 中午我在公司吃饭。 | W42: Zhōngwǔ wǒ zài gōngsī chīfàn. Buổi trưa tôi ăn cơm ở công ty.
A43: 484 | B43: HSK1+3 | C43: 最后 | D43: zuìhòu | E43: cuối cùng | G43: 最后 | H43: =IF(TRIM($G43)="","",IF(EXACT(TRIM($G43),TRIM($C43)),"✅ Đúng","❌ Sai")) | I43: =HYPERLINK("https://translate.google.com/translate_tts?ie=UTF-8&tl=zh-CN&client=tw-ob&q=最后","▶") | J43: =HYPERLINK("https://youglish.com/pronounce/最后/chinese","🔍") | R43: 2026-06-17 | T43: 最 [TỐI] · nhất, hơn cả ↳ Chiết tự: bộ 曰 (viết) + 取 (thủ – lấy) — chọn lấy cái đứng đầu 后 [HẬU] · phía sau, sau này; hoàng hậu ↳ Chiết tự: bộ 厂 (hán) + 一 + 口 (khẩu) — người quay ngoái lại phía sau | U43: ⏰ Thời gian & Ngày tháng | V43: 最后我们决定去海边。 | W43: Zuìhòu wǒmen juédìng qù hǎibiān. Cuối cùng chúng tôi quyết định đi biển.
A44: 485 | B44: HSK1+2 | C44: 昨天 | D44: zuótiān | E44: hôm qua | F44: 昨天 | G44: 昨天 | H44: =IF(TRIM($G44)="","",IF(EXACT(TRIM($G44),TRIM($C44)),"✅ Đúng","❌ Sai")) | I44: =HYPERLINK("https://translate.google.com/translate_tts?ie=UTF-8&tl=zh-CN&client=tw-ob&q=昨天","▶") | J44: =HYPERLINK("https://youglish.com/pronounce/昨天/chinese","🔍") | R44: 2026-06-17 | T44: 昨 [TẠC] · hôm qua, ngày trước ↳ Chiết tự: bộ 日 (nhật – ngày) + 乍 (sạ – vừa mới) — cái ngày vừa qua 天 [THIÊN] · trời, ngày, thiên nhiên ↳ Chiết tự: bộ 大 (đại – người) + 一 (nhất) trên đầu — khoảng cao nhất trên đầu người | U44: ⏰ Thời gian & Ngày tháng | V44: 昨天我没去上课。 | W44: Zuótiān wǒ méi qù shàngkè. Hôm qua tôi không đi học.
A45: 501 | B45: HSK2 | C45: 分钟 | D45: fēnzhōng | E45: phút | G45: 分钟 | H45: =IF(TRIM($G45)="","",IF(EXACT(TRIM($G45),TRIM($C45)),"✅ Đúng","❌ Sai")) | I45: ▶ | J45: 🔍 | R45: 46236 | T45: 分 [PHÂN] · chia; phút; phần ↳ Chiết tự: bộ 八 (bát – chia) + 刀 (đao – con dao) — lấy dao cắt làm hai 钟 [CHUNG] · cái chuông; đồng hồ, phút ↳ Chiết tự: giản thể của 鐘: bộ 钅 (kim – kim loại) + 中 (trung – âm đọc) — chuông đồng báo giờ | U45: ⏰ Thời gian & Ngày tháng | V45: 请给我五分钟。 | W45: Qǐng gěi wǒ wǔ fēnzhōng. Cho tôi năm phút.
A46: 564 | B46: HSK2 | C46: 已经 | D46: yǐjīng | E46: đã, đã rồi | G46: 已经 | H46: =IF(TRIM($G46)="","",IF(EXACT(TRIM($G46),TRIM($C46)),"✅ Đúng","❌ Sai")) | I46: ▶ | J46: 🔍 | R46: 46236 | T46: 已 [DĨ] · đã, đã rồi ↳ Chiết tự: bộ 己 (kỷ) biến thể — chữ chỉ sự, việc đã dứt 经 [KINH] · trải qua, đã; kinh điển; sợi dọc ↳ Chiết tự: giản thể của 經: bộ 纟 (mịch – sợi tơ) + 巠 (kinh – âm đọc) — sợi dọc của tấm vải, cái xuyên suốt | U46: ⏰ Thời gian & Ngày tháng | V46: 他已经走了。 | W46: Tā yǐjīng zǒu le. Anh ấy đã đi rồi.
A47: 28 | B47: HSK1 | C47: 病 | D47: bìng | E47: bệnh | F47: 病 | G47: 病 | H47: =IF(TRIM($G47)="","",IF(EXACT(TRIM($G47),TRIM($C47)),"✅ Đúng","❌ Sai")) | I47: =HYPERLINK("https://translate.google.com/translate_tts?ie=UTF-8&tl=zh-CN&client=tw-ob&q=病","▶") | J47: =HYPERLINK("https://youglish.com/pronounce/病/chinese","🔍") | R47: 2026-06-17 | T47: 病 [BỆNH] · bệnh tật, ốm ↳ Chiết tự: bộ 疒 (nạch – người ốm dựa giường) + 丙 (bính – âm đọc) — nằm liệt trên giường bệnh | U47: ⚕️ Sức khỏe & Cơ thể | V47: 他的病好了。 | W47: Tā de bìng hǎo le. Bệnh của anh ấy đã khỏi.
A48: 193 | B48: HSK1 | C48: 看病 | D48: kànbìng | E48: khám bệnh | F48: 看病 | G48: 看病 | H48: =IF(TRIM($G48)="","",IF(EXACT(TRIM($G48),TRIM($C48)),"✅ Đúng","❌ Sai")) | I48: =HYPERLINK("https://translate.google.com/translate_tts?ie=UTF-8&tl=zh-CN&client=tw-ob&q=看病","▶") | J48: =HYPERLINK("https://youglish.com/pronounce/看病/chinese","🔍") | R48: 2026-06-17 | T48: 看 [KHÁN] · nhìn, xem, trông coi ↳ Chiết tự: bộ 手 (thủ – bàn tay) đặt trên 目 (mục – con mắt) — che tay lên mắt mà ngóng 病 [BỆNH] · bệnh tật, ốm ↳ Chiết tự: bộ 疒 (nạch – người ốm dựa giường) + 丙 (bính – âm đọc) — nằm liệt trên giường bệnh | U48: ⚕️ Sức khỏe & Cơ thể | V48: 我去医院看病。 | W48: Wǒ qù yīyuàn kànbìng. Tôi đi bệnh viện khám bệnh.
A49: 203 | B49: HSK1+3 | C49: 口 | D49: kǒu | E49: miệng | F49: 口 | G49: 口 | H49: =IF(TRIM($G49)="","",IF(EXACT(TRIM($G49),TRIM($C49)),"✅ Đúng","❌ Sai")) | I49: =HYPERLINK("https://translate.google.com/translate_tts?ie=UTF-8&tl=zh-CN&client=tw-ob&q=口","▶") | J49: =HYPERLINK("https://youglish.com/pronounce/口/chinese","🔍") | R49: 2026-06-17 | T49: 口 [KHẨU] · cái miệng; cửa, nhân khẩu ↳ Chiết tự: bộ 口 (khẩu) — hình cái miệng mở | U49: ⚕️ Sức khỏe & Cơ thể | V49: 请张开口。 | W49: Qǐng zhāngkāi kǒu. Xin mở miệng ra.
A50: 317 | B50: HSK1+2 | C50: 身体 | D50: shēntǐ | E50: cơ thể, sức khỏe | H50: =IF(TRIM($G50)="","",IF(EXACT(TRIM($G50),TRIM($C50)),"✅ Đúng","❌ Sai")) | I50: =HYPERLINK("https://translate.google.com/translate_tts?ie=UTF-8&tl=zh-CN&client=tw-ob&q=身体","▶") | J50: =HYPERLINK("https://youglish.com/pronounce/身体/chinese","🔍") | R50: 2026-06-17 | T50: 身 [THÂN] · thân thể, bản thân ↳ Chiết tự: bộ 身 (thân) — hình người có bụng lớn, chỉ cơ thể 体 [THỂ] · thân thể, hình thể ↳ Chiết tự: giản thể của 體: bộ 亻 (nhân đứng – người) + 本 (bản – gốc) — cái gốc của con người | U50: ⚕️ Sức khỏe & Cơ thể | V50: 你要注意身体。 | W50: Nǐ yào zhùyì shēntǐ. Bạn phải chú ý sức khỏe.
A51: 319 | B51: HSK1+2 | C51: 生病 | D51: shēngbìng | E51: bị ốm | H51: =IF(TRIM($G51)="","",IF(EXACT(TRIM($G51),TRIM($C51)),"✅ Đúng","❌ Sai")) | I51: =HYPERLINK("https://translate.google.com/translate_tts?ie=UTF-8&tl=zh-CN&client=tw-ob&q=生病","▶") | J51: =HYPERLINK("https://youglish.com/pronounce/生病/chinese","🔍") | R51: 2026-06-17 | T51: 生 [SINH] · sinh ra, sống; học trò; sống (chưa chín) ↳ Chiết tự: bộ 生 (sinh) — hình mầm cây nhú lên khỏi mặt đất 病 [BỆNH] · bệnh tật, ốm ↳ Chiết tự: bộ 疒 (nạch – người ốm dựa giường) + 丙 (bính – âm đọc) — nằm liệt trên giường bệnh | U51: ⚕️ Sức khỏe & Cơ thể | V51: 妈妈生病了。 | W51: Māma shēngbìng le. Mẹ bị bệnh rồi.
A52: 329 | B52: HSK1 | C52: 手 | D52: shǒu | E52: tay | F52: 收 | G52: 手 | H52: =IF(TRIM($G52)="","",IF(EXACT(TRIM($G52),TRIM($C52)),"✅ Đúng","❌ Sai")) | I52: =HYPERLINK("https://translate.google.com/translate_tts?ie=UTF-8&tl=zh-CN&client=tw-ob&q=手","▶") | J52: =HYPERLINK("https://youglish.com/pronounce/手/chinese","🔍") | R52: 2026-06-17 | T52: 手 [THỦ] · bàn tay; người làm nghề ↳ Chiết tự: bộ 手 (thủ) — hình bàn tay xòe năm ngón | U52: ⚕️ Sức khỏe & Cơ thể | V52: 请洗手。 | W52: Qǐng xǐ shǒu. Xin hãy rửa tay.
A53: 560 | B53: HSK2 | C53: 眼睛 | D53: yǎnjing | E53: mắt | H53: =IF(TRIM($G53)="","",IF(EXACT(TRIM($G53),TRIM($C53)),"✅ Đúng","❌ Sai")) | I53: ▶ | J53: 🔍 | R53: 46236 | T53: 眼 [NHÃN] · con mắt ↳ Chiết tự: bộ 目 (mục – con mắt) + 艮 (cấn – âm đọc) — hình thanh 睛 [TINH] · con ngươi (眼睛 = mắt) ↳ Chiết tự: bộ 目 (mục – con mắt) + 青 (thanh – âm đọc) — hình thanh | U53: ⚕️ Sức khỏe & Cơ thể | V53: 她的眼睛很大。 | W53: Tā de yǎnjing hěn dà. Mắt cô ấy rất to.
A54: 562 | B54: HSK2 | C54: 药 | D54: yào | E54: thuốc | H54: =IF(TRIM($G54)="","",IF(EXACT(TRIM($G54),TRIM($C54)),"✅ Đúng","❌ Sai")) | I54: ▶ | J54: 🔍 | R54: 46236 | T54: 药 [DƯỢC] · thuốc, dược phẩm ↳ Chiết tự: giản thể của 藥: bộ 艹 (thảo – cây cỏ) + 约 (ước – âm đọc) — cây cỏ chữa bệnh | U54: ⚕️ Sức khỏe & Cơ thể | V54: 吃了药就好了。 | W54: Chī le yào jiù hǎo le. Uống thuốc là khỏi thôi.
A55: 110 | B55: HSK1 | C55: 风 | D55: fēng | E55: gió | F55: 风 | G55: 风 | H55: =IF(TRIM($G55)="","",IF(EXACT(TRIM($G55),TRIM($C55)),"✅ Đúng","❌ Sai")) | I55: =HYPERLINK("https://translate.google.com/translate_tts?ie=UTF-8&tl=zh-CN&client=tw-ob&q=风","▶") | J55: =HYPERLINK("https://youglish.com/pronounce/风/chinese","🔍") | R55: 2026-06-17 | T55: 风 [PHONG] · gió; phong cách ↳ Chiết tự: giản thể của 風: bộ 几 (kỷ) + 虫 (trùng) — luồng khí cuốn sinh ra sâu bọ | U55: 🌤️ Thiên nhiên & Thời tiết | V55: 今天风很大。 | W55: Jīntiān fēng hěn dà. Hôm nay gió rất to.
A56: 302 | B56: HSK1 | C56: 山 | D56: shān | E56: núi | F56: 山 | G56: 山 | H56: =IF(TRIM($G56)="","",IF(EXACT(TRIM($G56),TRIM($C56)),"✅ Đúng","❌ Sai")) | I56: =HYPERLINK("https://translate.google.com/translate_tts?ie=UTF-8&tl=zh-CN&client=tw-ob&q=山","▶") | J56: =HYPERLINK("https://youglish.com/pronounce/山/chinese","🔍") | R56: 2026-06-17 | T56: 山 [SƠN] · núi non ↳ Chiết tự: bộ 山 (sơn) — hình ba ngọn núi nhô lên | U56: 🌤️ Thiên nhiên & Thời tiết | V56: 我们明天去爬山。 | W56: Wǒmen míngtiān qù pá shān. Mai chúng tôi đi leo núi.
A57: 350 | B57: HSK1+2 | C57: 天气 | D57: tiānqì | E57: thời tiết | F57: 天气 | G57: 天气 | H57: =IF(TRIM($G57)="","",IF(EXACT(TRIM($G57),TRIM($C57)),"✅ Đúng","❌ Sai")) | I57: =HYPERLINK("https://translate.google.com/translate_tts?ie=UTF-8&tl=zh-CN&client=tw-ob&q=天气","▶") | J57: =HYPERLINK("https://youglish.com/pronounce/天气/chinese","🔍") | R57: 2026-06-17 | T57: 天 [THIÊN] · trời, ngày, thiên nhiên ↳ Chiết tự: bộ 大 (đại – người) + 一 (nhất) trên đầu — khoảng cao nhất trên đầu người 气 [KHÍ] · hơi, không khí; tức giận ↳ Chiết tự: giản thể của 氣: bộ 气 (khí) — hình làn hơi bốc lên | U57: 🌤️ Thiên nhiên & Thời tiết | V57: 今天的天气很冷。 | W57: Jīntiān de tiānqì hěn lěng. Thời tiết hôm nay rất lạnh.
A58: 386 | B58: HSK1+2 | C58: 下雨 | D58: xiàyǔ | E58: đổ mưa | G58: 下雨 | H58: =IF(TRIM($G58)="","",IF(EXACT(TRIM($G58),TRIM($C58)),"✅ Đúng","❌ Sai")) | I58: =HYPERLINK("https://translate.google.com/translate_tts?ie=UTF-8&tl=zh-CN&client=tw-ob&q=下雨","▶") | J58: =HYPERLINK("https://youglish.com/pronounce/下雨/chinese","🔍") | R58: 2026-06-17 | T58: 下 [HẠ] · ở dưới, xuống, kém hơn ↳ Chiết tự: bộ 一 (nhất – mặt đất) + vạch chỉ hướng xuống — chữ chỉ sự 雨 [VŨ] · mưa ↳ Chiết tự: bộ 雨 (vũ) — hình giọt mưa rơi dưới đám mây | U58: 🌤️ Thiên nhiên & Thời tiết | V58: 外边下雨了。 | W58: Wàibian xià yǔ le. Bên ngoài trời mưa rồi.
A59: 439 | B59: HSK1 | C59: 雨 | D59: yǔ | E59: mưa | G59: 雨 | H59: =IF(TRIM($G59)="","",IF(EXACT(TRIM($G59),TRIM($C59)),"✅ Đúng","❌ Sai")) | I59: =HYPERLINK("https://translate.google.com/translate_tts?ie=UTF-8&tl=zh-CN&client=tw-ob&q=雨","▶") | J59: =HYPERLINK("https://youglish.com/pronounce/雨/chinese","🔍") | R59: 2026-06-17 | T59: 雨 [VŨ] · mưa ↳ Chiết tự: bộ 雨 (vũ) — hình giọt mưa rơi dưới đám mây | U59: 🌤️ Thiên nhiên & Thời tiết | V59: 雨越来越大。 | W59: Yǔ yuè lái yuè dà. Mưa càng lúc càng to.
A60: 541 | B60: HSK2 | C60: 晴 | D60: qíng | E60: nắng, quang đãng | G60: 晴 | H60: =IF(TRIM($G60)="","",IF(EXACT(TRIM($G60),TRIM($C60)),"✅ Đúng","❌ Sai")) | I60: ▶ | J60: 🔍 | R60: 46236 | T60: 晴 [TÌNH] · trời quang, nắng ráo ↳ Chiết tự: bộ 日 (nhật – mặt trời) + 青 (thanh – xanh) — mặt trời trên nền trời xanh | U60: 🌤️ Thiên nhiên & Thời tiết | V60: 今天是晴天。 | W60: Jīntiān shì qíngtiān. Hôm nay là ngày nắng.
A61: 558 | B61: HSK2 | C61: 雪 | D61: xuě | E61: tuyết | G61: 雪 | H61: =IF(TRIM($G61)="","",IF(EXACT(TRIM($G61),TRIM($C61)),"✅ Đúng","❌ Sai")) | I61: ▶ | J61: 🔍 | R61: 46236 | T61: 雪 [TUYẾT] · tuyết; rửa sạch (雪耻) ↳ Chiết tự: bộ 雨 (vũ – mưa) + 彐 (kệ – bàn tay) — mưa đông cầm nắm được | U61: 🌤️ Thiên nhiên & Thời tiết | V61: 北京冬天常下雪。 | W61: Běijīng dōngtiān cháng xià xuě. Bắc Kinh mùa đông thường có tuyết.
A62: 566 | B62: HSK2 | C62: 阴 | D62: yīn | E62: âm u, râm mát | H62: =IF(TRIM($G62)="","",IF(EXACT(TRIM($G62),TRIM($C62)),"✅ Đúng","❌ Sai")) | I62: ▶ | J62: 🔍 | R62: 46236 | T62: 阴 [ÂM] · râm mát, u ám; âm (đối với dương) ↳ Chiết tự: giản thể của 陰: bộ 阝 (phụ – gò đất) + 月 (nguyệt – mặt trăng) — sườn núi khuất nắng | U62: 🌤️ Thiên nhiên & Thời tiết | V62: 今天天气有点儿阴。 | W62: Jīntiān tiānqì yǒudiǎnr yīn. Hôm nay trời hơi âm u.
A63: 16 | B63: HSK1 | C63: 包子 | D63: bāozi | E63: bánh bao | G63: 包子 | H63: =IF(TRIM($G63)="","",IF(EXACT(TRIM($G63),TRIM($C63)),"✅ Đúng","❌ Sai")) | I63: =HYPERLINK("https://translate.google.com/translate_tts?ie=UTF-8&tl=zh-CN&client=tw-ob&q=包子","▶") | J63: =HYPERLINK("https://youglish.com/pronounce/包子/chinese","🔍") | R63: 2026-06-17 | T63: 包 [BAO] · bao bọc, gói; cái túi ↳ Chiết tự: bộ 勹 (bao – ôm bọc) + 巳 (tị – thai nhi) — bụng mẹ bọc lấy thai 子 [TỬ] · con cái; hậu tố danh từ; ngài ↳ Chiết tự: bộ 子 (tử) — hình em bé quấn tã, hai tay giơ lên | U63: 🍜 Ăn uống | V63: 我早上吃了两个包子。 | W63: Wǒ zǎoshang chī le liǎng ge bāozi. Sáng nay tôi ăn hai cái bánh bao.
A64: 17 | B64: HSK1 | C64: 杯 | D64: bēi | E64: cốc, ly | F64: 杯 | G64: 杯 | H64: =IF(TRIM($G64)="","",IF(EXACT(TRIM($G64),TRIM($C64)),"✅ Đúng","❌ Sai")) | I64: =HYPERLINK("https://translate.google.com/translate_tts?ie=UTF-8&tl=zh-CN&client=tw-ob&q=杯","▶") | J64: =HYPERLINK("https://youglish.com/pronounce/杯/chinese","🔍") | R64: 2026-06-17 | T64: 杯 [BÔI] · cái chén, cái cốc ↳ Chiết tự: bộ 木 (mộc – gỗ) + 不 (bất – âm đọc) — chén khắc từ gỗ | U64: 🍜 Ăn uống | V64: 请给我一杯水。 | W64: Qǐng gěi wǒ yì bēi shuǐ. Cho tôi một cốc nước.
A65: 18 | B65: HSK1+2 | C65: 杯子 | D65: bēizi | E65: cốc, chén, ly | G65: 杯子 | H65: =IF(TRIM($G65)="","",IF(EXACT(TRIM($G65),TRIM($C65)),"✅ Đúng","❌ Sai")) | I65: =HYPERLINK("https://translate.google.com/translate_tts?ie=UTF-8&tl=zh-CN&client=tw-ob&q=杯子","▶") | J65: =HYPERLINK("https://youglish.com/pronounce/杯子/chinese","🔍") | R65: 2026-06-17 | T65: 杯 [BÔI] · cái chén, cái cốc ↳ Chiết tự: bộ 木 (mộc – gỗ) + 不 (bất – âm đọc) — chén khắc từ gỗ 子 [TỬ] · con cái; hậu tố danh từ; ngài ↳ Chiết tự: bộ 子 (tử) — hình em bé quấn tã, hai tay giơ lên | U65: 🍜 Ăn uống | V65: 这个杯子很漂亮。 | W65: Zhège bēizi hěn piàoliang. Cái cốc này rất đẹp.
A66: 35 | B66: HSK1+2 | C66: 菜 | D66: cài | E66: đồ ăn, món ăn | F66: 菜 | G66: 菜 | H66: =IF(TRIM($G66)="","",IF(EXACT(TRIM($G66),TRIM($C66)),"✅ Đúng","❌ Sai")) | I66: =HYPERLINK("https://translate.google.com/translate_tts?ie=UTF-8&tl=zh-CN&client=tw-ob&q=菜","▶") | J66: =HYPERLINK("https://youglish.com/pronounce/菜/chinese","🔍") | R66: 2026-06-17 | T66: 菜 [THÁI] · rau; món ăn ↳ Chiết tự: bộ 艹 (thảo – cây cỏ) + 采 (thái – hái) — thứ cỏ cây hái về ăn | U66: 🍜 Ăn uống | V66: 这个菜很好吃。 | W66: Zhège cài hěn hǎochī. Món này rất ngon.
A67: 37 | B67: HSK1+2 | C67: 茶 | D67: chá | E67: trà | F67: 茶 | G67: 茶 | H67: =IF(TRIM($G67)="","",IF(EXACT(TRIM($G67),TRIM($C67)),"✅ Đúng","❌ Sai")) | I67: =HYPERLINK("https://translate.google.com/translate_tts?ie=UTF-8&tl=zh-CN&client=tw-ob&q=茶","▶") | J67: =HYPERLINK("https://youglish.com/pronounce/茶/chinese","🔍") | R67: 2026-06-17 | T67: 茶 [TRÀ] · trà, chè ↳ Chiết tự: bộ 艹 (thảo – cây cỏ) + 人 (nhân) + 木 (mộc – cây) — lá cây người hái pha uống | U67: 🍜 Ăn uống | V67: 我喜欢喝中国茶。 | W67: Wǒ xǐhuan hē Zhōngguó chá. Tôi thích uống trà Trung Quốc.
A68: 46 | B68: HSK1+2 | C68: 吃 | D68: chī | E68: ăn | F68: 吃 | G68: 吃 | H68: =IF(TRIM($G68)="","",IF(EXACT(TRIM($G68),TRIM($C68)),"✅ Đúng","❌ Sai")) | I68: =HYPERLINK("https://translate.google.com/translate_tts?ie=UTF-8&tl=zh-CN&client=tw-ob&q=吃","▶") | J68: =HYPERLINK("https://youglish.com/pronounce/吃/chinese","🔍") | R68: 2026-06-17 | T68: 吃 [NGẬT] · ăn, nuốt ↳ Chiết tự: bộ 口 (khẩu – miệng) + 乞 (khất – xin) — đưa thức ăn vào miệng | U68: 🍜 Ăn uống | V68: 你想吃什么？ | W68: Nǐ xiǎng chī shénme? Bạn muốn ăn gì?
A69: 47 | B69: HSK1 | C69: 吃饭 | D69: chīfàn | E69: ăn cơm | F69: 吃饭 | G69: 吃饭 | H69: =IF(TRIM($G69)="","",IF(EXACT(TRIM($G69),TRIM($C69)),"✅ Đúng","❌ Sai")) | I69: =HYPERLINK("https://translate.google.com/translate_tts?ie=UTF-8&tl=zh-CN&client=tw-ob&q=吃饭","▶") | J69: =HYPERLINK("https://youglish.com/pronounce/吃饭/chinese","🔍") | R69: 2026-06-17 | T69: 吃 [NGẬT] · ăn, nuốt ↳ Chiết tự: bộ 口 (khẩu – miệng) + 乞 (khất – xin) — đưa thức ăn vào miệng 饭 [PHẠN] · cơm, bữa ăn ↳ Chiết tự: giản thể của 飯: bộ 饣 (thực – ăn) + 反 (phản – âm đọc) — bữa cơm | U69: 🍜 Ăn uống | V69: 我们一起吃饭吧。 | W69: Wǒmen yìqǐ chīfàn ba. Chúng ta cùng ăn cơm nhé.
A70: 96 | B70: HSK1+3 | C70: 饿 | D70: è | E70: đói | G70: 饿 | H70: =IF(TRIM($G70)="","",IF(EXACT(TRIM($G70),TRIM($C70)),"✅ Đúng","❌ Sai")) | I70: =HYPERLINK("https://translate.google.com/translate_tts?ie=UTF-8&tl=zh-CN&client=tw-ob&q=饿","▶") | J70: =HYPERLINK("https://youglish.com/pronounce/饿/chinese","🔍") | R70: 2026-06-17 | T70: 饿 [NGẠ] · đói ↳ Chiết tự: giản thể của 餓: bộ 饣 (thực – ăn) + 我 (ngã – tôi) — bản thân cần ăn | U70: 🍜 Ăn uống | V70: 我有点儿饿了。 | W70: Wǒ yǒudiǎnr è le. Tôi hơi đói rồi.
A71: 99 | B71: HSK1 | C71: 饭 | D71: fàn | E71: cơm | F71: 饭 | G71: 饭 | H71: =IF(TRIM($G71)="","",IF(EXACT(TRIM($G71),TRIM($C71)),"✅ Đúng","❌ Sai")) | I71: =HYPERLINK("https://translate.google.com/translate_tts?ie=UTF-8&tl=zh-CN&client=tw-ob&q=饭","▶") | J71: =HYPERLINK("https://youglish.com/pronounce/饭/chinese","🔍") | R71: 2026-06-17 | T71: 饭 [PHẠN] · cơm, bữa ăn ↳ Chiết tự: giản thể của 飯: bộ 饣 (thực – ăn) + 反 (phản – âm đọc) — bữa cơm | U71: 🍜 Ăn uống | V71: 饭已经做好了。 | W71: Fàn yǐjīng zuò hǎo le. Cơm đã nấu xong rồi.
A72: 100 | B72: HSK1+2 | C72: 饭店 | D72: fàndiàn | E72: quán ăn / nhà hàng | F72: 饭店 | G72: 饭店 | H72: =IF(TRIM($G72)="","",IF(EXACT(TRIM($G72),TRIM($C72)),"✅ Đúng","❌ Sai")) | I72: =HYPERLINK("https://translate.google.com/translate_tts?ie=UTF-8&tl=zh-CN&client=tw-ob&q=饭店","▶") | J72: =HYPERLINK("https://youglish.com/pronounce/饭店/chinese","🔍") | R72: 2026-06-17 | T72: 饭 [PHẠN] · cơm, bữa ăn ↳ Chiết tự: giản thể của 飯: bộ 饣 (thực – ăn) + 反 (phản – âm đọc) — bữa cơm 店 [ĐIẾM] · cửa hàng, quán ↳ Chiết tự: bộ 广 (nghiễm – mái nhà) + 占 (chiếm – âm đọc) — mái nhà chiếm chỗ bày bán | U72: 🍜 Ăn uống | V72: 这家饭店的菜很好。 | W72: Zhè jiā fàndiàn de cài hěn hǎo. Món ăn của nhà hàng này rất ngon.
A73: 139 | B73: HSK1+2 | C73: 好吃 | D73: hǎochī | E73: ngon | F73: 好吃 | G73: 好吃 | H73: =IF(TRIM($G73)="","",IF(EXACT(TRIM($G73),TRIM($C73)),"✅ Đúng","❌ Sai")) | I73: =HYPERLINK("https://translate.google.com/translate_tts?ie=UTF-8&tl=zh-CN&client=tw-ob&q=好吃","▶") | J73: =HYPERLINK("https://youglish.com/pronounce/好吃/chinese","🔍") | R73: 2026-06-17 | T73: 好 [HẢO / HIẾU] · tốt đẹp; thích, yêu ↳ Chiết tự: bộ 女 (nữ – mẹ) + 子 (tử – con) — mẹ bồng con là cảnh tốt đẹp nhất 吃 [NGẬT] · ăn, nuốt ↳ Chiết tự: bộ 口 (khẩu – miệng) + 乞 (khất – xin) — đưa thức ăn vào miệng | U73: 🍜 Ăn uống | V73: 妈妈做的菜真好吃。 | W73: Māma zuò de cài zhēn hǎochī. Món mẹ nấu thật ngon.
A74: 144 | B74: HSK1+2 | C74: 喝 | D74: hē | E74: uống | F74: 喝 | G74: 喝 | H74: =IF(TRIM($G74)="","",IF(EXACT(TRIM($G74),TRIM($C74)),"✅ Đúng","❌ Sai")) | I74: =HYPERLINK("https://translate.google.com/translate_tts?ie=UTF-8&tl=zh-CN&client=tw-ob&q=喝","▶") | J74: =HYPERLINK("https://youglish.com/pronounce/喝/chinese","🔍") | R74: 2026-06-17 | T74: 喝 [HÁT] · uống ↳ Chiết tự: bộ 口 (khẩu – miệng) + 曷 (hạt – âm đọc) — đưa nước qua miệng | U74: 🍜 Ăn uống | V74: 你要喝什么？ | W74: Nǐ yào hē shénme? Bạn muốn uống gì?
A75: 164 | B75: HSK1+2 | C75: 鸡蛋 | D75: jīdàn | E75: trứng gà | H75: =IF(TRIM($G75)="","",IF(EXACT(TRIM($G75),TRIM($C75)),"✅ Đúng","❌ Sai")) | I75: =HYPERLINK("https://translate.google.com/translate_tts?ie=UTF-8&tl=zh-CN&client=tw-ob&q=鸡蛋","▶") | J75: =HYPERLINK("https://youglish.com/pronounce/鸡蛋/chinese","🔍") | R75: 2026-06-17 | T75: 鸡 [KÊ] · con gà ↳ Chiết tự: giản thể của 雞: bộ 又 (hựu) + 鸟 (điểu – con chim) — loài chim nuôi trong nhà 蛋 [ĐẢN] · quả trứng ↳ Chiết tự: bộ 疋 (sơ) + 虫 (trùng – sâu bọ/loài vật) — vật do loài vật đẻ ra | U75: 🍜 Ăn uống | V75: 我每天吃一个鸡蛋。 | W75: Wǒ měitiān chī yí ge jīdàn. Mỗi ngày tôi ăn một quả trứng.
A76: 198 | B76: HSK1+3 | C76: 渴 | D76: kě | E76: khát | F76: 渴 | G76: 渴 | H76: =IF(TRIM($G76)="","",IF(EXACT(TRIM($G76),TRIM($C76)),"✅ Đúng","❌ Sai")) | I76: =HYPERLINK("https://translate.google.com/translate_tts?ie=UTF-8&tl=zh-CN&client=tw-ob&q=渴","▶") | J76: =HYPERLINK("https://youglish.com/pronounce/渴/chinese","🔍") | R76: 2026-06-17 | T76: 渴 [KHÁT] · khát nước, khao khát ↳ Chiết tự: bộ 氵 (thủy – nước) + 曷 (hạt – âm đọc) — thèm nước | U76: 🍜 Ăn uống | V76: 我很渴，想喝水。 | W76: Wǒ hěn kě, xiǎng hē shuǐ. Tôi rất khát, muốn uống nước.
A77: 239 | B77: HSK1+2+3 | C77: 米饭 | D77: mǐfàn | E77: cơm | F77: 米饭 | G77: 米饭 | H77: =IF(TRIM($G77)="","",IF(EXACT(TRIM($G77),TRIM($C77)),"✅ Đúng","❌ Sai")) | I77: =HYPERLINK("https://translate.google.com/translate_tts?ie=UTF-8&tl=zh-CN&client=tw-ob&q=米饭","▶") | J77: =HYPERLINK("https://youglish.com/pronounce/米饭/chinese","🔍") | R77: 2026-06-17 | T77: 米 [MỄ] · gạo; mét ↳ Chiết tự: bộ 米 (mễ) — hình các hạt gạo rơi quanh 饭 [PHẠN] · cơm, bữa ăn ↳ Chiết tự: giản thể của 飯: bộ 饣 (thực – ăn) + 反 (phản – âm đọc) — bữa cơm | U77: 🍜 Ăn uống | V77: 请给我一碗米饭。 | W77: Qǐng gěi wǒ yì wǎn mǐfàn. Cho tôi một bát cơm.
A78: 240 | B78: HSK1 | C78: 面 | D78: miàn | E78: mặt; mì | F78: 面 | G78: 面 | H78: =IF(TRIM($G78)="","",IF(EXACT(TRIM($G78),TRIM($C78)),"✅ Đúng","❌ Sai")) | I78: =HYPERLINK("https://translate.google.com/translate_tts?ie=UTF-8&tl=zh-CN&client=tw-ob&q=面","▶") | J78: =HYPERLINK("https://youglish.com/pronounce/面/chinese","🔍") | R78: 2026-06-17 | T78: 面 [DIỆN] · mặt, bề mặt, phía; sợi mì ↳ Chiết tự: bộ 面 (diện) — hình khuôn mặt có con mắt; giản thể gộp cả 麵 (mì) | U78: 🍜 Ăn uống | V78: 我不太喜欢吃面。 | W78: Wǒ bú tài xǐhuan chī miàn. Tôi không thích ăn mì lắm.
A79: 241 | B79: HSK1+3 | C79: 面包 | D79: miànbāo | E79: bánh mì | F79: 面包 | G79: 面包 | H79: =IF(TRIM($G79)="","",IF(EXACT(TRIM($G79),TRIM($C79)),"✅ Đúng","❌ Sai")) | I79: =HYPERLINK("https://translate.google.com/translate_tts?ie=UTF-8&tl=zh-CN&client=tw-ob&q=面包","▶") | J79: =HYPERLINK("https://youglish.com/pronounce/面包/chinese","🔍") | R79: 2026-06-17 | T79: 面 [DIỆN] · mặt, bề mặt, phía; sợi mì ↳ Chiết tự: bộ 面 (diện) — hình khuôn mặt có con mắt; giản thể gộp cả 麵 (mì) 包 [BAO] · bao bọc, gói; cái túi ↳ Chiết tự: bộ 勹 (bao – ôm bọc) + 巳 (tị – thai nhi) — bụng mẹ bọc lấy thai | U79: 🍜 Ăn uống | V79: 早上我吃面包。 | W79: Zǎoshang wǒ chī miànbāo. Buổi sáng tôi ăn bánh mì.
A80: 242 | B80: HSK1 | C80: 面条 | D80: miàntiáo | E80: mì sợi | F80: 面条 | G80: 面条 | H80: =IF(TRIM($G80)="","",IF(EXACT(TRIM($G80),TRIM($C80)),"✅ Đúng","❌ Sai")) | I80: =HYPERLINK("https://translate.google.com/translate_tts?ie=UTF-8&tl=zh-CN&client=tw-ob&q=面条","▶") | J80: =HYPERLINK("https://youglish.com/pronounce/面条/chinese","🔍") | R80: 2026-06-17 | T80: 面 [DIỆN] · mặt, bề mặt, phía; sợi mì ↳ Chiết tự: bộ 面 (diện) — hình khuôn mặt có con mắt; giản thể gộp cả 麵 (mì) 条 [ĐIỀU] · điều khoản; sợi, dải (lượng từ) ↳ Chiết tự: giản thể của 條: bộ 攸 (du) + 木 (mộc – cây) — nhánh cây nhỏ và dài | U80: 🍜 Ăn uống | V80: 这里的面条很好吃。 | W80: Zhèli de miàntiáo hěn hǎochī. Mì ở đây rất ngon.
A81: 265 | B81: HSK1+2 | C81: 牛奶 | D81: niúnǎi | E81: sữa bò | F81: 牛奶 | G81: 牛奶 | H81: =IF(TRIM($G81)="","",IF(EXACT(TRIM($G81),TRIM($C81)),"✅ Đúng","❌ Sai")) | I81: =HYPERLINK("https://translate.google.com/translate_tts?ie=UTF-8&tl=zh-CN&client=tw-ob&q=牛奶","▶") | J81: =HYPERLINK("https://youglish.com/pronounce/牛奶/chinese","🔍") | R81: 2026-06-17 | T81: 牛 [NGƯU] · con bò, con trâu ↳ Chiết tự: bộ 牛 (ngưu) — hình đầu trâu có hai sừng 奶 [NÃI] · sữa; bà nội ↳ Chiết tự: bộ 女 (nữ – phụ nữ) + 乃 (nãi – âm đọc) — người mẹ cho bú | U81: 🍜 Ăn uống | V81: 孩子每天喝牛奶。 | W81: Háizi měitiān hē niúnǎi. Đứa trẻ uống sữa mỗi ngày.
A82: 300 | B82: HSK1 | C82: 肉 | D82: ròu | E82: thịt | G82: 肉 | H82: =IF(TRIM($G82)="","",IF(EXACT(TRIM($G82),TRIM($C82)),"✅ Đúng","❌ Sai")) | I82: =HYPERLINK("https://translate.google.com/translate_tts?ie=UTF-8&tl=zh-CN&client=tw-ob&q=肉","▶") | J82: =HYPERLINK("https://youglish.com/pronounce/肉/chinese","🔍") | R82: 2026-06-17 | T82: 肉 [NHỤC] · thịt ↳ Chiết tự: bộ 肉 (nhục) — hình miếng thịt có thớ | U82: 🍜 Ăn uống | V82: 我不吃肉。 | W82: Wǒ bù chī ròu. Tôi không ăn thịt.
A83: 335 | B83: HSK1+2 | C83: 水 | D83: shuǐ | E83: nước | F83: 水 | G83: 水 | H83: =IF(TRIM($G83)="","",IF(EXACT(TRIM($G83),TRIM($C83)),"✅ Đúng","❌ Sai")) | I83: =HYPERLINK("https://translate.google.com/translate_tts?ie=UTF-8&tl=zh-CN&client=tw-ob&q=水","▶") | J83: =HYPERLINK("https://youglish.com/pronounce/水/chinese","🔍") | R83: 2026-06-17 | T83: 水 [THỦY] · nước ↳ Chiết tự: bộ 水 (thủy) — hình dòng nước chảy có nhánh | U83: 🍜 Ăn uống | V83: 请喝点儿水。 | W83: Qǐng hē diǎnr shuǐ. Uống chút nước đi.
A84: 336 | B84: HSK1+2 | C84: 水果 | D84: shuǐguǒ | E84: hoa quả, trái cây | G84: 水果 | H84: =IF(TRIM($G84)="","",IF(EXACT(TRIM($G84),TRIM($C84)),"✅ Đúng","❌ Sai")) | I84: =HYPERLINK("https://translate.google.com/translate_tts?ie=UTF-8&tl=zh-CN&client=tw-ob&q=水果","▶") | J84: =HYPERLINK("https://youglish.com/pronounce/水果/chinese","🔍") | R84: 2026-06-17 | T84: 水 [THỦY] · nước ↳ Chiết tự: bộ 水 (thủy) — hình dòng nước chảy có nhánh 果 [QUẢ] · quả, kết quả, quả nhiên ↳ Chiết tự: bộ 木 (mộc – cây) + 田 (điền – hình quả tròn) — cây kết trái trên ngọn | U84: 🍜 Ăn uống | V84: 我喜欢吃水果。 | W84: Wǒ xǐhuan chī shuǐguǒ. Tôi thích ăn trái cây.
A85: 363 | B85: HSK1 | C85: 晚饭 | D85: wǎnfàn | E85: bữa tối | F85: 晚饭 | G85: 晚饭 | H85: =IF(TRIM($G85)="","",IF(EXACT(TRIM($G85),TRIM($C85)),"✅ Đúng","❌ Sai")) | I85: =HYPERLINK("https://translate.google.com/translate_tts?ie=UTF-8&tl=zh-CN&client=tw-ob&q=晚饭","▶") | J85: =HYPERLINK("https://youglish.com/pronounce/晚饭/chinese","🔍") | R85: 2026-06-17 | T85: 晚 [VÃN] · muộn, tối, buổi tối ↳ Chiết tự: bộ 日 (nhật – mặt trời) + 免 (miễn – âm đọc) — mặt trời đã khuất 饭 [PHẠN] · cơm, bữa ăn ↳ Chiết tự: giản thể của 飯: bộ 饣 (thực – ăn) + 反 (phản – âm đọc) — bữa cơm | U85: 🍜 Ăn uống | V85: 晚饭你想吃什么？ | W85: Wǎnfàn nǐ xiǎng chī shénme? Cơm tối bạn muốn ăn gì?
A86: 373 | B86: HSK1 | C86: 午饭 | D86: wǔfàn | E86: bữa trưa | F86: 午饭 | G86: 午饭 | H86: =IF(TRIM($G86)="","",IF(EXACT(TRIM($G86),TRIM($C86)),"✅ Đúng","❌ Sai")) | I86: =HYPERLINK("https://translate.google.com/translate_tts?ie=UTF-8&tl=zh-CN&client=tw-ob&q=午饭","▶") | J86: =HYPERLINK("https://youglish.com/pronounce/午饭/chinese","🔍") | R86: 2026-06-17 | T86: 午 [NGỌ] · giờ Ngọ, buổi trưa ↳ Chiết tự: bộ 十 (thập) + 丿 (phiệt) — hình cái chày, mượn chỉ giữa trưa 饭 [PHẠN] · cơm, bữa ăn ↳ Chiết tự: giản thể của 飯: bộ 饣 (thực – ăn) + 反 (phản – âm đọc) — bữa cơm | U86: 🍜 Ăn uống | V86: 午饭我在公司吃。 | W86: Wǔfàn wǒ zài gōngsī chī. Cơm trưa tôi ăn ở công ty.
A87: 448 | B87: HSK1 | C87: 早饭 | D87: zǎofàn | E87: bữa sáng | F87: 早饭 | G87: 早饭 | H87: =IF(TRIM($G87)="","",IF(EXACT(TRIM($G87),TRIM($C87)),"✅ Đúng","❌ Sai")) | I87: =HYPERLINK("https://translate.google.com/translate_tts?ie=UTF-8&tl=zh-CN&client=tw-ob&q=早饭","▶") | J87: =HYPERLINK("https://youglish.com/pronounce/早饭/chinese","🔍") | R87: 2026-06-17 | T87: 早 [TẢO] · sớm, buổi sáng ↳ Chiết tự: bộ 日 (nhật – mặt trời) + 十 (thập) — mặt trời vừa nhô lên ngọn cỏ 饭 [PHẠN] · cơm, bữa ăn ↳ Chiết tự: giản thể của 飯: bộ 饣 (thực – ăn) + 反 (phản – âm đọc) — bữa cơm | U87: 🍜 Ăn uống | V87: 我没吃早饭。 | W87: Wǒ méi chī zǎofàn. Tôi chưa ăn sáng.
A88: 506 | B88: HSK2 | C88: 苹果 | D88: píngguǒ | E88: quả táo | G88: 苹果 | H88: =IF(TRIM($G88)="","",IF(EXACT(TRIM($G88),TRIM($C88)),"✅ Đúng","❌ Sai")) | I88: ▶ | J88: 🔍 | R88: 46236 | T88: 苹 [BÌNH] · quả táo (苹果) ↳ Chiết tự: giản thể của 蘋: bộ 艹 (thảo – cây cỏ) + 平 (bình – âm đọc) — hình thanh 果 [QUẢ] · quả, kết quả, quả nhiên ↳ Chiết tự: bộ 木 (mộc – cây) + 田 (điền – hình quả tròn) — cây kết trái trên ngọn | U88: 🍜 Ăn uống | V88: 这个苹果很甜。 | W88: Zhège píngguǒ hěn tián. Quả táo này rất ngọt.
A89: 530 | B89: HSK2 | C89: 咖啡 | D89: kāfēi | E89: cà phê | G89: 咖啡 | H89: =IF(TRIM($G89)="","",IF(EXACT(TRIM($G89),TRIM($C89)),"✅ Đúng","❌ Sai")) | I89: ▶ | J89: 🔍 | R89: 46236 | T89: 咖 [CA] · cà (咖啡 = cà phê) ↳ Chiết tự: bộ 口 (khẩu – miệng) + 加 (gia – âm đọc) — chữ phiên âm 啡 [PHÊ] · phê (咖啡 = cà phê) ↳ Chiết tự: bộ 口 (khẩu – miệng) + 非 (phi – âm đọc) — chữ phiên âm | U89: 🍜 Ăn uống | V89: 我想喝一杯咖啡。 | W89: Wǒ xiǎng hē yì bēi kāfēi. Tôi muốn uống một tách cà phê.
A90: 555 | B90: HSK2 | C90: 西瓜 | D90: xīguā | E90: dưa hấu | G90: 西瓜 | H90: =IF(TRIM($G90)="","",IF(EXACT(TRIM($G90),TRIM($C90)),"✅ Đúng","❌ Sai")) | I90: ▶ | J90: 🔍 | R90: 46236 | T90: 西 [TÂY] · hướng tây; phương Tây ↳ Chiết tự: bộ 覀/西 (tây) — hình tổ chim, chim về tổ khi mặt trời lặn ở phía tây 瓜 [QUA] · quả dưa, quả bầu bí ↳ Chiết tự: bộ 瓜 (qua) — hình dây leo có quả treo | U90: 🍜 Ăn uống | V90: 夏天我爱吃西瓜。 | W90: Xiàtiān wǒ ài chī xīguā. Mùa hè tôi thích ăn dưa hấu.
A91: 561 | B91: HSK2 | C91: 羊肉 | D91: yángròu | E91: thịt cừu, thịt dê | H91: =IF(TRIM($G91)="","",IF(EXACT(TRIM($G91),TRIM($C91)),"✅ Đúng","❌ Sai")) | I91: ▶ | J91: 🔍 | R91: 46236 | T91: 羊 [DƯƠNG] · con dê, con cừu ↳ Chiết tự: bộ 羊 (dương) — hình đầu dê có hai sừng cong 肉 [NHỤC] · thịt ↳ Chiết tự: bộ 肉 (nhục) — hình miếng thịt có thớ | U91: 🍜 Ăn uống | V91: 他不吃羊肉。 | W91: Tā bù chī yángròu. Anh ấy không ăn thịt cừu.
A92: 570 | B92: HSK2 | C92: 鱼 | D92: yú | E92: con cá | G92: 鱼 | H92: =IF(TRIM($G92)="","",IF(EXACT(TRIM($G92),TRIM($C92)),"✅ Đúng","❌ Sai")) | I92: ▶ | J92: 🔍 | R92: 46236 | T92: 鱼 [NGƯ] · con cá ↳ Chiết tự: giản thể của 魚: bộ 鱼 (ngư) — hình con cá có đầu, vảy và đuôi | U92: 🍜 Ăn uống | V92: 这条鱼很新鲜。 | W92: Zhè tiáo yú hěn xīnxiān. Con cá này rất tươi.
A93: 6 | B93: HSK1+2 | C93: 白 | D93: bái | E93: trắng | G93: 白 | H93: =IF(TRIM($G93)="","",IF(EXACT(TRIM($G93),TRIM($C93)),"✅ Đúng","❌ Sai")) | I93: =HYPERLINK("https://translate.google.com/translate_tts?ie=UTF-8&tl=zh-CN&client=tw-ob&q=白","▶") | J93: =HYPERLINK("https://youglish.com/pronounce/白/chinese","🔍") | R93: 2026-06-17 | T93: 白 [BẠCH] · trắng; rõ ràng; uổng công ↳ Chiết tự: bộ 白 (bạch) — hình tia nắng đầu tiên ló rạng | U93: 🎨 Tính từ & Trạng thái | V93: 她穿着白衣服。 | W93: Tā chuān zhe bái yīfu. Cô ấy mặc áo trắng.
A94: 24 | B94: HSK1+2 | C94: 比 | D94: bǐ | E94: so, so với | G94: 比 | H94: =IF(TRIM($G94)="","",IF(EXACT(TRIM($G94),TRIM($C94)),"✅ Đúng","❌ Sai")) | I94: =HYPERLINK("https://translate.google.com/translate_tts?ie=UTF-8&tl=zh-CN&client=tw-ob&q=比","▶") | J94: =HYPERLINK("https://youglish.com/pronounce/比/chinese","🔍") | R94: 2026-06-17 | T94: 比 [TỶ] · so sánh, tỉ lệ ↳ Chiết tự: bộ 比 (tỷ) — hai người đứng sát nhau để so | U94: 🎨 Tính từ & Trạng thái | V94: 今天比昨天冷。 | W94: Jīntiān bǐ zuótiān lěng. Hôm nay lạnh hơn hôm qua.
A95: 25 | B95: HSK1+2 | C95: 别 | D95: bié | E95: đừng, không được | G95: 别 | H95: =IF(TRIM($G95)="","",IF(EXACT(TRIM($G95),TRIM($C95)),"✅ Đúng","❌ Sai")) | I95: =HYPERLINK("https://translate.google.com/translate_tts?ie=UTF-8&tl=zh-CN&client=tw-ob&q=别","▶") | J95: =HYPERLINK("https://youglish.com/pronounce/别/chinese","🔍") | R95: 2026-06-17 | T95: 别 [BIỆT] · chia lìa, khác biệt; đừng ↳ Chiết tự: bộ 另 (lánh – khác) + 刂 (đao đứng – dao) — dùng dao tách xương ra riêng | U95: 🎨 Tính từ & Trạng thái | V95: 别忘了带钱包。 | W95: Bié wàng le dài qiánbāo. Đừng quên mang ví.
A96: 26 | B96: HSK1 | C96: 别的 | D96: biéde | E96: cái khác | G96: 别的 | H96: =IF(TRIM($G96)="","",IF(EXACT(TRIM($G96),TRIM($C96)),"✅ Đúng","❌ Sai")) | I96: =HYPERLINK("https://translate.google.com/translate_tts?ie=UTF-8&tl=zh-CN&client=tw-ob&q=别的","▶") | J96: =HYPERLINK("https://youglish.com/pronounce/别的/chinese","🔍") | R96: 2026-06-17 | T96: 别 [BIỆT] · chia lìa, khác biệt; đừng ↳ Chiết tự: bộ 另 (lánh – khác) + 刂 (đao đứng – dao) — dùng dao tách xương ra riêng 的 [ĐÍCH] · của, thuộc về (trợ từ); đích xác ↳ Chiết tự: bộ 白 (bạch – trắng) + 勺 (chước – cái muôi) — vốn nghĩa "cái đích trắng", mượn làm trợ từ | U96: 🎨 Tính từ & Trạng thái | V96: 你还有别的问题吗？ | W96: Nǐ hái yǒu biéde wèntí ma? Bạn còn câu hỏi nào khác không?
A97: 30 | B97: HSK1 | C97: 不大 | D97: búdà | E97: nhỏ, không lớn | F97: 不大 | G97: 不大 | H97: =IF(TRIM($G97)="","",IF(EXACT(TRIM($G97),TRIM($C97)),"✅ Đúng","❌ Sai")) | I97: =HYPERLINK("https://translate.google.com/translate_tts?ie=UTF-8&tl=zh-CN&client=tw-ob&q=不大","▶") | J97: =HYPERLINK("https://youglish.com/pronounce/不大/chinese","🔍") | R97: 2026-06-17 | T97: 不 [BẤT] · không, chẳng (phủ định) ↳ Chiết tự: bộ 一 (nhất – vòm trời) + 丿 (phiệt) — chim bay lên đụng trời, không qua được 大 [ĐẠI] · to lớn, vĩ đại ↳ Chiết tự: bộ 大 (đại) — hình người dang rộng hai tay hai chân | U97: 🎨 Tính từ & Trạng thái | V97: 这个房间不大。 | W97: Zhège fángjiān bú dà. Căn phòng này không to.
A98: 31 | B98: HSK1 | C98: 不对 | D98: búduì | E98: không đúng | F98: 不对 | G98: 不对 | H98: =IF(TRIM($G98)="","",IF(EXACT(TRIM($G98),TRIM($C98)),"✅ Đúng","❌ Sai")) | I98: =HYPERLINK("https://translate.google.com/translate_tts?ie=UTF-8&tl=zh-CN&client=tw-ob&q=不对","▶") | J98: =HYPERLINK("https://youglish.com/pronounce/不对/chinese","🔍") | R98: 2026-06-17 | T98: 不 [BẤT] · không, chẳng (phủ định) ↳ Chiết tự: bộ 一 (nhất – vòm trời) + 丿 (phiệt) — chim bay lên đụng trời, không qua được 对 [ĐỐI] · đúng, đối diện, đối với ↳ Chiết tự: giản thể của 對: bộ 又 (hựu – bàn tay) + 寸 (thốn – tấc tay) — hai bên đối chiếu cho khớp | U98: 🎨 Tính từ & Trạng thái | V98: 你说的不对。 | W98: Nǐ shuō de bú duì. Bạn nói không đúng.
A99: 36 | B99: HSK1+3 | C99: 差 | D99: chà | E99: thiếu, kém | G99: 差 | H99: =IF(TRIM($G99)="","",IF(EXACT(TRIM($G99),TRIM($C99)),"✅ Đúng","❌ Sai")) | I99: =HYPERLINK("https://translate.google.com/translate_tts?ie=UTF-8&tl=zh-CN&client=tw-ob&q=差","▶") | J99: =HYPERLINK("https://youglish.com/pronounce/差/chinese","🔍") | R99: 2026-06-17 | T99: 差 [SAI / SÁI] · kém, chênh lệch, sai biệt ↳ Chiết tự: bộ 羊 (dương – con dê) + 工 (công) — làm không đều thì sinh sai lệch | U99: 🎨 Tính từ & Trạng thái | V99: 我的汉语还差得远。 | W99: Wǒ de Hànyǔ hái chà de yuǎn. Tiếng Trung của tôi còn kém xa.
A100: 38 | B100: HSK1 | C100: 常 | D100: cháng | E100: thường | F100: 常 | G100: 常 | H100: =IF(TRIM($G100)="","",IF(EXACT(TRIM($G100),TRIM($C100)),"✅ Đúng","❌ Sai")) | I100: =HYPERLINK("https://translate.google.com/translate_tts?ie=UTF-8&tl=zh-CN&client=tw-ob&q=常","▶") | J100: =HYPERLINK("https://youglish.com/pronounce/常/chinese","🔍") | R100: 2026-06-17 | T100: 常 [THƯỜNG] · thường xuyên; bình thường ↳ Chiết tự: bộ 尚 (thượng – âm đọc) + 巾 (cân – vải) — tấm vải dùng hằng ngày | U100: 🎨 Tính từ & Trạng thái | V100: 他常来我家。 | W100: Tā cháng lái wǒ jiā. Anh ấy thường đến nhà tôi.
...

Sheet Câu từ nguồn (NLM)
A1: Nguồn | B1: STT | C1: 🀄 Hán tự | D1: 🔤 Pinyin & Nghĩa | E1: 📄 Câu gốc (nguyên văn) | F1: 🌐 YOUGLISH
A2: 626 ĐPTM.pdf | B2: 1 | C2: 这个价格合理吗？ | D2: Giá cả này hợp lý không? Zhège jiàgé hélǐ ma? | E2: 1 这个价格合理 吗？ Giá cả này hợp lý không? Zhège jiàgé hélǐ ma? | F2: =HYPERLINK("https://youglish.com/pronounce/这个价格合理吗/chinese","🔍")
A3: 626 ĐPTM.pdf | B3: 2 | C3: 我们是否可以协商一些具体的交货日期？ | D3: Chúng ta có thể đàm phán về một số ngày giao hàng cụ thể được không? Wǒmen shìfǒu kěyǐ xiéshāng yīxiē jùtǐ de jiāo huò rìqí? | E3: 2 我们是否可以 协商一些具体 的交货日期？ Chúng ta có thể đàm phán về một số ngày giao hàng cụ thể được không? Wǒmen shìfǒu kěyǐ xiéshāng yīxiē jùtǐ de jiāo huò rìqí? | F3: =HYPERLINK("https://youglish.com/pronounce/我们是否可以协商一些具体的交货日期/chinese","🔍")
A4: 626 ĐPTM.pdf | B4: 3 | C4: 我们需要探讨一下付款方式。 | D4: Chúng ta cần thảo luận về phương thức thanh toán. Wǒmen xūyào tàntǎo yīxià fùkuǎn fāngshì. | E4: 3 我们需要探讨 一下付款方式。 Chúng ta cần thảo luận về phương thức thanh toán. Wǒmen xūyào tàntǎo yīxià fùkuǎn fāngshì. | F4: =HYPERLINK("https://youglish.com/pronounce/我们需要探讨一下付款方式/chinese","🔍")
A5: 626 ĐPTM.pdf | B5: 4 | C5: 我们能否协商一下保险问题？ | D5: Chúng ta có thể đàm phán về vấn đề bảo hiểm không? Wǒmen néng fǒu xiéshāng yīxià bǎoxiǎn wèntí? | E5: 4 我们能否协商 一下保险问 题？ Chúng ta có thể đàm phán về vấn đề bảo hiểm không? Wǒmen néng fǒu xiéshāng yīxià bǎoxiǎn wèntí? | F5: =HYPERLINK("https://youglish.com/pronounce/我们能否协商一下保险问题/chinese","🔍")
A6: 626 ĐPTM.pdf | B6: 5 | C6: 我们需要协商一下产品的质量标准。 | D6: Chúng ta cần đàm phán về tiêu chuẩn chất lượng sản phẩm. Wǒmen xūyào xiéshāng yīxià chǎnpǐn de zhìliàng biāozhǔn. | E6: 5 我们需要协商 一下产品的质 量标准。 Chúng ta cần đàm phán về tiêu chuẩn chất lượng sản phẩm. Wǒmen xūyào xiéshāng yīxià chǎnpǐn de zhìliàng biāozhǔn. | F6: =HYPERLINK("https://youglish.com/pronounce/我们需要协商一下产品的质量标准/chinese","🔍")
A7: 626 ĐPTM.pdf | B7: 6 | C7: 我们是否可以讨论一下价格问题？ | D7: Chúng ta có thể thảo luận về vấn đề giá cả được không? Wǒmen shìfǒu kěyǐ tǎolùn yīxià jiàgé wèntí? | E7: 6 我们是否可以 讨论一下价格 问题？ Chúng ta có thể thảo luận về vấn đề giá cả được không? Wǒmen shìfǒu kěyǐ tǎolùn yīxià jiàgé wèntí? | F7: =HYPERLINK("https://youglish.com/pronounce/我们是否可以讨论一下价格问题/chinese","🔍")
A8: 626 ĐPTM.pdf | B8: 7 | C8: 我们需要进一步确认交货地点。 | D8: Chúng ta cần xác nhận thêm địa điểm giao hàng. Wǒmen xūyào jìnyībù quèrèn jiāo huò dìdiǎn. | E8: 7 我们需要进一 步确认交货地 点。 Chúng ta cần xác nhận thêm địa điểm giao hàng. Wǒmen xūyào jìnyībù quèrèn jiāo huò dìdiǎn. | F8: =HYPERLINK("https://youglish.com/pronounce/我们需要进一步确认交货地点/chinese","🔍")
A9: 626 ĐPTM.pdf | B9: 8 | C9: 我们需要协商一下质量检验的具体细节。 | D9: Chúng ta cần đàm phán về chi tiết kiểm tra chất lượng. Wǒmen xūyào xiéshāng yīxià zhìliàng jiǎnyàn de jùtǐ xìjié. | E9: 8 我们需要协商 一下质量检验 的具体细节。 Chúng ta cần đàm phán về chi tiết kiểm tra chất lượng. Wǒmen xūyào xiéshāng yīxià zhìliàng jiǎnyàn de jùtǐ xìjié. | F9: =HYPERLINK("https://youglish.com/pronounce/我们需要协商一下质量检验的具体细节/chinese","🔍")
A10: 626 ĐPTM.pdf | B10: 9 | C10: 我们是否可以讨论一下运输方式？ | D10: Chúng ta có thể thảo luận về phương thức vận chuyển được không? Wǒmen shìfǒu kěyǐ tǎolùn yīxià yùnshū fāngshì? | E10: 9 我们是否可以 讨论一下运输 方式？ Chúng ta có thể thảo luận về phương thức vận chuyển được không? Wǒmen shìfǒu kěyǐ tǎolùn yīxià yùnshū fāngshì? | F10: =HYPERLINK("https://youglish.com/pronounce/我们是否可以讨论一下运输方式/chinese","🔍")
A11: 626 ĐPTM.pdf | B11: 10 | C11: 我们需要探讨一下退换货政策。 | D11: Chúng ta cần thảo luận về chính sách đổi trả hàng. Wǒmen xūyào tàntǎo yīxià tuìhuàn huò zhèngcè. | E11: 10 我们需要探讨 一下退换货政 策。 Chúng ta cần thảo luận về chính sách đổi trả hàng. Wǒmen xūyào tàntǎo yīxià tuìhuàn huò zhèngcè. | F11: =HYPERLINK("https://youglish.com/pronounce/我们需要探讨一下退换货政策/chinese","🔍")
A12: 626 ĐPTM.pdf | B12: 11 | C12: 我们需要确认一下合同的有效期。 | D12: Chúng ta cần xác nhận thời hạn hiệu lực của hợp đồng. Wǒmen xūyào quèrèn yīxià hétóng de yǒuxiàoqí. | E12: 11 我们需要确认 一下合同的有 效期。 Chúng ta cần xác nhận thời hạn hiệu lực của hợp đồng. Wǒmen xūyào quèrèn yīxià hétóng de yǒuxiàoqí. | F12: =HYPERLINK("https://youglish.com/pronounce/我们需要确认一下合同的有效期/chinese","🔍")
A13: 626 ĐPTM.pdf | B13: 12 | C13: 我们是否可以讨论一下产品包装的问题？ | D13: Chúng ta có thể thảo luận về vấn đề đóng gói sản phẩm được không? Wǒmen shìfǒu kěyǐ tǎolùn yīxià chǎnpǐn bāozhuāng de wèntí? | E13: 12 我们是否可以 讨论一下产品 包装的问题？ Chúng ta có thể thảo luận về vấn đề đóng gói sản phẩm được không? Wǒmen shìfǒu kěyǐ tǎolùn yīxià chǎnpǐn bāozhuāng de wèntí? | F13: =HYPERLINK("https://youglish.com/pronounce/我们是否可以讨论一下产品包装的问题/chinese","🔍")
A14: 626 ĐPTM.pdf | B14: 13 | C14: 我们需要协商一下付款期限。 | D14: Chúng ta cần đàm phán về thời hạn thanh toán. Wǒmen xūyào xiéshāng yīxià fùkuǎn qíxiàn. | E14: 13 我们需要协商 一下付款期限。 Chúng ta cần đàm phán về thời hạn thanh toán. Wǒmen xūyào xiéshāng yīxià fùkuǎn qíxiàn. | F14: =HYPERLINK("https://youglish.com/pronounce/我们需要协商一下付款期限/chinese","🔍")
A15: 626 ĐPTM.pdf | B15: 14 | C15: 我们需要确认一下发票的具体要求。 | D15: Chúng ta cần xác nhận yêu cầu cụ thể về hóa đơn. Wǒmen xūyào quèrèn yīxià fāpiào de jùtǐ yāoqiú. | E15: 14 我们需要确认 一下发票的具 体要求。 Chúng ta cần xác nhận yêu cầu cụ thể về hóa đơn. Wǒmen xūyào quèrèn yīxià fāpiào de jùtǐ yāoqiú. | F15: =HYPERLINK("https://youglish.com/pronounce/我们需要确认一下发票的具体要求/chinese","🔍")
A16: 626 ĐPTM.pdf | B16: 15 | C16: 我们是否可以讨论一下产品的规格要求？ | D16: Chúng ta có thể thảo luận về yêu cầu kỹ thuật của sản phẩm được không? Wǒmen shìfǒu kěyǐ tǎolùn yīxià chǎnpǐn de guīgé yāoqiú? | E16: 15 我们是否可以 讨论一下产品 的规格要求？ Chúng ta có thể thảo luận về yêu cầu kỹ thuật của sản phẩm được không? Wǒmen shìfǒu kěyǐ tǎolùn yīxià chǎnpǐn de guīgé yāoqiú? | F16: =HYPERLINK("https://youglish.com/pronounce/我们是否可以讨论一下产品的规格要求/chinese","🔍")
A17: 626 ĐPTM.pdf | B17: 16 | C17: 我们需要协商一下产品数量的具体要求。 | D17: Chúng ta cần đàm phán về yêu cầu cụ thể về số lượng sản phẩm. Wǒmen xūyào xiéshāng yīxià chǎnpǐn shùliàng de jùtǐ yāoqiú. | E17: 16 我们需要协商 一下产品数量 的具体要求。 Chúng ta cần đàm phán về yêu cầu cụ thể về số lượng sản phẩm. Wǒmen xūyào xiéshāng yīxià chǎnpǐn shùliàng de jùtǐ yāoqiú. | F17: =HYPERLINK("https://youglish.com/pronounce/我们需要协商一下产品数量的具体要求/chinese","🔍")
A18: 626 ĐPTM.pdf | B18: 17 | C18: 我们是否可以讨论一下产品的交付方式？ | D18: Chúng ta có thể thảo luận về phương thức giao hàng sản phẩm được không? Wǒmen shìfǒu kěyǐ tǎolùn yīxià chǎnpǐn de jiāofù fāngshì? | E18: 17 我们是否可以 讨论一下产品 的交付方式？ Chúng ta có thể thảo luận về phương thức giao hàng sản phẩm được không? Wǒmen shìfǒu kěyǐ tǎolùn yīxià chǎnpǐn de jiāofù fāngshì? | F18: =HYPERLINK("https://youglish.com/pronounce/我们是否可以讨论一下产品的交付方式/chinese","🔍")
A19: 626 ĐPTM.pdf | B19: 18 | C19: 我们需要确认一下产品保质期的具体要求。 | D19: Chúng ta cần xác nhận yêu cầu cụ thể về thời hạn bảo hành sản phẩm. Wǒmen xūyào quèrèn yīxià chǎnpǐn bǎo zhì qí de jùtǐ yāoqiú. | E19: 18 我们需要确认 一下产品保质 期的具体要求。 Chúng ta cần xác nhận yêu cầu cụ thể về thời hạn bảo hành sản phẩm. Wǒmen xūyào quèrèn yīxià chǎnpǐn bǎo zhì qí de jùtǐ yāoqiú. | F19: =HYPERLINK("https://youglish.com/pronounce/我们需要确认一下产品保质期的具体要求/chinese","🔍")
A20: 626 ĐPTM.pdf | B20: 19 | C20: 我们需要协商一下产品的标识要求。 | D20: Chúng ta cần đàm phán về yêu cầu đánh dấu sản phẩm. Wǒmen xūyào xiéshāng yīxià chǎnpǐn de biāozhì yāoqiú. | E20: 19 我们需要协商 一下产品的标 识要求。 Chúng ta cần đàm phán về yêu cầu đánh dấu sản phẩm. Wǒmen xūyào xiéshāng yīxià chǎnpǐn de biāozhì yāoqiú. | F20: =HYPERLINK("https://youglish.com/pronounce/我们需要协商一下产品的标识要求/chinese","🔍")
A21: 626 ĐPTM.pdf | B21: 20 | C21: 我们是否可以讨论一下合同的违约责任问题？ | D21: Chúng ta có thể thảo luận về trách nhiệm vi phạm hợp đồng được không? Wǒmen shìfǒu kěyǐ tǎolùn yīxià hétóng de wéiyuē zérèn wèntí? | E21: 20 我们是否可以 讨论一下合同 的违约责任问 题？ Chúng ta có thể thảo luận về trách nhiệm vi phạm hợp đồng được không? Wǒmen shìfǒu kěyǐ tǎolùn yīxià hétóng de wéiyuē zérèn wèntí? | F21: =HYPERLINK("https://youglish.com/pronounce/我们是否可以讨论一下合同的违约责任问题/chinese","🔍")
A22: 626 ĐPTM.pdf | B22: 21 | C22: 我们需要确认一下产品的测试要求。 | D22: Chúng ta cần xác nhận yêu cầu kiểm tra sản phẩm. Wǒmen xūyào quèrèn yīxià chǎnpǐn de cèshì yāoqiú. | E22: 21 我们需要确认 一下产品的测 试要求。 Chúng ta cần xác nhận yêu cầu kiểm tra sản phẩm. Wǒmen xūyào quèrèn yīxià chǎnpǐn de cèshì yāoqiú. | F22: =HYPERLINK("https://youglish.com/pronounce/我们需要确认一下产品的测试要求/chinese","🔍")
A23: 626 ĐPTM.pdf | B23: 22 | C23: 我们需要探讨一下供应商的资质要求。 | D23: Chúng ta cần thảo luận về yêu cầu chứng nhận và giấy phép của nhà cung cấp. Wǒmen xūyào tàntǎo yīxià gōngyìng shāng de zīzhì yāoqiú. | E23: 22 我们需要探讨 一下供应商的 资质要求。 Chúng ta cần thảo luận về yêu cầu chứng nhận và giấy phép của nhà cung cấp. Wǒmen xūyào tàntǎo yīxià gōngyìng shāng de zīzhì yāoqiú. | F23: =HYPERLINK("https://youglish.com/pronounce/我们需要探讨一下供应商的资质要求/chinese","🔍")
A24: 626 ĐPTM.pdf | B24: 23 | C24: 我们是否可以讨论一下产品的样品要求？ | D24: Chúng ta có thể thảo luận về yêu cầu mẫu sản phẩm được không? Wǒmen shìfǒu kěyǐ tǎolùn yīxià chǎnpǐn de yàngpǐn yāoqiú? | E24: 23 我们是否可以 讨论一下产品 的样品要求？ Chúng ta có thể thảo luận về yêu cầu mẫu sản phẩm được không? Wǒmen shìfǒu kěyǐ tǎolùn yīxià chǎnpǐn de yàngpǐn yāoqiú? | F24: =HYPERLINK("https://youglish.com/pronounce/我们是否可以讨论一下产品的样品要求/chinese","🔍")
A25: 626 ĐPTM.pdf | B25: 24 | C25: 我们需要协商一下合同的解释权。 | D25: Chúng ta cần đàm phán về quyền giải thích hợp đồng. Wǒmen xūyào xiéshāng yīxià hétóng de jiěshì quán. | E25: 24 我们需要协商 一下合同的解 释权。 Chúng ta cần đàm phán về quyền giải thích hợp đồng. Wǒmen xūyào xiéshāng yīxià hétóng de jiěshì quán. | F25: =HYPERLINK("https://youglish.com/pronounce/我们需要协商一下合同的解释权/chinese","🔍")
A26: 626 ĐPTM.pdf | B26: 25 | C26: 我们需要确认一下合同的签订地点。 | D26: Chúng ta cần xác nhận địa điểm ký kết hợp đồng. Wǒmen xūyào quèrèn yīxià hétóng de qiāndìng dìdiǎn. | E26: 25 我们需要确认 一下合同的签 订地点。 Chúng ta cần xác nhận địa điểm ký kết hợp đồng. Wǒmen xūyào quèrèn yīxià hétóng de qiāndìng dìdiǎn. | F26: =HYPERLINK("https://youglish.com/pronounce/我们需要确认一下合同的签订地点/chinese","🔍")
A27: 626 ĐPTM.pdf | B27: 26 | C27: 我们需要协商一下合同的语言版本。 | D27: Chúng ta cần đàm phán về phiên bản ngôn ngữ của hợp đồng. Wǒmen xūyào xiéshāng yīxià hétóng de yǔyán bǎnběn. | E27: 26 我们需要协商 一下合同的语 言版本。 Chúng ta cần đàm phán về phiên bản ngôn ngữ của hợp đồng. Wǒmen xūyào xiéshāng yīxià hétóng de yǔyán bǎnběn. | F27: =HYPERLINK("https://youglish.com/pronounce/我们需要协商一下合同的语言版本/chinese","🔍")
A28: 626 ĐPTM.pdf | B28: 27 | C28: 我们是否可以讨论一下产品的安全要求？ | D28: Chúng ta có thể thảo luận về yêu cầu an toàn của sản phẩm không? Wǒmen shìfǒu kěyǐ tǎolùn yīxià chǎnpǐn de ānquán yāoqiú? | E28: 27 我们是否可以 讨论一下产品 的安全要求？ Chúng ta có thể thảo luận về yêu cầu an toàn của sản phẩm không? Wǒmen shìfǒu kěyǐ tǎolùn yīxià chǎnpǐn de ānquán yāoqiú? | F28: =HYPERLINK("https://youglish.com/pronounce/我们是否可以讨论一下产品的安全要求/chinese","🔍")
A29: 626 ĐPTM.pdf | B29: 28 | C29: 我们需要探讨一下付款的具体细节。 | D29: Chúng ta cần thảo luận chi tiết về việc thanh toán. Wǒmen xūyào tàntǎo yīxià fùkuǎn de jùtǐ xìjié. | E29: 28 我们需要探讨 一下付款的具 体细节。 Chúng ta cần thảo luận chi tiết về việc thanh toán. Wǒmen xūyào tàntǎo yīxià fùkuǎn de jùtǐ xìjié. | F29: =HYPERLINK("https://youglish.com/pronounce/我们需要探讨一下付款的具体细节/chinese","🔍")
A30: 626 ĐPTM.pdf | B30: 29 | C30: 我们需要协商一下运输保险的具体要求。 | D30: Chúng ta cần thương lượng về yêu cầu bảo hiểm vận chuyển cụ thể. Wǒmen xūyào xiéshāng yīxià yùnshū bǎoxiǎn de jùtǐ yāoqiú. | E30: 29 我们需要协商 一下运输保险 的具体要求。 Chúng ta cần thương lượng về yêu cầu bảo hiểm vận chuyển cụ thể. Wǒmen xūyào xiéshāng yīxià yùnshū bǎoxiǎn de jùtǐ yāoqiú. | F30: =HYPERLINK("https://youglish.com/pronounce/我们需要协商一下运输保险的具体要求/chinese","🔍")
A31: 626 ĐPTM.pdf | B31: 30 | C31: 我们需要确认一下产品的产地要求。 | D31: Chúng ta cần xác nhận yêu cầu xuất xứ sản phẩm. Wǒmen xūyào quèrèn yīxià chǎnpǐn de chǎndì yāoqiú. | E31: 30 我们需要确认 一下产品的产 地要求。 Chúng ta cần xác nhận yêu cầu xuất xứ sản phẩm. Wǒmen xūyào quèrèn yīxià chǎnpǐn de chǎndì yāoqiú. | F31: =HYPERLINK("https://youglish.com/pronounce/我们需要确认一下产品的产地要求/chinese","🔍")
A32: 626 ĐPTM.pdf | B32: 31 | C32: 我们是否可以讨论一下产品的包装要求？ | D32: Chúng ta có thể thảo luận về yêu cầu đóng gói sản phẩm không? Wǒmen shìfǒu kěyǐ tǎolùn yīxià chǎnpǐn de bāozhuāng yāoqiú? | E32: 31 我们是否可以 讨论一下产品 的包装要求？ Chúng ta có thể thảo luận về yêu cầu đóng gói sản phẩm không? Wǒmen shìfǒu kěyǐ tǎolùn yīxià chǎnpǐn de bāozhuāng yāoqiú? | F32: =HYPERLINK("https://youglish.com/pronounce/我们是否可以讨论一下产品的包装要求/chinese","🔍")
A33: 626 ĐPTM.pdf | B33: 32 | C33: 我们需要协商一下质量标准的测试方法。 | D33: Chúng ta cần thương lượng về phương pháp kiểm tra tiêu chuẩn chất lượng. Wǒmen xūyào xiéshāng yīxià zhìliàng biāozhǔn dì cèshì fāngfǎ. | E33: 32 我们需要协商 一下质量标准 的测试方法。 Chúng ta cần thương lượng về phương pháp kiểm tra tiêu chuẩn chất lượng. Wǒmen xūyào xiéshāng yīxià zhìliàng biāozhǔn dì cèshì fāngfǎ. | F33: =HYPERLINK("https://youglish.com/pronounce/我们需要协商一下质量标准的测试方法/chinese","🔍")
A34: 626 ĐPTM.pdf | B34: 33 | C34: 我们需要确认一下产品的保修期要求。 | D34: Chúng ta cần xác nhận yêu cầu thời hạn bảo hành sản phẩm. Wǒmen xūyào quèrèn yīxià chǎnpǐn de bǎoxiū qī yāoqiú. | E34: 33 我们需要确认 一下产品的保 修期要求。 Chúng ta cần xác nhận yêu cầu thời hạn bảo hành sản phẩm. Wǒmen xūyào quèrèn yīxià chǎnpǐn de bǎoxiū qī yāoqiú. | F34: =HYPERLINK("https://youglish.com/pronounce/我们需要确认一下产品的保修期要求/chinese","🔍")
A35: 626 ĐPTM.pdf | B35: 34 | C35: 我们需要探讨一下产品的环保要求。 | D35: Chúng ta cần thảo luận về yêu cầu bảo vệ môi trường của sản phẩm. Wǒmen xūyào tàntǎo yīxià chǎnpǐn de huánbǎo yāoqiú. | E35: 34 我们需要探讨 一下产品的环 保要求。 Chúng ta cần thảo luận về yêu cầu bảo vệ môi trường của sản phẩm. Wǒmen xūyào tàntǎo yīxià chǎnpǐn de huánbǎo yāoqiú. | F35: =HYPERLINK("https://youglish.com/pronounce/我们需要探讨一下产品的环保要求/chinese","🔍")
A36: 626 ĐPTM.pdf | B36: 35 | C36: 我们是否可以讨论一下产品的性能要求？ | D36: Chúng ta có thể thảo luận về yêu cầu hiệu suất sản phẩm không? Wǒmen shìfǒu kěyǐ tǎolùn yīxià chǎnpǐn dì xìngnéng yāoqiú? | E36: 35 我们是否可以 讨论一下产品 的性能要求？ Chúng ta có thể thảo luận về yêu cầu hiệu suất sản phẩm không? Wǒmen shìfǒu kěyǐ tǎolùn yīxià chǎnpǐn dì xìngnéng yāoqiú? | F36: =HYPERLINK("https://youglish.com/pronounce/我们是否可以讨论一下产品的性能要求/chinese","🔍")
A37: 626 ĐPTM.pdf | B37: 36 | C37: 我们需要协商一下产品的售后服务。 | D37: Chúng ta cần thương lượng về dịch vụ hậu mãi của sản phẩm. Wǒmen xūyào xiéshāng yīxià chǎnpǐn de shòuhòu fúwù. | E37: 36 我们需要协商 一下产品的售 后服务。 Chúng ta cần thương lượng về dịch vụ hậu mãi của sản phẩm. Wǒmen xūyào xiéshāng yīxià chǎnpǐn de shòuhòu fúwù. | F37: =HYPERLINK("https://youglish.com/pronounce/我们需要协商一下产品的售后服务/chinese","🔍")
A38: 626 ĐPTM.pdf | B38: 37 | C38: 我们需要确认一下产品的生产周期。 | D38: Chúng ta cần xác nhận chu kỳ sản xuất sản phẩm. Wǒmen xūyào quèrèn yīxià chǎnpǐn de shēngchǎn zhōuqí. | E38: 37 我们需要确认 一下产品的生 产周期。 Chúng ta cần xác nhận chu kỳ sản xuất sản phẩm. Wǒmen xūyào quèrèn yīxià chǎnpǐn de shēngchǎn zhōuqí. | F38: =HYPERLINK("https://youglish.com/pronounce/我们需要确认一下产品的生产周期/chinese","🔍")
A39: 626 ĐPTM.pdf | B39: 38 | C39: 我们需要探讨一下合同的生效条件。 | D39: Chúng ta cần thảo luận về điều kiện có hiệu lực của hợp đồng. Wǒmen xūyào tàntǎo yīxià hétóng de shēngxiào tiáojiàn. | E39: 38 我们需要探讨 一下合同的生 效条件。 Chúng ta cần thảo luận về điều kiện có hiệu lực của hợp đồng. Wǒmen xūyào tàntǎo yīxià hétóng de shēngxiào tiáojiàn. | F39: =HYPERLINK("https://youglish.com/pronounce/我们需要探讨一下合同的生效条件/chinese","🔍")
A40: 626 ĐPTM.pdf | B40: 39 | C40: 我们需要协商一下产品的标准包装数量。 | D40: Chúng ta cần thương lượng về số lượng đóng gói tiêu chuẩn của sản phẩm. Wǒmen xūyào xiéshāng yīxià chǎnpǐn de biāozhǔn bāozhuāng shùliàng. | E40: 39 我们需要协商 一下产品的标 准包装数量。 Chúng ta cần thương lượng về số lượng đóng gói tiêu chuẩn của sản phẩm. Wǒmen xūyào xiéshāng yīxià chǎnpǐn de biāozhǔn bāozhuāng shùliàng. | F40: =HYPERLINK("https://youglish.com/pronounce/我们需要协商一下产品的标准包装数量/chinese","🔍")
A41: 626 ĐPTM.pdf | B41: 40 | C41: 我们是否可以讨论一下产品的使用说明书问题？ | D41: Chúng ta có thể thảo luận về vấn đề sách hướng dẫn sử dụng sản phẩm không? Wǒmen shìfǒu kěyǐ tǎolùn yīxià chǎnpǐn de shǐyòng shuōmíngshū wèntí? | E41: 40 我们是否可以 讨论一下产品 的使用说明书 问题？ Chúng ta có thể thảo luận về vấn đề sách hướng dẫn sử dụng sản phẩm không? Wǒmen shìfǒu kěyǐ tǎolùn yīxià chǎnpǐn de shǐyòng shuōmíngshū wèntí? | F41: =HYPERLINK("https://youglish.com/pronounce/我们是否可以讨论一下产品的使用说明书问题/chinese","🔍")
A42: 626 ĐPTM.pdf | B42: 41 | C42: 我们需要达成一个有利于双方的协议。 | D42: Chúng ta cần đạt được một thỏa thuận có lợi cho cả hai bên. Wǒmen xūyào dáchéng yīgè yǒu lìyú shuāngfāng de xiéyì. | E42: 41 我们需要达成 一个有利于双 方的协议。 Chúng ta cần đạt được một thỏa thuận có lợi cho cả hai bên. Wǒmen xūyào dáchéng yīgè yǒu lìyú shuāngfāng de xiéyì. | F42: =HYPERLINK("https://youglish.com/pronounce/我们需要达成一个有利于双方的协议/chinese","🔍")
A43: 626 ĐPTM.pdf | B43: 42 | C43: 我们需要澄清一些条款以确保我们都理解了它们的含义。 | D43: Chúng ta cần làm rõ một số điều khoản để đảm bảo chúng ta hiểu ý nghĩa của chúng. Wǒmen xūyào chéngqīng yīxiē tiáokuǎn yǐ quèbǎo wǒmen dōu lǐjiěle tāmen de hányì. | E43: 42 我们需要澄清 一些条款以确 保我们都理解 了它们的含 义。 Chúng ta cần làm rõ một số điều khoản để đảm bảo chúng ta hiểu ý nghĩa của chúng. Wǒmen xūyào chéngqīng yīxiē tiáokuǎn yǐ quèbǎo wǒmen dōu lǐjiěle tāmen de hányì. | F43: =HYPERLINK("https://youglish.com/pronounce/我们需要澄清一些条款以确保我们都理解了它们的含义/chinese","🔍")
A44: 626 ĐPTM.pdf | B44: 43 | C44: 我们需要讨论付款方式。 | D44: Chúng ta cần thảo luận về cách thanh toán. Wǒmen xūyào tǎolùn fùkuǎn fāngshì. | E44: 43 我们需要讨论 付款方式。 Chúng ta cần thảo luận về cách thanh toán. Wǒmen xūyào tǎolùn fùkuǎn fāngshì. | F44: =HYPERLINK("https://youglish.com/pronounce/我们需要讨论付款方式/chinese","🔍")
A45: 626 ĐPTM.pdf | B45: 44 | C45: 我们需要确定货物的数量和交付时间。 | D45: Chúng ta cần xác định số lượng hàng hóa và thời gian giao hàng. Wǒmen xūyào quèdìng huòwù de shùliàng hé jiāofù shíjiān. | E45: 44 我们需要确定 货物的数量和 交付时间。 Chúng ta cần xác định số lượng hàng hóa và thời gian giao hàng. Wǒmen xūyào quèdìng huòwù de shùliàng hé jiāofù shíjiān. | F45: =HYPERLINK("https://youglish.com/pronounce/我们需要确定货物的数量和交付时间/chinese","🔍")
A46: 626 ĐPTM.pdf | B46: 45 | C46: 我们需要协商有关货物质量的条款。 | D46: Chúng ta cần đàm phán về điều khoản liên quan đến chất lượng hàng hóa. Wǒmen xūyào xiéshāng yǒuguān huòwù zhí liàng de tiáokuǎn. | E46: 45 我们需要协商 有关货物质量 的条款。 Chúng ta cần đàm phán về điều khoản liên quan đến chất lượng hàng hóa. Wǒmen xūyào xiéshāng yǒuguān huòwù zhí liàng de tiáokuǎn. | F46: =HYPERLINK("https://youglish.com/pronounce/我们需要协商有关货物质量的条款/chinese","🔍")
A47: 626 ĐPTM.pdf | B47: 46 | C47: 我们需要讨论货物的保险责任。 | D47: Chúng ta cần thảo luận về trách nhiệm bảo hiểm hàng hóa. Wǒmen xūyào tǎolùn huòwù de bǎoxiǎn zérèn. | E47: 46 我们需要讨论 货物的保险责 任。 Chúng ta cần thảo luận về trách nhiệm bảo hiểm hàng hóa. Wǒmen xūyào tǎolùn huòwù de bǎoxiǎn zérèn. | F47: =HYPERLINK("https://youglish.com/pronounce/我们需要讨论货物的保险责任/chinese","🔍")
A48: 626 ĐPTM.pdf | B48: 47 | C48: 我们需要商讨可能的违约和争议解决方案。 | D48: Chúng ta cần thảo luận về các giải pháp có thể xảy ra khi vi phạm hợp đồng và giải quyết tranh chấp. Wǒmen xūyào shāngtǎo kěnéng de wéiyuē hé zhēngyì jiějué fāng'àn. | E48: 47 我们需要商讨 可能的违约和 争议解决方 案。 Chúng ta cần thảo luận về các giải pháp có thể xảy ra khi vi phạm hợp đồng và giải quyết tranh chấp. Wǒmen xūyào shāngtǎo kěnéng de wéiyuē hé zhēngyì jiějué fāng'àn. | F48: =HYPERLINK("https://youglish.com/pronounce/我们需要商讨可能的违约和争议解决方案/chinese","🔍")
A49: 626 ĐPTM.pdf | B49: 48 | C49: 我们需要协商有关配送和运输的条款。 | D49: Chúng ta cần đàm phán về các điều khoản liên quan đến vận chuyển và giao hàng. Wǒmen xūyào xiéshāng yǒuguān pèisòng hé yùnshū de tiáokuǎn. | E49: 48 我们需要协商 有关配送和运 输的条款。 Chúng ta cần đàm phán về các điều khoản liên quan đến vận chuyển và giao hàng. Wǒmen xūyào xiéshāng yǒuguān pèisòng hé yùnshū de tiáokuǎn. | F49: =HYPERLINK("https://youglish.com/pronounce/我们需要协商有关配送和运输的条款/chinese","🔍")
A50: 626 ĐPTM.pdf | B50: 49 | C50: 我们需要讨论可能的延误和遗漏。 | D50: Chúng ta cần thảo luận về khả năng chậm trễ và thiếu sót có thể xảy ra. Wǒmen xūyào tǎolùn kěnéng de yánwù hé yílòu. | E50: 49 我们需要讨论 可能的延误和 遗漏。 Chúng ta cần thảo luận về khả năng chậm trễ và thiếu sót có thể xảy ra. Wǒmen xūyào tǎolùn kěnéng de yánwù hé yílòu. | F50: =HYPERLINK("https://youglish.com/pronounce/我们需要讨论可能的延误和遗漏/chinese","🔍")
A51: 626 ĐPTM.pdf | B51: 50 | C51: 我们需要协商关于商品的规格和质量标准。 | D51: Chúng ta cần đàm phán về các tiêu chuẩn về quy cách và chất lượng hàng hóa. Wǒmen xūyào xiéshāng guānyú shāngpǐn de guīgé hé zhìliàng biāozhǔn. | E51: 50 我们需要协商 关于商品的规 格和质量标 准。 Chúng ta cần đàm phán về các tiêu chuẩn về quy cách và chất lượng hàng hóa. Wǒmen xūyào xiéshāng guānyú shāngpǐn de guīgé hé zhìliàng biāozhǔn. | F51: =HYPERLINK("https://youglish.com/pronounce/我们需要协商关于商品的规格和质量标准/chinese","🔍")
A52: 626 ĐPTM.pdf | B52: 51 | C52: 我们需要确定责任分配，尤其是在货物损坏或丢失的情况下。 | D52: Chúng ta cần xác định phân chia trách nhiệm, đặc biệt là trong trường hợp hàng hóa bị hư hỏng hoặc bị mất. Wǒmen xūyào quèdìng zérèn fēnpèi, yóuqí shì zài huòwù sǔnhuài huò diūshī de qíngkuàng xià. | E52: 51 我们需要确定 责任分配，尤 其是在货物损 坏或丢失的情 况下。 Chúng ta cần xác định phân chia trách nhiệm, đặc biệt là trong trường hợp hàng hóa bị hư hỏng hoặc bị mất. Wǒmen xūyào quèdìng zérèn fēnpèi, yóuqí shì zài huòwù sǔnhuài huò diūshī de qíngkuàng xià. | F52: =HYPERLINK("https://youglish.com/pronounce/我们需要确定责任分配尤其是在货物损坏或丢失的情况下/chinese","🔍")
A53: 626 ĐPTM.pdf | B53: 52 | C53: 我们需要讨论有关可能的商品缺陷和退货的条款。 | D53: Chúng ta cần thảo luận về các điều khoản liên quan đến khả năng hàng hóa bị lỗi và chính sách trả hàng. Wǒmen xūyào tǎolùn yǒuguān kěnéng de shāngpǐn quēxiàn hé tuìhuò de tiáokuǎn. | E53: 52 我们需要讨论 有关可能的商 品缺陷和退货 的条款。 Chúng ta cần thảo luận về các điều khoản liên quan đến khả năng hàng hóa bị lỗi và chính sách trả hàng. Wǒmen xūyào tǎolùn yǒuguān kěnéng de shāngpǐn quēxiàn hé tuìhuò de tiáokuǎn. | F53: =HYPERLINK("https://youglish.com/pronounce/我们需要讨论有关可能的商品缺陷和退货的条款/chinese","🔍")
A54: 626 ĐPTM.pdf | B54: 53 | C54: 我们需要确定有关保修和售后服务的条款。 | D54: Chúng ta cần xác định các điều khoản về bảo hành và dịch vụ sau bán hàng. Wǒmen xūyào quèdìng yǒuguān bǎoxiū hé shòuhòu fúwù de tiáokuǎn. | E54: 53 我们需要确定 有关保修和售 后服务的条 款。 Chúng ta cần xác định các điều khoản về bảo hành và dịch vụ sau bán hàng. Wǒmen xūyào quèdìng yǒuguān bǎoxiū hé shòuhòu fúwù de tiáokuǎn. | F54: =HYPERLINK("https://youglish.com/pronounce/我们需要确定有关保修和售后服务的条款/chinese","🔍")
A55: 626 ĐPTM.pdf | B55: 54 | C55: 我们需要讨论货物的验收程序和标准。 | D55: Chúng ta cần thảo luận về quy trình và tiêu chuẩn kiểm tra hàng hóa. Wǒmen xūyào tǎolùn huòwù de yànshōu chéngxù hé biāozhǔn. | E55: 54 我们需要讨论 货物的验收程 序和标准。 Chúng ta cần thảo luận về quy trình và tiêu chuẩn kiểm tra hàng hóa. Wǒmen xūyào tǎolùn huòwù de yànshōu chéngxù hé biāozhǔn. | F55: =HYPERLINK("https://youglish.com/pronounce/我们需要讨论货物的验收程序和标准/chinese","🔍")
A56: 626 ĐPTM.pdf | B56: 55 | C56: 我们需要协商有关货物来源和生产地的条款。 | D56: Chúng ta cần đàm phán về các điều khoản liên quan đến nguồn gốc và địa điểm sản xuất hàng hóa. Wǒmen xūyào xiéshāng yǒuguān huòwù láiyuán hé shēngchǎndì de tiáokuǎn. | E56: 55 我们需要协商 有关货物来源 和生产地的条 款。 Chúng ta cần đàm phán về các điều khoản liên quan đến nguồn gốc và địa điểm sản xuất hàng hóa. Wǒmen xūyào xiéshāng yǒuguān huòwù láiyuán hé shēngchǎndì de tiáokuǎn. | F56: =HYPERLINK("https://youglish.com/pronounce/我们需要协商有关货物来源和生产地的条款/chinese","🔍")
A57: 626 ĐPTM.pdf | B57: 56 | C57: 我们需要确定有关付款期限和利率的条款。 | D57: Chúng ta cần xác định các điều khoản về thời hạn thanh toán và lãi suất. Wǒmen xūyào quèdìng yǒuguān fùkuǎn qíxiàn hé lìlǜ de tiáokuǎn. | E57: 56 我们需要确定 有关付款期限 和利率的条款。 Chúng ta cần xác định các điều khoản về thời hạn thanh toán và lãi suất. Wǒmen xūyào quèdìng yǒuguān fùkuǎn qíxiàn hé lìlǜ de tiáokuǎn. | F57: =HYPERLINK("https://youglish.com/pronounce/我们需要确定有关付款期限和利率的条款/chinese","🔍")
A58: 626 ĐPTM.pdf | B58: 57 | C58: 我们需要讨论有关可能的违约和罚款的条款。 | D58: Chúng ta cần thảo luận về các điều khoản liên quan đến khả năng vi phạm hợp đồng và phí phạt. Wǒmen xūyào tǎolùn yǒuguān kěnéng de wéiyuē hé fákuǎn de tiáokuǎn. | E58: 57 我们需要讨论 有关可能的违 约和罚款的条 款。 Chúng ta cần thảo luận về các điều khoản liên quan đến khả năng vi phạm hợp đồng và phí phạt. Wǒmen xūyào tǎolùn yǒuguān kěnéng de wéiyuē hé fákuǎn de tiáokuǎn. | F58: =HYPERLINK("https://youglish.com/pronounce/我们需要讨论有关可能的违约和罚款的条款/chinese","🔍")
A59: 626 ĐPTM.pdf | B59: 58 | C59: 我们需要协商关于可能的知识产权纠纷的条款。 | D59: Chúng ta cần đàm phán về các điều khoản liên quan đến tranh chấp sở hữu trí tuệ có thể xảy ra. Wǒmen xūyào xiéshāng guānyú kěnéng de zhīshì chǎnquán jiūfēn de tiáokuǎn. | E59: 58 我们需要协商 关于可能的知 识产权纠纷的 条款。 Chúng ta cần đàm phán về các điều khoản liên quan đến tranh chấp sở hữu trí tuệ có thể xảy ra. Wǒmen xūyào xiéshāng guānyú kěnéng de zhīshì chǎnquán jiūfēn de tiáokuǎn. | F59: =HYPERLINK("https://youglish.com/pronounce/我们需要协商关于可能的知识产权纠纷的条款/chinese","🔍")
A60: 626 ĐPTM.pdf | B60: 59 | C60: 我们需要确定有关保密和保护商业机密的条款。 | D60: Chúng ta cần xác định các điều khoản về bảo mật và bảo vệ bí mật thương mại. Wǒmen xūyào quèdìng yǒuguān bǎomì hé bǎohù shāngyèjīmì de tiáokuǎn. | E60: 59 我们需要确定 有关保密和保 护商业机密的 条款。 Chúng ta cần xác định các điều khoản về bảo mật và bảo vệ bí mật thương mại. Wǒmen xūyào quèdìng yǒuguān bǎomì hé bǎohù shāngyèjīmì de tiáokuǎn. | F60: =HYPERLINK("https://youglish.com/pronounce/我们需要确定有关保密和保护商业机密的条款/chinese","🔍")
A61: 626 ĐPTM.pdf | B61: 60 | C61: 我们需要更改一下付款方式， 您有没有任何建议？ | D61: Chúng tôi cần thay đổi phương thức thanh toán, anh/cô có đề xuất nào không? Wǒmen xūyào gēnggǎi yīxià fùkuǎn fāngshì, nín yǒu méiyǒu rènhé jiànyì? | E61: 60 我们需要更改 一下付款方式， 您有没有任何 建议？ Chúng tôi cần thay đổi phương thức thanh toán, anh/cô có đề xuất nào không? Wǒmen xūyào gēnggǎi yīxià fùkuǎn fāngshì, nín yǒu méiyǒu rènhé jiànyì? | F61: =HYPERLINK("https://youglish.com/pronounce/我们需要更改一下付款方式您有没有任何建议/chinese","🔍")
A62: 626 ĐPTM.pdf | B62: 61 | C62: 请提供您的货物的详细清单和规格以便我们审核。 | D62: Vui lòng cung cấp danh sách chi tiết và thông số kỹ thuật hàng hoá của anh/cô để chúng tôi có thể kiểm tra. Qǐng tígōng nín de huòwù de xiángxì qīngdān hé guīgé yǐbiàn wǒmen shěnhé. | E62: 61 请提供您的货 物的详细清单 和规格以便我 们审核。 Vui lòng cung cấp danh sách chi tiết và thông số kỹ thuật hàng hoá của anh/cô để chúng tôi có thể kiểm tra. Qǐng tígōng nín de huòwù de xiángxì qīngdān hé guīgé yǐbiàn wǒmen shěnhé. | F62: =HYPERLINK("https://youglish.com/pronounce/请提供您的货物的详细清单和规格以便我们审核/chinese","🔍")
A63: 626 ĐPTM.pdf | B63: 62 | C63: 我们需要对商品进行检验， 请提供相关检验报告。 | D63: Chúng tôi cần kiểm tra hàng hoá, vui lòng cung cấp báo cáo kiểm định liên quan. Wǒmen xūyào duì shāngpǐn jìnxíng jiǎnyàn, qǐng tígōng xiāngguān jiǎnyàn bàogào. | E63: 62 我们需要对商 品进行检验， 请提供相关检 验报告。 Chúng tôi cần kiểm tra hàng hoá, vui lòng cung cấp báo cáo kiểm định liên quan. Wǒmen xūyào duì shāngpǐn jìnxíng jiǎnyàn, qǐng tígōng xiāngguān jiǎnyàn bàogào. | F63: =HYPERLINK("https://youglish.com/pronounce/我们需要对商品进行检验请提供相关检验报告/chinese","🔍")
A64: 626 ĐPTM.pdf | B64: 63 | C64: 我们需要更改一下交货时间 ，您方便吗？ | D64: Chúng tôi cần thay đổi thời gian giao hàng, anh/cô có thể linh động không? Wǒmen xūyào gēnggǎi yīxià jiāo huò shíjiān, nín fāngbiàn ma? | E64: 63 我们需要更改 一下交货时间 ，您方便吗？ Chúng tôi cần thay đổi thời gian giao hàng, anh/cô có thể linh động không? Wǒmen xūyào gēnggǎi yīxià jiāo huò shíjiān, nín fāngbiàn ma? | F64: =HYPERLINK("https://youglish.com/pronounce/我们需要更改一下交货时间您方便吗/chinese","🔍")
A65: 626 ĐPTM.pdf | B65: 64 | C65: 请提供您的银行账户信息， 以便我们安排付款。 | D65: Vui lòng cung cấp thông tin tài khoản ngân hàng của anh/cô để chúng tôi có thể sắp xếp thanh toán. Qǐng tígōng nín de yínháng zhànghù xìnxī, yǐbiàn wǒmen ānpái fùkuǎn. | E65: 64 请提供您的银 行账户信息， 以便我们安排 付款。 Vui lòng cung cấp thông tin tài khoản ngân hàng của anh/cô để chúng tôi có thể sắp xếp thanh toán. Qǐng tígōng nín de yínháng zhànghù xìnxī, yǐbiàn wǒmen ānpái fùkuǎn. | F65: =HYPERLINK("https://youglish.com/pronounce/请提供您的银行账户信息以便我们安排付款/chinese","🔍")
A66: 626 ĐPTM.pdf | B66: 65 | C66: 我们需要您提供商品的质量保证书。 | D66: Chúng tôi cần anh/cô cung cấp chứng nhận chất lượng cho hàng hoá. Wǒmen xūyào nín tígōng shāngpǐn de zhìliàng bǎozhèngshū. | E66: 65 我们需要您提 供商品的质量 保证书。 Chúng tôi cần anh/cô cung cấp chứng nhận chất lượng cho hàng hoá. Wǒmen xūyào nín tígōng shāngpǐn de zhìliàng bǎozhèngshū. | F66: =HYPERLINK("https://youglish.com/pronounce/我们需要您提供商品的质量保证书/chinese","🔍")
A67: 626 ĐPTM.pdf | B67: 66 | C67: 您能否为我们提供一些样品以供确认？ | D67: Anh/cô có thể cung cấp mẫu sản phẩm để chúng tôi xác nhận được không? Nín néng fǒu wèi wǒmen tígōng yīxiē yàngpǐn yǐ gōng quèrèn? | E67: 66 您能否为我们 提供一些样品 以供确认？ Anh/cô có thể cung cấp mẫu sản phẩm để chúng tôi xác nhận được không? Nín néng fǒu wèi wǒmen tígōng yīxiē yàngpǐn yǐ gōng quèrèn? | F67: =HYPERLINK("https://youglish.com/pronounce/您能否为我们提供一些样品以供确认/chinese","🔍")
A68: 626 ĐPTM.pdf | B68: 67 | C68: 我们需要您提供商品的产地证明。 | D68: Chúng tôi cần anh/cô cung cấp giấy chứng nhận xuất xứ cho hàng hoá. Wǒmen xūyào nín tígōng shāngpǐn de chǎndì zhèngmíng. | E68: 67 我们需要您提 供商品的产地 证明。 Chúng tôi cần anh/cô cung cấp giấy chứng nhận xuất xứ cho hàng hoá. Wǒmen xūyào nín tígōng shāngpǐn de chǎndì zhèngmíng. | F68: =HYPERLINK("https://youglish.com/pronounce/我们需要您提供商品的产地证明/chinese","🔍")
A69: 626 ĐPTM.pdf | B69: 68 | C69: 我们需要您提供出口许可证和相关文件。 | D69: Chúng tôi cần anh/cô cung cấp giấy phép xuất khẩu và các tài liệu liên quan. Wǒmen xūyào nín tígōng chūkǒu xǔkě zhèng hé xiāngguān wénjiàn. | E69: 68 我们需要您提 供出口许可证 和相关文件。 Chúng tôi cần anh/cô cung cấp giấy phép xuất khẩu và các tài liệu liên quan. Wǒmen xūyào nín tígōng chūkǒu xǔkě zhèng hé xiāngguān wénjiàn. | F69: =HYPERLINK("https://youglish.com/pronounce/我们需要您提供出口许可证和相关文件/chinese","🔍")
A70: 626 ĐPTM.pdf | B70: 69 | C70: 我们需要您提供商品的运输保险证明。 | D70: Chúng tôi cần anh/cô cung cấp chứng nhận bảo hiểm vận chuyển cho hàng hoá. Wǒmen xūyào nín tígōng shāngpǐn de yùnshū bǎoxiǎn zhèngmíng. | E70: 69 我们需要您提 供商品的运输 保险证明。 Chúng tôi cần anh/cô cung cấp chứng nhận bảo hiểm vận chuyển cho hàng hoá. Wǒmen xūyào nín tígōng shāngpǐn de yùnshū bǎoxiǎn zhèngmíng. | F70: =HYPERLINK("https://youglish.com/pronounce/我们需要您提供商品的运输保险证明/chinese","🔍")
A71: 626 ĐPTM.pdf | B71: 70 | C71: 我们需要对合同条款进行细节的商讨和确认。 | D71: Chúng tôi cần thương lượng và xác nhận các chi tiết liên quan đến điều khoản trong hợp đồng. Wǒmen xūyào duì hétóng tiáokuǎn jìnxíng xìjié de shāngtǎo hé quèrèn. | E71: 70 我们需要对合 同条款进行细 节的商讨和确 认。 Chúng tôi cần thương lượng và xác nhận các chi tiết liên quan đến điều khoản trong hợp đồng. Wǒmen xūyào duì hétóng tiáokuǎn jìnxíng xìjié de shāngtǎo hé quèrèn. | F71: =HYPERLINK("https://youglish.com/pronounce/我们需要对合同条款进行细节的商讨和确认/chinese","🔍")
A72: 626 ĐPTM.pdf | B72: 71 | C72: 我们需要您在合同中明确规定质量保证期限。 | D72: Chúng tôi cần anh/cô chỉ rõ thời hạn bảo hành trong hợp đồng. Wǒmen xūyào nín zài hétóng zhōng míngquè guīdìng zhí liàng bǎozhèng qíxiàn. | E72: 71 我们需要您在 合同中明确规 定质量保证期 限。 Chúng tôi cần anh/cô chỉ rõ thời hạn bảo hành trong hợp đồng. Wǒmen xūyào nín zài hétóng zhōng míngquè guīdìng zhí liàng bǎozhèng qíxiàn. | F72: =HYPERLINK("https://youglish.com/pronounce/我们需要您在合同中明确规定质量保证期限/chinese","🔍")
A73: 626 ĐPTM.pdf | B73: 72 | C73: 请提供您的公司营业执照和税务登记证明。 | D73: Vui lòng cung cấp giấy phép kinh doanh và giấy chứng nhận đăng ký thuế của công ty anh/cô. Qǐng tígōng nín de gōngsī yíngyè zhízhào hé shuìwù dēngjì zhèngmíng. | E73: 72 请提供您的公 司营业执照和 税务登记证 明。 Vui lòng cung cấp giấy phép kinh doanh và giấy chứng nhận đăng ký thuế của công ty anh/cô. Qǐng tígōng nín de gōngsī yíngyè zhízhào hé shuìwù dēngjì zhèngmíng. | F73: =HYPERLINK("https://youglish.com/pronounce/请提供您的公司营业执照和税务登记证明/chinese","🔍")
A74: 626 ĐPTM.pdf | B74: 73 | C74: 我们需要您提供海关报关单和相关文件。 | D74: Chúng tôi cần anh/cô cung cấp biên bản hải quan và các tài liệu liên quan. Wǒmen xūyào nín tígōng hǎiguān bàoguān dān hé xiāngguān wénjiàn. | E74: 73 我们需要您提 供海关报关单 和相关文件。 Chúng tôi cần anh/cô cung cấp biên bản hải quan và các tài liệu liên quan. Wǒmen xūyào nín tígōng hǎiguān bàoguān dān hé xiāngguān wénjiàn. | F74: =HYPERLINK("https://youglish.com/pronounce/我们需要您提供海关报关单和相关文件/chinese","🔍")
A75: 626 ĐPTM.pdf | B75: 74 | C75: 我们需要您在合同中明确规定支付方式和条款。 | D75: Chúng tôi cần anh/cô chỉ rõ phương thức và điều kiện thanh toán trong hợp đồng. Wǒmen xūyào nín zài hétóng zhōng míngquè guīdìng zhīfù fāngshì hé tiáokuǎn. | E75: 74 我们需要您在 合同中明确规 定支付方式和 条款。 Chúng tôi cần anh/cô chỉ rõ phương thức và điều kiện thanh toán trong hợp đồng. Wǒmen xūyào nín zài hétóng zhōng míngquè guīdìng zhīfù fāngshì hé tiáokuǎn. | F75: =HYPERLINK("https://youglish.com/pronounce/我们需要您在合同中明确规定支付方式和条款/chinese","🔍")
A76: 626 ĐPTM.pdf | B76: 75 | C76: 请提供您的商品的包装方式和包装材料规格。 | D76: Vui lòng cung cấp thông tin về cách đóng gói và quy cách vật liệu đóng gói của hàng hoá của anh/cô. Qǐng tígōng nín de shāngpǐn de bāozhuāng fāngshì hé bāozhuāng cáiliào guīgé. | E76: 75 请提供您的商 品的包装方式 Vui lòng cung cấp thông tin về cách đóng gói và quy cách vật liệu đóng gói của hàng hoá của anh/cô. Qǐng tígōng nín de shāngpǐn de bāozhuāng fāngshì hé bāozhuāng cáiliào guīgé. 和包装材料规 格。 | F76: =HYPERLINK("https://youglish.com/pronounce/请提供您的商品的包装方式和包装材料规格/chinese","🔍")
A77: 626 ĐPTM.pdf | B77: 76 | C77: 我们需要对货物进行验收， 请提供相关验收标准和流程。 | D77: Chúng tôi cần kiểm tra hàng hoá và yêu cầu anh/cô cung cấp các tiêu chuẩn và quy trình kiểm tra liên quan. Wǒmen xūyào duì huòwù jìnxíng yànshōu, qǐng tígōng xiāngguān yànshōu biāozhǔn hé liúchéng. | E77: 76 我们需要对货 物进行验收， 请提供相关验 收标准和流 程。 Chúng tôi cần kiểm tra hàng hoá và yêu cầu anh/cô cung cấp các tiêu chuẩn và quy trình kiểm tra liên quan. Wǒmen xūyào duì huòwù jìnxíng yànshōu, qǐng tígōng xiāngguān yànshōu biāozhǔn hé liúchéng. | F77: =HYPERLINK("https://youglish.com/pronounce/我们需要对货物进行验收请提供相关验收标准和流程/chinese","🔍")
A78: 626 ĐPTM.pdf | B78: 77 | C78: 我们需要您提供商品的使用说明和维修保养手册。 | D78: Chúng tôi cần anh/cô cung cấp hướng dẫn sử dụng và sổ tay bảo trì cho hàng hoá. Wǒmen xūyào nín tígōng shāngpǐn de shǐyòng shuōmíng hé wéixiū bǎoyǎng shǒucè. | E78: 77 我们需要您提 供商品的使用 说明和维修保 养手册。 Chúng tôi cần anh/cô cung cấp hướng dẫn sử dụng và sổ tay bảo trì cho hàng hoá. Wǒmen xūyào nín tígōng shāngpǐn de shǐyòng shuōmíng hé wéixiū bǎoyǎng shǒucè. | F78: =HYPERLINK("https://youglish.com/pronounce/我们需要您提供商品的使用说明和维修保养手册/chinese","🔍")
A79: 626 ĐPTM.pdf | B79: 78 | C79: 我们需要您提供商品的价格保证书。 | D79: Chúng tôi cần anh/cô cung cấp giấy chứng nhận giá của hàng hoá. Wǒmen xūyào nín tígōng shāngpǐn de jiàgé bǎozhèngshū. | E79: 78 我们需要您提 供商品的价格 保证书。 Chúng tôi cần anh/cô cung cấp giấy chứng nhận giá của hàng hoá. Wǒmen xūyào nín tígōng shāngpǐn de jiàgé bǎozhèngshū. | F79: =HYPERLINK("https://youglish.com/pronounce/我们需要您提供商品的价格保证书/chinese","🔍")
A80: 626 ĐPTM.pdf | B80: 79 | C80: 请提供您的公司的组织机构代码证明。 | D80: Vui lòng cung cấp giấy chứng nhận tổ chức của công ty anh/cô. Qǐng tígōng nín de gōngsī de zǔzhī jīgòu dàimǎ zhèngmíng. | E80: 79 请提供您的公 司的组织机构 代码证明。 Vui lòng cung cấp giấy chứng nhận tổ chức của công ty anh/cô. Qǐng tígōng nín de gōngsī de zǔzhī jīgòu dàimǎ zhèngmíng. | F80: =HYPERLINK("https://youglish.com/pronounce/请提供您的公司的组织机构代码证明/chinese","🔍")
A81: 626 ĐPTM.pdf | B81: 80 | C81: 我们需要您在合同中明确规定商品的规格和数量。 | D81: Chúng tôi cần bạn xác định rõ số lượng và quy cách hàng hóa trong hợp đồng. Wǒmen xūyào nín zài hétóng zhōng míngquè guīdìng shāngpǐn de guīgé hé shùliàng. | E81: 80 我们需要您在 合同中明确规 定商品的规格 和数量。 Chúng tôi cần bạn xác định rõ số lượng và quy cách hàng hóa trong hợp đồng. Wǒmen xūyào nín zài hétóng zhōng míngquè guīdìng shāngpǐn de guīgé hé shùliàng. | F81: =HYPERLINK("https://youglish.com/pronounce/我们需要您在合同中明确规定商品的规格和数量/chinese","🔍")
A82: 626 ĐPTM.pdf | B82: 81 | C82: 请提供您的公司的信用证证明以便我们确认付款方式。 | D82: Vui lòng cung cấp giấy chứng nhận tín dụng của công ty để chúng tôi xác nhận phương thức thanh toán. Qǐng tígōng nín de gōngsī de xìnyòng zhèng zhèngmíng yǐbiàn wǒmen quèrèn fùkuǎn fāngshì. | E82: 81 请提供您的公 司的信用证证 明以便我们确 认付款方式。 Vui lòng cung cấp giấy chứng nhận tín dụng của công ty để chúng tôi xác nhận phương thức thanh toán. Qǐng tígōng nín de gōngsī de xìnyòng zhèng zhèngmíng yǐbiàn wǒmen quèrèn fùkuǎn fāngshì. | F82: =HYPERLINK("https://youglish.com/pronounce/请提供您的公司的信用证证明以便我们确认付款方式/chinese","🔍")
A83: 626 ĐPTM.pdf | B83: 82 | C83: 我们需要您提供商品的外包装和内包装的标识。 | D83: Chúng tôi cần bạn cung cấp nhãn mác bên trong và bên ngoài của hàng hóa. Wǒmen xūyào nín tígōng shāngpǐn de wài bāozhuāng hé nèi bāozhuāng de biāozhì. | E83: 82 我们需要您提 供商品的外包 装和内包装的 标识。 Chúng tôi cần bạn cung cấp nhãn mác bên trong và bên ngoài của hàng hóa. Wǒmen xūyào nín tígōng shāngpǐn de wài bāozhuāng hé nèi bāozhuāng de biāozhì. | F83: =HYPERLINK("https://youglish.com/pronounce/我们需要您提供商品的外包装和内包装的标识/chinese","🔍")
A84: 626 ĐPTM.pdf | B84: 83 | C84: 我们需要您提供商品的进出口许可证明和相关证明文件。 | D84: Chúng tôi cần bạn cung cấp giấy chứng nhận xuất nhập khẩu và các tài liệu liên quan cho sản phẩm. Wǒmen xūyào nín tígōng shāngpǐn de jìn chūkǒu xǔkě zhèngmíng hé xiāngguān zhèngmíng wénjiàn. | E84: 83 我们需要您提 供商品的进出 口许可证明和 相关证明文 件。 Chúng tôi cần bạn cung cấp giấy chứng nhận xuất nhập khẩu và các tài liệu liên quan cho sản phẩm. Wǒmen xūyào nín tígōng shāngpǐn de jìn chūkǒu xǔkě zhèngmíng hé xiāngguān zhèngmíng wénjiàn. | F84: =HYPERLINK("https://youglish.com/pronounce/我们需要您提供商品的进出口许可证明和相关证明文件/chinese","🔍")
A85: 626 ĐPTM.pdf | B85: 84 | C85: 我们需要您提供商品的售后服务承诺书。 | D85: Chúng tôi cần bạn cung cấp cam kết dịch vụ hậu mãi cho sản phẩm. Wǒmen xūyào nín tígōng shāngpǐn de shòuhòu fúwù chéngnuò shū. | E85: 84 我们需要您提 供商品的售后 服务承诺书。 Chúng tôi cần bạn cung cấp cam kết dịch vụ hậu mãi cho sản phẩm. Wǒmen xūyào nín tígōng shāngpǐn de shòuhòu fúwù chéngnuò shū. | F85: =HYPERLINK("https://youglish.com/pronounce/我们需要您提供商品的售后服务承诺书/chinese","🔍")
A86: 626 ĐPTM.pdf | B86: 85 | C86: 我们需要您提供商品的检验合格证明。 | D86: Chúng tôi cần bạn cung cấp giấy chứng nhận kiểm định cho sản phẩm. Wǒmen xūyào nín tígōng shāngpǐn de jiǎnyàn hégé zhèngmíng. | E86: 85 我们需要您提 供商品的检验 合格证明。 Chúng tôi cần bạn cung cấp giấy chứng nhận kiểm định cho sản phẩm. Wǒmen xūyào nín tígōng shāngpǐn de jiǎnyàn hégé zhèngmíng. | F86: =HYPERLINK("https://youglish.com/pronounce/我们需要您提供商品的检验合格证明/chinese","🔍")
A87: 626 ĐPTM.pdf | B87: 86 | C87: 我们需要您提供商品的品质保证书和产品质量报告。 | D87: Chúng tôi cần bạn cung cấp giấy chứng nhận chất lượng và báo cáo chất lượng sản phẩm. Wǒmen xūyào nín tígōng shāngpǐn de pǐnzhí bǎozhèngshū hé chǎnpǐnzhí liàng bàogào. | E87: 86 我们需要您提 供商品的品质 保证书和产品 质量报告。 Chúng tôi cần bạn cung cấp giấy chứng nhận chất lượng và báo cáo chất lượng sản phẩm. Wǒmen xūyào nín tígōng shāngpǐn de pǐnzhí bǎozhèngshū hé chǎnpǐnzhí liàng bàogào. | F87: =HYPERLINK("https://youglish.com/pronounce/我们需要您提供商品的品质保证书和产品质量报告/chinese","🔍")
A88: 626 ĐPTM.pdf | B88: 87 | C88: 请提供您的公司的经营范围和注册资本证明。 | D88: Vui lòng cung cấp phạm vi kinh doanh và chứng nhận vốn đăng ký của công ty. Qǐng tígōng nín de gōngsī de jīngyíng fànwéi hé zhùcè zīběn zhèngmíng. | E88: 87 请提供您的公 司的经营范围 和注册资本证 明。 Vui lòng cung cấp phạm vi kinh doanh và chứng nhận vốn đăng ký của công ty. Qǐng tígōng nín de gōngsī de jīngyíng fànwéi hé zhùcè zīběn zhèngmíng. | F88: =HYPERLINK("https://youglish.com/pronounce/请提供您的公司的经营范围和注册资本证明/chinese","🔍")
A89: 626 ĐPTM.pdf | B89: 88 | C89: 我们需要您提供商品的品牌授权证明。 | D89: Chúng tôi cần bạn cung cấp giấy chứng nhận ủy quyền thương hiệu cho sản phẩm. Wǒmen xūyào nín tígōng shāngpǐn de pǐnpái shòuquán zhèngmíng. | E89: 88 我们需要您提 供商品的品牌 授权证明。 Chúng tôi cần bạn cung cấp giấy chứng nhận ủy quyền thương hiệu cho sản phẩm. Wǒmen xūyào nín tígōng shāngpǐn de pǐnpái shòuquán zhèngmíng. | F89: =HYPERLINK("https://youglish.com/pronounce/我们需要您提供商品的品牌授权证明/chinese","🔍")
A90: 626 ĐPTM.pdf | B90: 89 | C90: 我们需要对商品进行重量和数量的核对， 请提供相关证明文件。 | D90: Chúng tôi cần kiểm tra lại trọng lượng và số lượng hàng hóa, vui lòng cung cấp các tài liệu liên quan. Wǒmen xūyào duì shāngpǐn jìnxíng zhòngliàng hé shùliàng de héduì, qǐng tígōng xiāngguān zhèngmíng wénjiàn. | E90: 89 我们需要对商 品进行重量和 数量的核对， 请提供相关证 明文件。 Chúng tôi cần kiểm tra lại trọng lượng và số lượng hàng hóa, vui lòng cung cấp các tài liệu liên quan. Wǒmen xūyào duì shāngpǐn jìnxíng zhòngliàng hé shùliàng de héduì, qǐng tígōng xiāngguān zhèngmíng wénjiàn. | F90: =HYPERLINK("https://youglish.com/pronounce/我们需要对商品进行重量和数量的核对请提供相关证明文件/chinese","🔍")
A91: 626 ĐPTM.pdf | B91: 90 | C91: 我们需要您提供商品的国内销售授权书。 | D91: Chúng tôi cần bạn cung cấp giấy phép bán hàng trong nước cho sản phẩm. Wǒmen xūyào nín tígōng shāngpǐn de guónèi xiāoshòu shòuquán shū. | E91: 90 我们需要您提 供商品的国内 销售授权书。 Chúng tôi cần bạn cung cấp giấy phép bán hàng trong nước cho sản phẩm. Wǒmen xūyào nín tígōng shāngpǐn de guónèi xiāoshòu shòuquán shū. | F91: =HYPERLINK("https://youglish.com/pronounce/我们需要您提供商品的国内销售授权书/chinese","🔍")
A92: 626 ĐPTM.pdf | B92: 91 | C92: 请提供您的公司的税务清单以便我们审核。 | D92: Vui lòng cung cấp danh sách thuế của công ty để chúng tôi kiểm tra. Qǐng tígōng nín de gōngsī de shuìwù qīngdān yǐbiàn wǒmen shěnhé. | E92: 91 请提供您的公 司的税务清单 以便我们审 核。 Vui lòng cung cấp danh sách thuế của công ty để chúng tôi kiểm tra. Qǐng tígōng nín de gōngsī de shuìwù qīngdān yǐbiàn wǒmen shěnhé. | F92: =HYPERLINK("https://youglish.com/pronounce/请提供您的公司的税务清单以便我们审核/chinese","🔍")
A93: 626 ĐPTM.pdf | B93: 92 | C93: 我们需要您提供商品的相关技术参数和规格说明。 | D93: Chúng tôi cần bạn cung cấp thông số kỹ thuật và mô tả chi tiết quy cách của sản phẩm. Wǒmen xūyào nín tígōng shāngpǐn de xiāngguān jìshù cānshù hé guīgé shuōmíng. | E93: 92 我们需要您提 供商品的相关 技术参数和规 格说明。 Chúng tôi cần bạn cung cấp thông số kỹ thuật và mô tả chi tiết quy cách của sản phẩm. Wǒmen xūyào nín tígōng shāngpǐn de xiāngguān jìshù cānshù hé guīgé shuōmíng. | F93: =HYPERLINK("https://youglish.com/pronounce/我们需要您提供商品的相关技术参数和规格说明/chinese","🔍")
A94: 626 ĐPTM.pdf | B94: 93 | C94: 我们需要您提供商品的厂家出厂合格证明。 | D94: Chúng tôi cần bạn cung cấp giấy chứng nhận xuất xưởng của nhà sản xuất cho sản phẩm. Wǒmen xūyào nín tígōng shāngpǐn de chǎngjiā chūchǎng hégé zhèngmíng. | E94: 93 我们需要您提 供商品的厂家 出厂合格证 明。 Chúng tôi cần bạn cung cấp giấy chứng nhận xuất xưởng của nhà sản xuất cho sản phẩm. Wǒmen xūyào nín tígōng shāngpǐn de chǎngjiā chūchǎng hégé zhèngmíng. | F94: =HYPERLINK("https://youglish.com/pronounce/我们需要您提供商品的厂家出厂合格证明/chinese","🔍")
A95: 626 ĐPTM.pdf | B95: 94 | C95: 我们需要您提供商品的配件和附件清单。 | D95: Chúng tôi cần bạn cung cấp danh sách phụ kiện và bộ phận kèm theo của sản phẩm. Wǒmen xūyào nín tígōng shāngpǐn de pèijiàn hé fùjiàn qīngdān. | E95: 94 我们需要您提 供商品的配件 和附件清单。 Chúng tôi cần bạn cung cấp danh sách phụ kiện và bộ phận kèm theo của sản phẩm. Wǒmen xūyào nín tígōng shāngpǐn de pèijiàn hé fùjiàn qīngdān. | F95: =HYPERLINK("https://youglish.com/pronounce/我们需要您提供商品的配件和附件清单/chinese","🔍")
A96: 626 ĐPTM.pdf | B96: 95 | C96: 我们需要您提供商品的生产许可证明和生产厂家的资质证书。 | D96: Chúng tôi cần bạn cung cấp giấy phép sản xuất và chứng nhận năng lực sản xuất của nhà sản xuất. Wǒmen xūyào nín tígōng shāngpǐn de shēngchǎn xǔkě zhèngmíng hé shēngchǎn chǎngjiā de zīzhì zhèngshū. | E96: 95 我们需要您提 供商品的生产 许可证明和生 产厂家的资质 证书。 Chúng tôi cần bạn cung cấp giấy phép sản xuất và chứng nhận năng lực sản xuất của nhà sản xuất. Wǒmen xūyào nín tígōng shāngpǐn de shēngchǎn xǔkě zhèngmíng hé shēngchǎn chǎngjiā de zīzhì zhèngshū. | F96: =HYPERLINK("https://youglish.com/pronounce/我们需要您提供商品的生产许可证明和生产厂家的资质证书/chinese","🔍")
A97: 626 ĐPTM.pdf | B97: 96 | C97: 请提供您的公司的财务报表和资产负债表。 | D97: Vui lòng cung cấp báo cáo tài chính và bảng cân đối kế toán của công ty. Qǐng tígōng nín de gōngsī de cáiwù bàobiǎo hé zīchǎn fùzhài biǎo. | E97: 96 请提供您的公 司的财务报表 和资产负债 表。 Vui lòng cung cấp báo cáo tài chính và bảng cân đối kế toán của công ty. Qǐng tígōng nín de gōngsī de cáiwù bàobiǎo hé zīchǎn fùzhài biǎo. | F97: =HYPERLINK("https://youglish.com/pronounce/请提供您的公司的财务报表和资产负债表/chinese","🔍")
A98: 626 ĐPTM.pdf | B98: 97 | C98: 我们需要您提供商品的库存证明和库存清单。 | D98: Chúng tôi cần bạn cung cấp giấy chứng nhận kho của sản phẩm và danh sách hàng tồn kho. Wǒmen xūyào nín tígōng shāngpǐn de kùcún zhèngmíng hé kùcún qīngdān. | E98: 97 我们需要您提 供商品的库存 证明和库存清 单。 Chúng tôi cần bạn cung cấp giấy chứng nhận kho của sản phẩm và danh sách hàng tồn kho. Wǒmen xūyào nín tígōng shāngpǐn de kùcún zhèngmíng hé kùcún qīngdān. | F98: =HYPERLINK("https://youglish.com/pronounce/我们需要您提供商品的库存证明和库存清单/chinese","🔍")
A99: 626 ĐPTM.pdf | B99: 98 | C99: 我们需要您提供商品的安全生产许可证明和环境保护许可证明。 | D99: Chúng tôi cần bạn cung cấp giấy chứng nhận an toàn sản xuất và giấy phép bảo vệ môi trường của sản phẩm. Wǒmen xūyào nín tígōng shāngpǐn de ānquán shēngchǎn xǔkě zhèngmíng hé huánjìng bǎohù xǔkě zhèngmíng. | E99: 98 我们需要您提 供商品的安全 生产许可证明 和环境保护许 可证明。 Chúng tôi cần bạn cung cấp giấy chứng nhận an toàn sản xuất và giấy phép bảo vệ môi trường của sản phẩm. Wǒmen xūyào nín tígōng shāngpǐn de ānquán shēngchǎn xǔkě zhèngmíng hé huánjìng bǎohù xǔkě zhèngmíng. | F99: =HYPERLINK("https://youglish.com/pronounce/我们需要您提供商品的安全生产许可证明和环境保护许可证明/chinese","🔍")
A100: 626 ĐPTM.pdf | B100: 99 | C100: 我们需要您提供商品的专利和商标授权证明。 | D100: Chúng tôi cần bạn cung cấp giấy chứng nhận sở hữu trí tuệ và ủy quyền thương hiệu của sản phẩm. Wǒmen xūyào nín tígōng shāngpǐn de zhuānlì hé shāngbiāo shòuquán zhèngmíng. | E100: 99 我们需要您提 供商品的专利 和商标授权证 明。 Chúng tôi cần bạn cung cấp giấy chứng nhận sở hữu trí tuệ và ủy quyền thương hiệu của sản phẩm. Wǒmen xūyào nín tígōng shāngpǐn de zhuānlì hé shāngbiāo shòuquán zhèngmíng. | F100: =HYPERLINK("https://youglish.com/pronounce/我们需要您提供商品的专利和商标授权证明/chinese","🔍")
...

Sheet Thống kê nguồn
A1: 📊 THỐNG KÊ SỐ CÂU/MỤC TRÍCH TỪ NGUỒN NotebookLM
A2: Notebook: Trọn bộ 500 Từ vựng HSK 1 Đầy đủ • Trích xuất: 20260813_001110
A4: STT | B4: Nguồn (PDF) | C4: Số câu/mục | D4: Ghi chú
A5: 1 | B5: 626 ĐPTM.pdf | C5: 646 | D5: Đàm phán TM - đã ghép lại câu bị vỡ dòng (2 cột)
A6: 2 | B6: PDF Tiếng Trung Đàm Phán Thương Mại _ HỌC BÁ CHINESE.pdf | C6: 202 | D6: Câu Hán + Pinyin + Nghĩa
A7: 3 | B7: PDF_Tiếng trung Full BỘ BCT.pdf | C7: 999 | D7: Thuật ngữ PMC/chuỗi cung ứng (Hán+Pinyin+Anh+Việt)
A8: 4 | B8: PDF 300+ Mẫu Câu Giao tiếp theo chủ đề.pdf | C8: 610 | D8: Từ vựng + mẫu câu theo chủ đề
A9: 5 | B9: PDF 500 mẫu câu thông dụng.pdf | C9: 184 | D9: Mẫu câu giao tiếp thông dụng
A10: 6 | B10: PDF_Tổng hợp từ vựng mẫu câ cho NDL.pdf | C10: 177 | D10: Từ vựng + mẫu câu người đi làm
A11: 7 | B11: PDF-Từ vựng phỏng vấn _ HỌC BÁ CHINESE.pdf | C11: 512 | D11: Từ vựng + câu ví dụ phỏng vấn
B12: TỔNG CỘNG | C12: 3330 | D12: 7 nguồn đọc được / 8 nguồn (1 nguồn lỗi, ko đọc được)

Sheet Khẩu ngữ thông dụng
A1: 🗣️ KHẨU NGỮ THÔNG DỤNG TIẾNG TRUNG — 500 câu cửa miệng giao tiếp hằng ngày
A2: STT | B2: 📂 Chủ đề | C2: 🀄 Hán tự | D2: 🔤 Pinyin | E2: 🇻🇳 Nghĩa tiếng Việt | F2: 💬 Cách dùng | G2: 🌐 YOUGLISH
A3: 1 | B3: Cảm thán / Phản ứng | C3: 加油！ | D3: Jiā yóu! | E3: Cố lên! | F3: Động viên | G3: =HYPERLINK("https://youglish.com/pronounce/加油/chinese","🔍")
A4: 2 | B4: Cảm thán / Phản ứng | C4: 太好了！ | D4: Tài hǎo le! | E4: Tuyệt quá! | F4: Vui mừng | G4: =HYPERLINK("https://youglish.com/pronounce/太好了/chinese","🔍")
A5: 3 | B5: Cảm thán / Phản ứng | C5: 真的吗？ | D5: Zhēn de ma? | E5: Thật á? | F5: Ngạc nhiên | G5: =HYPERLINK("https://youglish.com/pronounce/真的吗/chinese","🔍")
A6: 4 | B6: Cảm thán / Phản ứng | C6: 不会吧！ | D6: Bú huì ba! | E6: Không thể nào! | F6: Khó tin | G6: =HYPERLINK("https://youglish.com/pronounce/不会吧/chinese","🔍")
A7: 5 | B7: Cảm thán / Phản ứng | C7: 哎呀！ | D7: Āi yā! | E7: Ối! / Ái chà! | F7: Than, giật mình | G7: =HYPERLINK("https://youglish.com/pronounce/哎呀/chinese","🔍")
A8: 6 | B8: Cảm thán / Phản ứng | C8: 哇！ | D8: Wa! | E8: Wow! | F8: Trầm trồ | G8: =HYPERLINK("https://youglish.com/pronounce/哇/chinese","🔍")
A9: 7 | B9: Cảm thán / Phản ứng | C9: 天哪！ | D9: Tiān nǎ! | E9: Trời ơi! | F9: Kinh ngạc | G9: =HYPERLINK("https://youglish.com/pronounce/天哪/chinese","🔍")
A10: 8 | B10: Cảm thán / Phản ứng | C10: 我的天！ | D10: Wǒ de tiān! | E10: Trời đất ơi! | F10: Kinh ngạc mạnh | G10: =HYPERLINK("https://youglish.com/pronounce/我的天/chinese","🔍")
A11: 9 | B11: Cảm thán / Phản ứng | C11: 完了！ | D11: Wán le! | E11: Toi rồi! | F11: Gặp chuyện xấu | G11: =HYPERLINK("https://youglish.com/pronounce/完了/chinese","🔍")
A12: 10 | B12: Cảm thán / Phản ứng | C12: 糟糕！ | D12: Zāo gāo! | E12: Hỏng bét! | F12: Gặp sự cố | G12: =HYPERLINK("https://youglish.com/pronounce/糟糕/chinese","🔍")
A13: 11 | B13: Cảm thán / Phản ứng | C13: 拜托！ | D13: Bài tuō! | E13: Làm ơn đi! | F13: Nài nỉ, bực | G13: =HYPERLINK("https://youglish.com/pronounce/拜托/chinese","🔍")
A14: 12 | B14: Cảm thán / Phản ứng | C14: 得了吧！ | D14: Dé le ba! | E14: Thôi đi! | F14: Bác bỏ | G14: =HYPERLINK("https://youglish.com/pronounce/得了吧/chinese","🔍")
A15: 13 | B15: Cảm thán / Phản ứng | C15: 我去！ | D15: Wǒ qù! | E15: Ối giời! | F15: Kinh ngạc (khẩu ngữ) | G15: =HYPERLINK("https://youglish.com/pronounce/我去/chinese","🔍")
A16: 14 | B16: Cảm thán / Phản ứng | C16: 哎哟！ | D16: Āi yō! | E16: Ái da! | F16: Đau, bất ngờ | G16: =HYPERLINK("https://youglish.com/pronounce/哎哟/chinese","🔍")
A17: 15 | B17: Cảm thán / Phản ứng | C17: 哼！ | D17: Hēng! | E17: Hừ! | F17: Khinh, giận dỗi | G17: =HYPERLINK("https://youglish.com/pronounce/哼/chinese","🔍")
A18: 16 | B18: Cảm thán / Phản ứng | C18: 啊？ | D18: A? | E18: Hả? | F18: Không nghe rõ | G18: =HYPERLINK("https://youglish.com/pronounce/啊/chinese","🔍")
A19: 17 | B19: Cảm thán / Phản ứng | C19: 咦？ | D19: Yí? | E19: Ơ kìa? | F19: Lạ lùng | G19: =HYPERLINK("https://youglish.com/pronounce/咦/chinese","🔍")
A20: 18 | B20: Cảm thán / Phản ứng | C20: 唉。 | D20: Āi. | E20: Haiz. | F20: Thở dài | G20: =HYPERLINK("https://youglish.com/pronounce/唉/chinese","🔍")
A21: 19 | B21: Cảm thán / Phản ứng | C21: 哈哈！ | D21: Hā hā! | E21: Ha ha! | F21: Cười | G21: =HYPERLINK("https://youglish.com/pronounce/哈哈/chinese","🔍")
A22: 20 | B22: Cảm thán / Phản ứng | C22: 好家伙！ | D22: Hǎo jiā huo! | E22: Chà chà! | F22: Trầm trồ/bất ngờ | G22: =HYPERLINK("https://youglish.com/pronounce/好家伙/chinese","🔍")
A23: 21 | B23: Cảm thán / Phản ứng | C23: 不是吧！ | D23: Bú shì ba! | E23: Lẽ nào! | F23: Khó tin | G23: =HYPERLINK("https://youglish.com/pronounce/不是吧/chinese","🔍")
A24: 22 | B24: Cảm thán / Phản ứng | C24: 我的妈呀！ | D24: Wǒ de mā ya! | E24: Mẹ ơi! | F24: Hoảng | G24: =HYPERLINK("https://youglish.com/pronounce/我的妈呀/chinese","🔍")
A25: 23 | B25: Cảm thán / Phản ứng | C25: 吓我一跳！ | D25: Xià wǒ yī tiào! | E25: Làm tôi giật mình! | F25: Bị hù | G25: =HYPERLINK("https://youglish.com/pronounce/吓我一跳/chinese","🔍")
A26: 24 | B26: Cảm thán / Phản ứng | C26: 可不是嘛！ | D26: Kě bú shì ma! | E26: Chuẩn còn gì! | F26: Đồng tình | G26: =HYPERLINK("https://youglish.com/pronounce/可不是嘛/chinese","🔍")
A27: 25 | B27: Cảm thán / Phản ứng | C27: 就说嘛！ | D27: Jiù shuō ma! | E27: Đã bảo mà! | F27: Được xác nhận | G27: =HYPERLINK("https://youglish.com/pronounce/就说嘛/chinese","🔍")
A28: 26 | B28: Cảm thán / Phản ứng | C28: 服了你了！ | D28: Fú le nǐ le! | E28: Chịu bạn luôn! | F28: Bó tay | G28: =HYPERLINK("https://youglish.com/pronounce/服了你了/chinese","🔍")
A29: 27 | B29: Cảm thán / Phản ứng | C29: 绝了！ | D29: Jué le! | E29: Đỉnh của chóp! | F29: Quá đỉnh | G29: =HYPERLINK("https://youglish.com/pronounce/绝了/chinese","🔍")
A30: 28 | B30: Cảm thán / Phản ứng | C30: 有没有搞错！ | D30: Yǒu méi yǒu gǎo cuò! | E30: Có nhầm không đấy! | F30: Bực/khó tin | G30: =HYPERLINK("https://youglish.com/pronounce/有没有搞错/chinese","🔍")
A31: 29 | B31: Cảm thán / Phản ứng | C31: 搞什么啊！ | D31: Gǎo shén me a! | E31: Làm cái gì vậy! | F31: Bực bội | G31: =HYPERLINK("https://youglish.com/pronounce/搞什么啊/chinese","🔍")
A32: 30 | B32: Cảm thán / Phản ứng | C32: 不敢相信！ | D32: Bù gǎn xiāng xìn! | E32: Không dám tin! | F32: Sốc | G32: =HYPERLINK("https://youglish.com/pronounce/不敢相信/chinese","🔍")
A33: 31 | B33: Đồng ý / Khẳng định | C33: 好的。 | D33: Hǎo de. | E33: Được / OK. | F33: Đồng ý | G33: =HYPERLINK("https://youglish.com/pronounce/好的/chinese","🔍")
A34: 32 | B34: Đồng ý / Khẳng định | C34: 行。 | D34: Xíng. | E34: Được. | F34: Ngắn gọn | G34: =HYPERLINK("https://youglish.com/pronounce/行/chinese","🔍")
A35: 33 | B35: Đồng ý / Khẳng định | C35: 没问题。 | D35: Méi wèn tí. | E35: Không vấn đề gì. | F35: Nhận lời | G35: =HYPERLINK("https://youglish.com/pronounce/没问题/chinese","🔍")
A36: 34 | B36: Đồng ý / Khẳng định | C36: 当然。 | D36: Dāng rán. | E36: Đương nhiên. | F36: Khẳng định | G36: =HYPERLINK("https://youglish.com/pronounce/当然/chinese","🔍")
A37: 35 | B37: Đồng ý / Khẳng định | C37: 没错。 | D37: Méi cuò. | E37: Đúng vậy / Chuẩn. | F37: Xác nhận | G37: =HYPERLINK("https://youglish.com/pronounce/没错/chinese","🔍")
A38: 36 | B38: Đồng ý / Khẳng định | C38: 你说得对。 | D38: Nǐ shuō dé duì. | E38: Bạn nói đúng. | F38: Tán thành | G38: =HYPERLINK("https://youglish.com/pronounce/你说得对/chinese","🔍")
A39: 37 | B39: Đồng ý / Khẳng định | C39: 就这样。 | D39: Jiù zhè yàng. | E39: Cứ vậy đi. | F39: Chốt | G39: =HYPERLINK("https://youglish.com/pronounce/就这样/chinese","🔍")
A40: 38 | B40: Đồng ý / Khẳng định | C40: 听你的。 | D40: Tīng nǐ de. | E40: Nghe theo bạn. | F40: Nhường | G40: =HYPERLINK("https://youglish.com/pronounce/听你的/chinese","🔍")
A41: 39 | B41: Đồng ý / Khẳng định | C41: 我同意。 | D41: Wǒ tóng yì. | E41: Tôi đồng ý. | F41: Tán thành | G41: =HYPERLINK("https://youglish.com/pronounce/我同意/chinese","🔍")
A42: 40 | B42: Đồng ý / Khẳng định | C42: 好主意。 | D42: Hǎo zhǔ yì. | E42: Ý hay đấy. | F42: Khen ý | G42: =HYPERLINK("https://youglish.com/pronounce/好主意/chinese","🔍")
A43: 41 | B43: Đồng ý / Khẳng định | C43: 就是啊！ | D43: Jiù shì a! | E43: Đúng thế! | F43: Đồng tình mạnh | G43: =HYPERLINK("https://youglish.com/pronounce/就是啊/chinese","🔍")
A44: 42 | B44: Đồng ý / Khẳng định | C44: 我也是。 | D44: Wǒ yě shì. | E44: Tôi cũng vậy. | F44: Đồng cảnh | G44: =HYPERLINK("https://youglish.com/pronounce/我也是/chinese","🔍")
A45: 43 | B45: Đồng ý / Khẳng định | C45: 是的。 | D45: Shì de. | E45: Vâng / Đúng. | F45: Xác nhận | G45: =HYPERLINK("https://youglish.com/pronounce/是的/chinese","🔍")
A46: 44 | B46: Đồng ý / Khẳng định | C46: 可以。 | D46: Kě yǐ. | E46: Được đấy. | F46: Chấp thuận | G46: =HYPERLINK("https://youglish.com/pronounce/可以/chinese","🔍")
A47: 45 | B47: Đồng ý / Khẳng định | C47: 一定。 | D47: Yí dìng. | E47: Nhất định. | F47: Cam kết | G47: =HYPERLINK("https://youglish.com/pronounce/一定/chinese","🔍")
A48: 46 | B48: Đồng ý / Khẳng định | C48: 肯定。 | D48: Kěn dìng. | E48: Chắc chắn. | F48: Khẳng định | G48: =HYPERLINK("https://youglish.com/pronounce/肯定/chinese","🔍")
A49: 47 | B49: Đồng ý / Khẳng định | C49: 绝对。 | D49: Jué duì. | E49: Tuyệt đối. | F49: Nhấn mạnh | G49: =HYPERLINK("https://youglish.com/pronounce/绝对/chinese","🔍")
A50: 48 | B50: Đồng ý / Khẳng định | C50: 那当然。 | D50: Nà dāng rán. | E50: Vậy còn phải nói. | F50: Hiển nhiên | G50: =HYPERLINK("https://youglish.com/pronounce/那当然/chinese","🔍")
A51: 49 | B51: Đồng ý / Khẳng định | C51: 有道理。 | D51: Yǒu dào lǐ. | E51: Có lý đấy. | F51: Tán thành | G51: =HYPERLINK("https://youglish.com/pronounce/有道理/chinese","🔍")
A52: 50 | B52: Đồng ý / Khẳng định | C52: 我懂了。 | D52: Wǒ dǒng le. | E52: Tôi hiểu rồi. | F52: Đã hiểu | G52: =HYPERLINK("https://youglish.com/pronounce/我懂了/chinese","🔍")
A53: 51 | B53: Đồng ý / Khẳng định | C53: 知道了。 | D53: Zhī dào le. | E53: Biết rồi. | F53: Tiếp nhận | G53: =HYPERLINK("https://youglish.com/pronounce/知道了/chinese","🔍")
A54: 52 | B54: Đồng ý / Khẳng định | C54: 收到。 | D54: Shōu dào. | E54: Đã nhận / Rõ. | F54: Xác nhận (nhắn tin) | G54: =HYPERLINK("https://youglish.com/pronounce/收到/chinese","🔍")
A55: 53 | B55: Đồng ý / Khẳng định | C55: 好嘞！ | D55: Hǎo lei! | E55: Được ngay! | F55: Vui vẻ nhận lời | G55: =HYPERLINK("https://youglish.com/pronounce/好嘞/chinese","🔍")
A56: 54 | B56: Đồng ý / Khẳng định | C56: 都行。 | D56: Dōu xíng. | E56: Sao cũng được. | F56: Dễ tính | G56: =HYPERLINK("https://youglish.com/pronounce/都行/chinese","🔍")
A57: 55 | B57: Đồng ý / Khẳng định | C57: 完全同意。 | D57: Wán quán tóng yì. | E57: Hoàn toàn đồng ý. | F57: Tán thành mạnh | G57: =HYPERLINK("https://youglish.com/pronounce/完全同意/chinese","🔍")
A58: 56 | B58: Đồng ý / Khẳng định | C58: 我挺你。 | D58: Wǒ tǐng nǐ. | E58: Tôi ủng hộ bạn. | F58: Hậu thuẫn | G58: =HYPERLINK("https://youglish.com/pronounce/我挺你/chinese","🔍")
A59: 57 | B59: Đồng ý / Khẳng định | C59: 就这么定了。 | D59: Jiù zhè me dìng le. | E59: Cứ quyết vậy nhé. | F59: Chốt kèo | G59: =HYPERLINK("https://youglish.com/pronounce/就这么定了/chinese","🔍")
A60: 58 | B60: Đồng ý / Khẳng định | C60: 没意见。 | D60: Méi yì jiàn. | E60: Không ý kiến gì. | F60: Đồng thuận | G60: =HYPERLINK("https://youglish.com/pronounce/没意见/chinese","🔍")
A61: 59 | B61: Đồng ý / Khẳng định | C61: 照办。 | D61: Zhào bàn. | E61: Làm theo vậy. | F61: Tuân theo | G61: =HYPERLINK("https://youglish.com/pronounce/照办/chinese","🔍")
A62: 60 | B62: Đồng ý / Khẳng định | C62: 遵命。 | D62: Zūn mìng. | E62: Xin tuân lệnh. | F62: Đùa/lịch sự | G62: =HYPERLINK("https://youglish.com/pronounce/遵命/chinese","🔍")
A63: 61 | B63: Từ chối / Phản đối | C63: 不行。 | D63: Bù xíng. | E63: Không được. | F63: Từ chối | G63: =HYPERLINK("https://youglish.com/pronounce/不行/chinese","🔍")
A64: 62 | B64: Từ chối / Phản đối | C64: 不用了。 | D64: Bù yòng le. | E64: Không cần đâu. | F64: Nhã nhặn | G64: =HYPERLINK("https://youglish.com/pronounce/不用了/chinese","🔍")
A65: 63 | B65: Từ chối / Phản đối | C65: 算了。 | D65: Suàn le. | E65: Thôi bỏ đi. | F65: Buông | G65: =HYPERLINK("https://youglish.com/pronounce/算了/chinese","🔍")
A66: 64 | B66: Từ chối / Phản đối | C66: 我不想。 | D66: Wǒ bù xiǎng. | E66: Tôi không muốn. | F66: Từ chối | G66: =HYPERLINK("https://youglish.com/pronounce/我不想/chinese","🔍")
A67: 65 | B67: Từ chối / Phản đối | C67: 别这样。 | D67: Bié zhè yàng. | E67: Đừng như vậy. | F67: Ngăn cản | G67: =HYPERLINK("https://youglish.com/pronounce/别这样/chinese","🔍")
A68: 66 | B68: Từ chối / Phản đối | C68: 别闹了。 | D68: Bié nào le. | E68: Thôi nào. | F68: Nhắc nhở | G68: =HYPERLINK("https://youglish.com/pronounce/别闹了/chinese","🔍")
A69: 67 | B69: Từ chối / Phản đối | C69: 少来。 | D69: Shǎo lái. | E69: Thôi đi. | F69: Bác bỏ thân mật | G69: =HYPERLINK("https://youglish.com/pronounce/少来/chinese","🔍")
A70: 68 | B70: Từ chối / Phản đối | C70: 我不管。 | D70: Wǒ bù guǎn. | E70: Tôi mặc kệ. | F70: Không quan tâm | G70: =HYPERLINK("https://youglish.com/pronounce/我不管/chinese","🔍")
A71: 69 | B71: Từ chối / Phản đối | C71: 想得美。 | D71: Xiǎng dé měi. | E71: Đừng mơ. | F71: Bác bỏ hài hước | G71: =HYPERLINK("https://youglish.com/pronounce/想得美/chinese","🔍")
A72: 70 | B72: Từ chối / Phản đối | C72: 门儿都没有。 | D72: Mén ér dōu méi yǒu. | E72: Còn lâu / Đừng hòng. | F72: Dứt khoát | G72: =HYPERLINK("https://youglish.com/pronounce/门儿都没有/chinese","🔍")
A73: 71 | B73: Từ chối / Phản đối | C73: 不要。 | D73: Bú yào. | E73: Không cần. | F73: Từ chối | G73: =HYPERLINK("https://youglish.com/pronounce/不要/chinese","🔍")
A74: 72 | B74: Từ chối / Phản đối | C74: 没门。 | D74: Méi mén. | E74: Không đời nào. | F74: Dứt khoát | G74: =HYPERLINK("https://youglish.com/pronounce/没门/chinese","🔍")
A75: 73 | B75: Từ chối / Phản đối | C75: 不可能。 | D75: Bù kě néng. | E75: Không thể nào. | F75: Phủ định | G75: =HYPERLINK("https://youglish.com/pronounce/不可能/chinese","🔍")
A76: 74 | B76: Từ chối / Phản đối | C76: 我拒绝。 | D76: Wǒ jù jué. | E76: Tôi từ chối. | F76: Rõ ràng | G76: =HYPERLINK("https://youglish.com/pronounce/我拒绝/chinese","🔍")
A77: 75 | B77: Từ chối / Phản đối | C77: 才不要。 | D77: Cái bú yào. | E77: Không thèm. | F77: Bướng | G77: =HYPERLINK("https://youglish.com/pronounce/才不要/chinese","🔍")
A78: 76 | B78: Từ chối / Phản đối | C78: 才怪。 | D78: Cái guài. | E78: Còn lâu mới thế. | F78: Mỉa mai | G78: =HYPERLINK("https://youglish.com/pronounce/才怪/chinese","🔍")
A79: 77 | B79: Từ chối / Phản đối | C79: 胡说。 | D79: Hú shuō. | E79: Nói bậy. | F79: Bác bỏ | G79: =HYPERLINK("https://youglish.com/pronounce/胡说/chinese","🔍")
A80: 78 | B80: Từ chối / Phản đối | C80: 瞎说。 | D80: Xiā shuō. | E80: Nói linh tinh. | F80: Bác bỏ | G80: =HYPERLINK("https://youglish.com/pronounce/瞎说/chinese","🔍")
A81: 79 | B81: Từ chối / Phản đối | C81: 别逗了。 | D81: Bié dòu le. | E81: Đừng đùa nữa. | F81: Không tin | G81: =HYPERLINK("https://youglish.com/pronounce/别逗了/chinese","🔍")
A82: 80 | B82: Từ chối / Phản đối | C82: 没戏。 | D82: Méi xì. | E82: Vô vọng / Toi rồi. | F82: Không có cửa | G82: =HYPERLINK("https://youglish.com/pronounce/没戏/chinese","🔍")
A83: 81 | B83: Từ chối / Phản đối | C83: 免谈。 | D83: Miǎn tán. | E83: Miễn bàn. | F83: Cắt đứt | G83: =HYPERLINK("https://youglish.com/pronounce/免谈/chinese","🔍")
A84: 82 | B84: Từ chối / Phản đối | C84: 拉倒吧。 | D84: Lā dǎo ba. | E84: Thôi dẹp đi. | F84: Bác bỏ | G84: =HYPERLINK("https://youglish.com/pronounce/拉倒吧/chinese","🔍")
A85: 83 | B85: Từ chối / Phản đối | C85: 省省吧。 | D85: Shěng shěng ba. | E85: Thôi tha đi. | F85: Bác bỏ mỉa | G85: =HYPERLINK("https://youglish.com/pronounce/省省吧/chinese","🔍")
A86: 84 | B86: Từ chối / Phản đối | C86: 打住。 | D86: Dǎ zhù. | E86: Dừng lại đó. | F86: Ngắt lời | G86: =HYPERLINK("https://youglish.com/pronounce/打住/chinese","🔍")
A87: 85 | B87: Từ chối / Phản đối | C87: 别说了。 | D87: Bié shuō le. | E87: Đừng nói nữa. | F87: Chặn lời | G87: =HYPERLINK("https://youglish.com/pronounce/别说了/chinese","🔍")
A88: 86 | B88: Từ chối / Phản đối | C88: 我不信。 | D88: Wǒ bù xìn. | E88: Tôi không tin. | F88: Nghi ngờ | G88: =HYPERLINK("https://youglish.com/pronounce/我不信/chinese","🔍")
A89: 87 | B89: Từ chối / Phản đối | C89: 骗人的。 | D89: Piàn rén de. | E89: Xạo đấy. | F89: Không tin | G89: =HYPERLINK("https://youglish.com/pronounce/骗人的/chinese","🔍")
A90: 88 | B90: Từ chối / Phản đối | C90: 鬼才信。 | D90: Guǐ cái xìn. | E90: Ma mới tin. | F90: Không tin | G90: =HYPERLINK("https://youglish.com/pronounce/鬼才信/chinese","🔍")
A91: 89 | B91: Từ chối / Phản đối | C91: 想都别想。 | D91: Xiǎng dōu bié xiǎng. | E91: Đừng có mơ. | F91: Dứt khoát | G91: =HYPERLINK("https://youglish.com/pronounce/想都别想/chinese","🔍")
A92: 90 | B92: Từ chối / Phản đối | C92: 死心吧。 | D92: Sǐ xīn ba. | E92: Thôi chết cái ý đó đi. | F92: Khuyên từ bỏ | G92: =HYPERLINK("https://youglish.com/pronounce/死心吧/chinese","🔍")
A93: 91 | B93: Hỏi thăm / Xã giao | C93: 最近怎么样？ | D93: Zuì jìn zěn me yàng? | E93: Dạo này thế nào? | F93: Hỏi thăm | G93: =HYPERLINK("https://youglish.com/pronounce/最近怎么样/chinese","🔍")
A94: 92 | B94: Hỏi thăm / Xã giao | C94: 吃了吗？ | D94: Chī le ma? | E94: Ăn cơm chưa? | F94: Chào cửa miệng | G94: =HYPERLINK("https://youglish.com/pronounce/吃了吗/chinese","🔍")
A95: 93 | B95: Hỏi thăm / Xã giao | C95: 忙什么呢？ | D95: Máng shén me ne? | E95: Bận gì thế? | F95: Bắt chuyện | G95: =HYPERLINK("https://youglish.com/pronounce/忙什么呢/chinese","🔍")
A96: 94 | B96: Hỏi thăm / Xã giao | C96: 好久不见。 | D96: Hǎo jiǔ bú jiàn. | E96: Lâu rồi không gặp. | F96: Gặp lại | G96: =HYPERLINK("https://youglish.com/pronounce/好久不见/chinese","🔍")
A97: 95 | B97: Hỏi thăm / Xã giao | C97: 怎么了？ | D97: Zěn me le? | E97: Sao thế? | F97: Quan tâm | G97: =HYPERLINK("https://youglish.com/pronounce/怎么了/chinese","🔍")
A98: 96 | B98: Hỏi thăm / Xã giao | C98: 你说呢？ | D98: Nǐ shuō ne? | E98: Bạn thấy sao? | F98: Hỏi ý | G98: =HYPERLINK("https://youglish.com/pronounce/你说呢/chinese","🔍")
A99: 97 | B99: Hỏi thăm / Xã giao | C99: 什么意思？ | D99: Shén me yì si? | E99: Ý là sao? | F99: Hỏi lại | G99: =HYPERLINK("https://youglish.com/pronounce/什么意思/chinese","🔍")
A100: 98 | B100: Hỏi thăm / Xã giao | C100: 明白了吗？ | D100: Míng bái le ma? | E100: Hiểu chưa? | F100: Xác nhận | G100: =HYPERLINK("https://youglish.com/pronounce/明白了吗/chinese","🔍")
...

Sheet business
A1: 💼 TỪ VỰNG THƯƠNG MẠI — BCT 标准教程 1 (Business Chinese Test · Standard Course 1) · 词语表 Appendix IV
A2: STT | B2: 🀄 Hán tự | C2: 🔤 Pinyin | D2: 📝 Từ loại | E2: 🇬🇧 English | F2: 🇻🇳 Nghĩa tiếng Việt | G2: 📖 Bài | H2: 🌐 YOUGLISH
A3: 1 | B3: 啊 | C3: a | D3: int. | E3: used after a sentence to indicate the mood | F3: trợ từ ngữ khí (cuối câu) | G3: 15 | H3: =HYPERLINK("https://youglish.com/pronounce/啊/chinese","🔍")
A4: 2 | B4: 八 | C4: bā | D4: num. | E4: eight | F4: tám | G4: 8 | H4: =HYPERLINK("https://youglish.com/pronounce/八/chinese","🔍")
A5: 3 | B5: 八月 | C5: bāyuè | D5: n. | E5: August | F5: tháng Tám | G5: 10 | H5: =HYPERLINK("https://youglish.com/pronounce/八月/chinese","🔍")
A6: 4 | B6: 吧 | C6: ba | D6: int. | E6: used at the end of a sentence (suggestion/request/mild command) | F6: trợ từ ngữ khí (đề nghị, gợi ý) | G6: 7 | H6: =HYPERLINK("https://youglish.com/pronounce/吧/chinese","🔍")
A7: 5 | B7: 百 | C7: bǎi | D7: num. | E7: hundred | F7: trăm | G7: 14 | H7: =HYPERLINK("https://youglish.com/pronounce/百/chinese","🔍")
A8: 6 | B8: 办公室 | C8: bàngōngshì | D8: n. | E8: office | F8: văn phòng | G8: 11 | H8: =HYPERLINK("https://youglish.com/pronounce/办公室/chinese","🔍")
A9: 7 | B9: 半 | C9: bàn | D9: num. | E9: half | F9: rưỡi; nửa | G9: 8 | H9: =HYPERLINK("https://youglish.com/pronounce/半/chinese","🔍")
A10: 8 | B10: 杯 | C10: bēi | D10: mw. | E10: a cup of (coffee, tea, etc.) | F10: cốc, ly (lượng từ) | G10: 18 | H10: =HYPERLINK("https://youglish.com/pronounce/杯/chinese","🔍")
A11: 9 | B11: 宾馆 | C11: bīnguǎn | D11: n. | E11: hotel | F11: khách sạn | G11: 11 | H11: =HYPERLINK("https://youglish.com/pronounce/宾馆/chinese","🔍")
A12: 10 | B12: 不 | C12: bù | D12: adv. | E12: not; no | F12: không | G12: 4 | H12: =HYPERLINK("https://youglish.com/pronounce/不/chinese","🔍")
A13: 11 | B13: 菜 | C13: cài | D13: n. | E13: dish | F13: món ăn | G13: 18 | H13: =HYPERLINK("https://youglish.com/pronounce/菜/chinese","🔍")
A14: 12 | B14: 餐厅 | C14: cāntīng | D14: n. | E14: restaurant | F14: nhà hàng | G14: 18 | H14: =HYPERLINK("https://youglish.com/pronounce/餐厅/chinese","🔍")
A15: 13 | B15: 层 | C15: céng | D15: mw. | E15: floor; layer | F15: tầng (lượng từ) | G15: 15 | H15: =HYPERLINK("https://youglish.com/pronounce/层/chinese","🔍")
A16: 14 | B16: 茶 | C16: chá | D16: n. | E16: tea | F16: trà | G16: 18 | H16: =HYPERLINK("https://youglish.com/pronounce/茶/chinese","🔍")
A17: 15 | B17: 超市 | C17: chāoshì | D17: n. | E17: supermarket | F17: siêu thị | G17: 19 | H17: =HYPERLINK("https://youglish.com/pronounce/超市/chinese","🔍")
A18: 16 | B18: 吃饭 | C18: chīfàn | D18: v. | E18: have breakfast/lunch/dinner | F18: ăn cơm | G18: 10 | H18: =HYPERLINK("https://youglish.com/pronounce/吃饭/chinese","🔍")
A19: 17 | B19: 出差 | C19: chūchāi | D19: v. | E19: be on a business trip | F19: đi công tác | G19: 7 | H19: =HYPERLINK("https://youglish.com/pronounce/出差/chinese","🔍")
A20: 18 | B20: 出租车 | C20: chūzūchē | D20: n. | E20: taxi | F20: taxi | G20: 14 | H20: =HYPERLINK("https://youglish.com/pronounce/出租车/chinese","🔍")
A21: 19 | B21: 打 | C21: dǎ | D21: v. | E21: make (a call) | F21: gọi (điện thoại) | G21: 13 | H21: =HYPERLINK("https://youglish.com/pronounce/打/chinese","🔍")
A22: 20 | B22: 打印 | C22: dǎyìn | D22: v. | E22: print | F22: in (ấn) | G22: 17 | H22: =HYPERLINK("https://youglish.com/pronounce/打印/chinese","🔍")
A23: 21 | B23: 到 | C23: dào | D23: v. | E23: arrive; reach | F23: đến; tới | G23: 14 | H23: =HYPERLINK("https://youglish.com/pronounce/到/chinese","🔍")
A24: 22 | B24: 的 | C24: de | D24: part. | E24: of (marker of attributive) | F24: trợ từ (định ngữ) | G24: 3 | H24: =HYPERLINK("https://youglish.com/pronounce/的/chinese","🔍")
A25: 23 | B25: 第一 | C25: dìyī | D25: num. | E25: the first | F25: thứ nhất | G25: 16 | H25: =HYPERLINK("https://youglish.com/pronounce/第一/chinese","🔍")
A26: 24 | B26: 点 | C26: diǎn | D26: n. | E26: o'clock | F26: giờ (đúng) | G26: 8 | H26: =HYPERLINK("https://youglish.com/pronounce/点/chinese","🔍")
A27: 25 | B27: 点 | C27: diǎn | D27: v. | E27: order | F27: gọi món; đặt món | G27: 18 | H27: =HYPERLINK("https://youglish.com/pronounce/点/chinese","🔍")
A28: 26 | B28: 电话 | C28: diànhuà | D28: n. | E28: phone | F28: điện thoại | G28: 13 | H28: =HYPERLINK("https://youglish.com/pronounce/电话/chinese","🔍")
A29: 27 | B29: 电脑 | C29: diànnǎo | D29: n. | E29: computer | F29: máy tính | G29: 17 | H29: =HYPERLINK("https://youglish.com/pronounce/电脑/chinese","🔍")
A30: 28 | B30: 电梯 | C30: diàntī | D30: n. | E30: elevator; lift | F30: thang máy | G30: 15 | H30: =HYPERLINK("https://youglish.com/pronounce/电梯/chinese","🔍")
A31: 29 | B31: 订 | C31: dìng | D31: v. | E31: book; reserve | F31: đặt; đặt trước | G31: 20 | H31: =HYPERLINK("https://youglish.com/pronounce/订/chinese","🔍")
A32: 30 | B32: 对不起 | C32: duìbuqǐ | D32: v. | E32: I'm sorry. | F32: xin lỗi | G32: 6 | H32: =HYPERLINK("https://youglish.com/pronounce/对不起/chinese","🔍")
A33: 31 | B33: 多少 | C33: duōshao | D33: pron. | E33: how many; how much | F33: bao nhiêu | G33: 13 | H33: =HYPERLINK("https://youglish.com/pronounce/多少/chinese","🔍")
A34: 32 | B34: 二 | C34: èr | D34: num. | E34: two | F34: hai | G34: 7 | H34: =HYPERLINK("https://youglish.com/pronounce/二/chinese","🔍")
A35: 33 | B35: 二月 | C35: èryuè | D35: n. | E35: February | F35: tháng Hai | G35: 10 | H35: =HYPERLINK("https://youglish.com/pronounce/二月/chinese","🔍")
A36: 34 | B36: 房间 | C36: fángjiān | D36: n. | E36: room | F36: căn phòng | G36: 11 | H36: =HYPERLINK("https://youglish.com/pronounce/房间/chinese","🔍")
A37: 35 | B37: 飞机 | C37: fēijī | D37: n. | E37: plane | F37: máy bay | G37: 8 | H37: =HYPERLINK("https://youglish.com/pronounce/飞机/chinese","🔍")
A38: 36 | B38: 服务员 | C38: fúwùyuán | D38: n. | E38: attendant; waiter; waitress | F38: nhân viên phục vụ | G38: 18 | H38: =HYPERLINK("https://youglish.com/pronounce/服务员/chinese","🔍")
A39: 37 | B39: 干杯 | C39: gānbēi | D39: v. | E39: cheers | F39: cạn ly | G39: 18 | H39: =HYPERLINK("https://youglish.com/pronounce/干杯/chinese","🔍")
A40: 38 | B40: 高兴 | C40: gāoxìng | D40: adj. | E40: happy; glad; cheerful; pleased | F40: vui mừng | G40: 2 | H40: =HYPERLINK("https://youglish.com/pronounce/高兴/chinese","🔍")
A41: 39 | B41: 个 | C41: gè | D41: mw. | E41: used with nouns without specific measure words | F41: cái (lượng từ chung) | G41: 5 | H41: =HYPERLINK("https://youglish.com/pronounce/个/chinese","🔍")
A42: 40 | B42: 给 | C42: gěi | D42: prep./v. | E42: for; hand over; give | F42: cho; đưa | G42: 13 | H42: =HYPERLINK("https://youglish.com/pronounce/给/chinese","🔍")
A43: 41 | B43: 工作 | C43: gōngzuò | D43: v. | E43: work | F43: làm việc; công việc | G43: 3 | H43: =HYPERLINK("https://youglish.com/pronounce/工作/chinese","🔍")
A44: 42 | B44: 公司 | C44: gōngsī | D44: n. | E44: company; firm | F44: công ty | G44: 2 | H44: =HYPERLINK("https://youglish.com/pronounce/公司/chinese","🔍")
A45: 43 | B45: 贵 | C45: guì | D45: adj. | E45: (respectful, when asking name/age) | F45: quý (kính ngữ khi hỏi tên/tuổi) | G45: 3 | H45: =HYPERLINK("https://youglish.com/pronounce/贵/chinese","🔍")
A46: 44 | B46: 贵 | C46: guì | D46: adj. | E46: expensive; costly | F46: đắt | G46: 14 | H46: =HYPERLINK("https://youglish.com/pronounce/贵/chinese","🔍")
A47: 45 | B47: 国家 | C47: guójiā | D47: n. | E47: country | F47: quốc gia; đất nước | G47: 5 | H47: =HYPERLINK("https://youglish.com/pronounce/国家/chinese","🔍")
A48: 46 | B48: 韩国 | C48: Hánguó | D48: n. | E48: South Korea | F48: Hàn Quốc | G48: 5 | H48: =HYPERLINK("https://youglish.com/pronounce/韩国/chinese","🔍")
A49: 47 | B49: 汉语 | C49: Hànyǔ | D49: n. | E49: Chinese language | F49: tiếng Hán; tiếng Trung | G49: 5 | H49: =HYPERLINK("https://youglish.com/pronounce/汉语/chinese","🔍")
A50: 48 | B50: 好 | C50: hǎo | D50: a. | E50: good; nice; well; fine | F50: tốt; khỏe | G50: 1 | H50: =HYPERLINK("https://youglish.com/pronounce/好/chinese","🔍")
A51: 49 | B51: 好吃 | C51: hǎochī | D51: adj. | E51: delicious | F51: ngon | G51: 18 | H51: =HYPERLINK("https://youglish.com/pronounce/好吃/chinese","🔍")
A52: 50 | B52: 好久 | C52: hǎojiǔ | D52: adj. | E52: long time | F52: (đã) lâu | G52: 4 | H52: =HYPERLINK("https://youglish.com/pronounce/好久/chinese","🔍")
A53: 51 | B53: 号 | C53: hào | D53: n. | E53: date | F53: ngày (trong tháng) | G53: 10 | H53: =HYPERLINK("https://youglish.com/pronounce/号/chinese","🔍")
A54: 52 | B54: 号码 | C54: hàomǎ | D54: n. | E54: number | F54: số (hiệu) | G54: 13 | H54: =HYPERLINK("https://youglish.com/pronounce/号码/chinese","🔍")
A55: 53 | B55: 喝 | C55: hē | D55: v. | E55: drink | F55: uống | G55: 18 | H55: =HYPERLINK("https://youglish.com/pronounce/喝/chinese","🔍")
A56: 54 | B56: 和 | C56: hé | D56: prep./conj. | E56: with; and | F56: và; với | G56: 10 | H56: =HYPERLINK("https://youglish.com/pronounce/和/chinese","🔍")
A57: 55 | B57: 很 | C57: hěn | D57: adv. | E57: very | F57: rất | G57: 2 | H57: =HYPERLINK("https://youglish.com/pronounce/很/chinese","🔍")
A58: 56 | B58: 后面 | C58: hòumiàn | D58: n. | E58: behind; at the back; in the rear | F58: phía sau | G58: 16 | H58: =HYPERLINK("https://youglish.com/pronounce/后面/chinese","🔍")
A59: 57 | B59: 护照 | C59: hùzhào | D59: n. | E59: passport | F59: hộ chiếu | G59: 11 | H59: =HYPERLINK("https://youglish.com/pronounce/护照/chinese","🔍")
A60: 58 | B60: 欢迎 | C60: huānyíng | D60: v. | E60: welcome | F60: hoan nghênh; chào mừng | G60: 2 | H60: =HYPERLINK("https://youglish.com/pronounce/欢迎/chinese","🔍")
A61: 59 | B61: 回 | C61: huí | D61: v. | E61: go back | F61: về; quay về | G61: 7 | H61: =HYPERLINK("https://youglish.com/pronounce/回/chinese","🔍")
A62: 60 | B62: 会议 | C62: huìyì | D62: n. | E62: meeting | F62: hội nghị; cuộc họp | G62: 7 | H62: =HYPERLINK("https://youglish.com/pronounce/会议/chinese","🔍")
A63: 61 | B63: 机场 | C63: jīchǎng | D63: n. | E63: airport | F63: sân bay | G63: 14 | H63: =HYPERLINK("https://youglish.com/pronounce/机场/chinese","🔍")
A64: 62 | B64: 几 | C64: jǐ | D64: pron. | E64: how many | F64: mấy; bao nhiêu | G64: 7 | H64: =HYPERLINK("https://youglish.com/pronounce/几/chinese","🔍")
A65: 63 | B65: 见 | C65: jiàn | D65: v. | E65: see | F65: gặp; thấy | G65: 4 | H65: =HYPERLINK("https://youglish.com/pronounce/见/chinese","🔍")
A66: 64 | B66: 见面 | C66: jiànmiàn | D66: v. | E66: meet | F66: gặp mặt | G66: 12 | H66: =HYPERLINK("https://youglish.com/pronounce/见面/chinese","🔍")
A67: 65 | B67: 叫 | C67: jiào | D67: v. | E67: be called; be named | F67: gọi là; tên là | G67: 3 | H67: =HYPERLINK("https://youglish.com/pronounce/叫/chinese","🔍")
A68: 66 | B68: 介绍 | C68: jièshào | D68: v. | E68: introduce | F68: giới thiệu | G68: 3 | H68: =HYPERLINK("https://youglish.com/pronounce/介绍/chinese","🔍")
A69: 67 | B69: 今天 | C69: jīntiān | D69: n. | E69: today | F69: hôm nay | G69: 7 | H69: =HYPERLINK("https://youglish.com/pronounce/今天/chinese","🔍")
A70: 68 | B70: 进 | C70: jìn | D70: v. | E70: enter | F70: vào | G70: 2 | H70: =HYPERLINK("https://youglish.com/pronounce/进/chinese","🔍")
A71: 69 | B71: 经理 | C71: jīnglǐ | D71: n. | E71: manager | F71: giám đốc; quản lý | G71: 3 | H71: =HYPERLINK("https://youglish.com/pronounce/经理/chinese","🔍")
A72: 70 | B72: 九 | C72: jiǔ | D72: num. | E72: nine | F72: chín | G72: 8 | H72: =HYPERLINK("https://youglish.com/pronounce/九/chinese","🔍")
A73: 71 | B73: 九月 | C73: jiǔyuè | D73: n. | E73: September | F73: tháng Chín | G73: 10 | H73: =HYPERLINK("https://youglish.com/pronounce/九月/chinese","🔍")
A74: 72 | B74: 咖啡 | C74: kāfēi | D74: n. | E74: coffee | F74: cà phê | G74: 17 | H74: =HYPERLINK("https://youglish.com/pronounce/咖啡/chinese","🔍")
A75: 73 | B75: 开会 | C75: kāihuì | D75: v. | E75: have a meeting | F75: họp | G75: 8 | H75: =HYPERLINK("https://youglish.com/pronounce/开会/chinese","🔍")
A76: 74 | B76: 看 | C76: kàn | D76: v. | E76: look; watch | F76: xem; nhìn | G76: 10 | H76: =HYPERLINK("https://youglish.com/pronounce/看/chinese","🔍")
A77: 75 | B77: 可以 | C77: kěyǐ | D77: aux. | E77: can; may | F77: có thể; được | G77: 7 | H77: =HYPERLINK("https://youglish.com/pronounce/可以/chinese","🔍")
A78: 76 | B78: 客气 | C78: kèqi | D78: adj. | E78: polite; courteous | F78: khách sáo | G78: 11 | H78: =HYPERLINK("https://youglish.com/pronounce/客气/chinese","🔍")
A79: 77 | B79: 块 | C79: kuài | D79: mw. | E79: kuai, RMB yuan | F79: đồng (tệ, khẩu ngữ) | G79: 14 | H79: =HYPERLINK("https://youglish.com/pronounce/块/chinese","🔍")
A80: 78 | B80: 来 | C80: lái | D80: v. | E80: come | F80: đến | G80: 2 | H80: =HYPERLINK("https://youglish.com/pronounce/来/chinese","🔍")
A81: 79 | B81: 来 | C81: lái | D81: v. | E81: used to indicate some action | F81: (dùng thay động từ chỉ động tác) | G81: 18 | H81: =HYPERLINK("https://youglish.com/pronounce/来/chinese","🔍")
A82: 80 | B82: 了 | C82: le | D82: part. | E82: indicates completed action / change of status | F82: trợ từ (hoàn thành / thay đổi) | G82: 6 | H82: =HYPERLINK("https://youglish.com/pronounce/了/chinese","🔍")
A83: 81 | B83: 冷 | C83: lěng | D83: adj. | E83: cold | F83: lạnh | G83: 7 | H83: =HYPERLINK("https://youglish.com/pronounce/冷/chinese","🔍")
A84: 82 | B84: 两 | C84: liǎng | D84: num. | E84: two | F84: hai | G84: 8 | H84: =HYPERLINK("https://youglish.com/pronounce/两/chinese","🔍")
A85: 83 | B85: 辆 | C85: liàng | D85: mw. | E85: used for automobiles | F85: chiếc (xe) (lượng từ) | G85: 14 | H85: =HYPERLINK("https://youglish.com/pronounce/辆/chinese","🔍")
A86: 84 | B86: 零 | C86: líng | D86: num. | E86: zero | F86: không (số 0) | G86: 11 | H86: =HYPERLINK("https://youglish.com/pronounce/零/chinese","🔍")
